Workbook

Sheet Risk Register
E3: Africa CDC Risk Management Register - 2026
B5: Business Unit | C5: Enterprise Risk Theme | D5: Risk Name | E5: Risk Consequence | F5: Root Causes | G5: Risk Type | H5: Likelihood (L) of Risk happening | I5: Score of Likelihood | J5: Impact (I) if Risk happens | K5: Score of Impact | L5: Inherent Risk Score | M5: Mitigation | N5: Management Response | O5: Timeline | P5: Status Update | Q5: Responsible Owner | R5: Action Update | S5: Date of Update | T5: Status Update (colunm N) verified by Africa CDC OIO | U5: Inherent Risk Rating | V5: Mitigation Effectiveness (reviewer assessed) | W5: Residual Likelihood Score | X5: Residual Impact Score | Y5: Residual Risk Score | Z5: Residual Risk Rating | AA5: Risk Movement (Inherent to Residual) | AB5: Rank Helper (Residual, do not edit)
A6: =1 -> 1 | B6: PHC/CHSHP | C6: 2. Workforce sustainability and institutional capability | D6: Short-term contracts for staff with a duration of less than a year and limited forecasting on the renewal plan | E6: If more than 75% of staff have contracts of less than 1 year, then the division faces serious operational disruptions, failure to implement planned activities and impacts on strategic growth of the organization | F6: 1. An absence of comprehensive long-term staffing plan can lead to reliance on short-term contracts without clear renewal strategies. 2. This may stem from project-based staff recruitments, 3. Inadequate HR forecasting of staff needs 4. Short-term project-based programming, which is not sustainable 5. Budget constraints, or a reactive approach to staffing needs that is not matched to the organizational structure. | G6: Operational | H6: Certain | I6: =IFERROR(IF(H6="Unlikely",1,IF(H6="Possible",2,IF(H6="Likely",3,IF(H6="Almost Certain",4,IF(H6="Certain",5,""))))),"") -> 5 | J6: Critical | K6: =IFERROR(IF(J6="Negligible",1,IF(J6="Minor",2,IF(J6="Moderate",3,IF(J6="Major",4,IF(J6="Critical",5,""))))),"") -> 5 | L6: =IF(OR(I6="",K6=""),"",I6*K6) -> 25 | M6: 1. Develop a comprehensive staffing plan that is mapped to available resources, with a clear renewal plan in place. 2. Provide fixed-term contracts with a one-year duration or longer-term contracts, to align with the assumption of duty 3. Create a LOE mechanism across various grants to avoid reliance on the Staff Costs on one funding mechanism, or diversify funding options | O6: 45930 | P6: Open - Extended | Q6: PHC Head of Division HR Senior Leadership | U6: =IF(L6="","",IF(L6<=4,"Low",IF(L6<=9,"Medium",IF(L6<=15,"High","Critical")))) -> Critical | W6: =IF(I6="","",MAX(1,I6-(IF(V6="Limited",1,IF(V6="Partial",2,IF(V6="Substantial",3,IF(V6="Highly Effective",4,0))))))) -> 5 | X6: =IF(K6="","",MAX(1,K6-ROUNDDOWN((IF(V6="Limited",1,IF(V6="Partial",2,IF(V6="Substantial",3,IF(V6="Highly Effective",4,0)))))/2,0))) -> 5 | Y6: =IF(OR(W6="",X6=""),"",W6*X6) -> 25 | Z6: =IF(Y6="","",IF(Y6<=4,"Low",IF(Y6<=9,"Medium",IF(Y6<=15,"High","Critical")))) -> Critical | AA6: =IF(OR(L6="",Y6=""),"",IF(Y6<L6,"Reduced by "&(L6-Y6)&" pts",IF(Y6=L6,"No Change","Increased by "&(Y6-L6)&" pts"))) -> No Change | AB6: =IF(Y6="","",Y6+(ROW()/10000000)) -> 25.000001
A7: =1+1 -> 2 | B7: PHC/CHSHP | C7: 1. Sustainable financing and resource mobilization | D7: Inadequate funding for programme implementation | E7: If the centre/division has inadequate funding for programme implementation, then the organisation will not be able to deliver on its mandate, thereby damaging the organisation's reputation | F7: 1. Lack of comprehensive financial planning that accurately estimates the funding needed for the entire program lifecycle. 2. Ineffective proposal writing or failure to meet funding application requirements, resulting in unsuccessful grant applications. 3. Insufficient divisional or organizational budget due to competing priorities or budget cuts. 4. Poor forecasting or planning that underestimates the actual funding needs. 5. Dependence on unreliable or unpredictable funding sources such as grants. 6. Misallocation of funds or delays in disbursing available resources. 7. Over-reliance on a single funding stream makes the organization vulnerable to funding cuts | G7: Reputational | H7: Almost Certain | I7: =IFERROR(IF(H7="Unlikely",1,IF(H7="Possible",2,IF(H7="Likely",3,IF(H7="Almost Certain",4,IF(H7="Certain",5,""))))),"") -> 4 | J7: Critical | K7: =IFERROR(IF(J7="Negligible",1,IF(J7="Minor",2,IF(J7="Moderate",3,IF(J7="Major",4,IF(J7="Critical",5,""))))),"") -> 5 | L7: =IF(OR(I7="",K7=""),"",I7*K7) -> 20 | M7: 1. Conduct thorough needs assessments and realistic budgeting, including implementing rolling forecasts to adapt to changing contexts. 2. Diversify funding sources through strengthening partnerships, sponsorships, and relationships with a broader range of donors and stakeholders. 3. Improve financial management through regular financial monitoring and reporting to ensure efficient use of resources. Also, identify and eliminate waste or inefficiencies. 4. Build strong relationships to secure ongoing support 5. Ensure transparency and accountability to build trust with funders. 6. Leverage technology and innovation for effective use digital tools for efficient programme management and reporting | O7: 45930 | P7: Open - Extended | Q7: PHC Center Director Head of Division | U7: =IF(L7="","",IF(L7<=4,"Low",IF(L7<=9,"Medium",IF(L7<=15,"High","Critical")))) -> Critical | W7: =IF(I7="","",MAX(1,I7-(IF(V7="Limited",1,IF(V7="Partial",2,IF(V7="Substantial",3,IF(V7="Highly Effective",4,0))))))) -> 4 | X7: =IF(K7="","",MAX(1,K7-ROUNDDOWN((IF(V7="Limited",1,IF(V7="Partial",2,IF(V7="Substantial",3,IF(V7="Highly Effective",4,0)))))/2,0))) -> 5 | Y7: =IF(OR(W7="",X7=""),"",W7*X7) -> 20 | Z7: =IF(Y7="","",IF(Y7<=4,"Low",IF(Y7<=9,"Medium",IF(Y7<=15,"High","Critical")))) -> Critical | AA7: =IF(OR(L7="",Y7=""),"",IF(Y7<L7,"Reduced by "&(L7-Y7)&" pts",IF(Y7=L7,"No Change","Increased by "&(Y7-L7)&" pts"))) -> No Change | AB7: =IF(Y7="","",Y7+(ROW()/10000000)) -> 20.000001
A8: =1+2 -> 3 | B8: PHC/CHSHP | C8: 2. Workforce sustainability and institutional capability | D8: Loss of institutional memory and capacity | E8: If there are frequent resignations or attrition of experienced personnel, coupled with an informal knowledge transfer mechanism and limited knowledge management practices, then there will be a loss of institutional memory, which may lead to inadequate productivity and increased operational costs | F8: 1. Lack of effective staff retention strategies 2. Informal or nonexistent knowledge transfer protocols 3. Limited or poorly implemented knowledge management systems 4. Organizational culture that does not prioritize knowledge sharing | G8: Operational | H8: Likely | I8: =IFERROR(IF(H8="Unlikely",1,IF(H8="Possible",2,IF(H8="Likely",3,IF(H8="Almost Certain",4,IF(H8="Certain",5,""))))),"") -> 3 | J8: Major | K8: =IFERROR(IF(J8="Negligible",1,IF(J8="Minor",2,IF(J8="Moderate",3,IF(J8="Major",4,IF(J8="Critical",5,""))))),"") -> 4 | L8: =IF(OR(I8="",K8=""),"",I8*K8) -> 12 | M8: 1. Promote a positive, inclusive, and engaging workplace culture. 2. Document roles, responsibilities, and critical knowledge during onboarding and exit interviews. 3. Implement Knowledge Management Systems such as centralized knowledge repositories like intranet, shared drives, or specialized knowledge management software to store institutional knowledge together with collaboration tools like SharePoint, for ongoing knowledge sharing. 4. Foster a culture of knowledge sharing to promote transparency and collaboration. | O8: 45930 | P8: Open - Extended | Q8: PHC Centre Director Head of Division | U8: =IF(L8="","",IF(L8<=4,"Low",IF(L8<=9,"Medium",IF(L8<=15,"High","Critical")))) -> High | W8: =IF(I8="","",MAX(1,I8-(IF(V8="Limited",1,IF(V8="Partial",2,IF(V8="Substantial",3,IF(V8="Highly Effective",4,0))))))) -> 3 | X8: =IF(K8="","",MAX(1,K8-ROUNDDOWN((IF(V8="Limited",1,IF(V8="Partial",2,IF(V8="Substantial",3,IF(V8="Highly Effective",4,0)))))/2,0))) -> 4 | Y8: =IF(OR(W8="",X8=""),"",W8*X8) -> 12 | Z8: =IF(Y8="","",IF(Y8<=4,"Low",IF(Y8<=9,"Medium",IF(Y8<=15,"High","Critical")))) -> High | AA8: =IF(OR(L8="",Y8=""),"",IF(Y8<L8,"Reduced by "&(L8-Y8)&" pts",IF(Y8=L8,"No Change","Increased by "&(Y8-L8)&" pts"))) -> No Change | AB8: =IF(Y8="","",Y8+(ROW()/10000000)) -> 12.000001
A9: 4 | B9: PHC/CHSHP | C9: 4. Program execution and delivery | D9: Inadequate internal programmatic alignment to the overall PHC structure & silo implementation | E9: If there is inadequate internal programmatic alignment with the overall PHC structure, then there will be duplication of efforts, verticalisation, and fragmentation of support to member states, which increases administrative costs and undermines the effectiveness of the PHC centre to demonstrate results towards achievement of the African Continental targets | F9: 1. Lack of interdisciplinary teamwork and shared objectives 2. Divisions/ Units/ Teams operate in silo, with limited coordination, collaboration, integrated strategies undermining the integrated PHC approach | G9: Strategic | H9: Likely | I9: =IFERROR(IF(H9="Unlikely",1,IF(H9="Possible",2,IF(H9="Likely",3,IF(H9="Almost Certain",4,IF(H9="Certain",5,""))))),"") -> 3 | J9: Critical | K9: =IFERROR(IF(J9="Negligible",1,IF(J9="Minor",2,IF(J9="Moderate",3,IF(J9="Major",4,IF(J9="Critical",5,""))))),"") -> 5 | L9: =IF(OR(I9="",K9=""),"",I9*K9) -> 15 | M9: 1. Create a comprehensive strategic plan that clearly links all units’ activities to the overarching goals and targets 2. Joint Planning, Regular Meetings, Joint Reviews, Shared Platforms, and Reporting Systems to foster collaboration, transparency, coordination and accountability 3. Regularly assess activities for overlaps, gaps, and alignment; use findings to adjust strategies and budgets that support integrated activities rather than fragmented efforts. | O9: 45930 | P9: Open - Extended | Q9: PHC Centre Director | U9: =IF(L9="","",IF(L9<=4,"Low",IF(L9<=9,"Medium",IF(L9<=15,"High","Critical")))) -> High | W9: =IF(I9="","",MAX(1,I9-(IF(V9="Limited",1,IF(V9="Partial",2,IF(V9="Substantial",3,IF(V9="Highly Effective",4,0))))))) -> 3 | X9: =IF(K9="","",MAX(1,K9-ROUNDDOWN((IF(V9="Limited",1,IF(V9="Partial",2,IF(V9="Substantial",3,IF(V9="Highly Effective",4,0)))))/2,0))) -> 5 | Y9: =IF(OR(W9="",X9=""),"",W9*X9) -> 15 | Z9: =IF(Y9="","",IF(Y9<=4,"Low",IF(Y9<=9,"Medium",IF(Y9<=15,"High","Critical")))) -> High | AA9: =IF(OR(L9="",Y9=""),"",IF(Y9<L9,"Reduced by "&(L9-Y9)&" pts",IF(Y9=L9,"No Change","Increased by "&(Y9-L9)&" pts"))) -> No Change | AB9: =IF(Y9="","",Y9+(ROW()/10000000)) -> 15.000001
A10: 5 | B10: PHC/CHSHP | C10: 3. Fiduciary stewardship and internal control | D10: Delays in disbursements of funds for the implementation of activities due to several approval levels and the absence of approval thresholds | E10: If there are delays in disbursement of funds, then there will be delayed implementation of planned activities which may result in failure to meet promised targets, leading to organizational reputation risk and reduced funding opportunities | F10: Multiple approval layers or hierarchical review stages that slow down the disbursement process due to a lack of clear delegation of authority, leading to delays in decision-making | G10: Reputational | H10: Almost Certain | I10: =IFERROR(IF(H10="Unlikely",1,IF(H10="Possible",2,IF(H10="Likely",3,IF(H10="Almost Certain",4,IF(H10="Certain",5,""))))),"") -> 4 | J10: Critical | K10: =IFERROR(IF(J10="Negligible",1,IF(J10="Minor",2,IF(J10="Moderate",3,IF(J10="Major",4,IF(J10="Critical",5,""))))),"") -> 5 | L10: =IF(OR(I10="",K10=""),"",I10*K10) -> 20 | M10: 1. Establish a clear Delegation of Authority (DoA) Framework,clearly specifying approval limits based on transaction size and risk level. Map out who can approve what to reduce unnecessary layers. Document authority levels and ensure all parties understand their decision-making scope. 2. Strengthen Automated Workflow and Approval Systems for workflow routing of approval requests based on predefined DoA, and set automatic escalation protocols with real-time tracking for transparency and quick identification of approval delays 3. Set Key Performance Indicators (KPIs) and Accountability to track approval turnaround times and hold approvers accountable for unnecessary delays to foster responsibility 4. Enhance the existing Rapid-Approval Protocol for quick approval pathways of urgent disbursements to prevent reputational damage | O10: 45930 | P10: Open - Extended | Q10: Senior Leadership | U10: =IF(L10="","",IF(L10<=4,"Low",IF(L10<=9,"Medium",IF(L10<=15,"High","Critical")))) -> Critical | W10: =IF(I10="","",MAX(1,I10-(IF(V10="Limited",1,IF(V10="Partial",2,IF(V10="Substantial",3,IF(V10="Highly Effective",4,0))))))) -> 4 | X10: =IF(K10="","",MAX(1,K10-ROUNDDOWN((IF(V10="Limited",1,IF(V10="Partial",2,IF(V10="Substantial",3,IF(V10="Highly Effective",4,0)))))/2,0))) -> 5 | Y10: =IF(OR(W10="",X10=""),"",W10*X10) -> 20 | Z10: =IF(Y10="","",IF(Y10<=4,"Low",IF(Y10<=9,"Medium",IF(Y10<=15,"High","Critical")))) -> Critical | AA10: =IF(OR(L10="",Y10=""),"",IF(Y10<L10,"Reduced by "&(L10-Y10)&" pts",IF(Y10=L10,"No Change","Increased by "&(Y10-L10)&" pts"))) -> No Change | AB10: =IF(Y10="","",Y10+(ROW()/10000000)) -> 20.000001
A11: 6 | B11: PHC/CHSHP | C11: 1. Sustainable financing and resource mobilization | D11: Impact of ODA Cuts on community health initiatives on the African continent | E11: If recent geopolitical shifts and changing donor priorities continue, then it will lead to significant cuts in ODA allocated to health programs, this reduction results in decreased funding for community health initiatives. | F11: 1. Changes in donor countries' political priorities or economic downturns can lead to reduced ODA budgets, including the diversion of funding away from health initiatives due to geopolitical conflicts. 2. Limited domestic resources and weak fiscal capacity in recipient countries make them heavily reliant on ODA for community health programs, which is compounded by a lack of sustainable financing mechanisms within member states. 3. Donor agencies often set priorities based on their strategic interests, which may not align with local health needs 4. Poor integration of community health services into national health systems, making programs vulnerable when external funding decreases. | G11: Contextual | H11: Almost Certain | I11: =IFERROR(IF(H11="Unlikely",1,IF(H11="Possible",2,IF(H11="Likely",3,IF(H11="Almost Certain",4,IF(H11="Certain",5,""))))),"") -> 4 | J11: Critical | K11: =IFERROR(IF(J11="Negligible",1,IF(J11="Minor",2,IF(J11="Moderate",3,IF(J11="Major",4,IF(J11="Critical",5,""))))),"") -> 5 | L11: =IF(OR(I11="",K11=""),"",I11*K11) -> 20 | M11: 1. Encourage governments to increase domestic budget allocations for health, including innovative financing mechanisms like health taxes to fund CH initiatives 2. Continue advocacy on embedding community health initiatives into national health systems to ensure continuity regardless of external funding fluctuations and shift investment to local health workforce training, infrastructure, and supply chains to improve self-sufficiency 3. Diversify Funding Sources and Donor Engagement for funding from a variety of sources, including the private sector, philanthropic organizations, and regional bodies & forster multi-stakeholder coordination, including rebranding the strategic approach | O11: 45930 | P11: Open - Extended | Q11: PHC Centre Director | U11: =IF(L11="","",IF(L11<=4,"Low",IF(L11<=9,"Medium",IF(L11<=15,"High","Critical")))) -> Critical | W11: =IF(I11="","",MAX(1,I11-(IF(V11="Limited",1,IF(V11="Partial",2,IF(V11="Substantial",3,IF(V11="Highly Effective",4,0))))))) -> 4 | X11: =IF(K11="","",MAX(1,K11-ROUNDDOWN((IF(V11="Limited",1,IF(V11="Partial",2,IF(V11="Substantial",3,IF(V11="Highly Effective",4,0)))))/2,0))) -> 5 | Y11: =IF(OR(W11="",X11=""),"",W11*X11) -> 20 | Z11: =IF(Y11="","",IF(Y11<=4,"Low",IF(Y11<=9,"Medium",IF(Y11<=15,"High","Critical")))) -> Critical | AA11: =IF(OR(L11="",Y11=""),"",IF(Y11<L11,"Reduced by "&(L11-Y11)&" pts",IF(Y11=L11,"No Change","Increased by "&(Y11-L11)&" pts"))) -> No Change | AB11: =IF(Y11="","",Y11+(ROW()/10000000)) -> 20.000001
A12: 7 | B12: PHC/IDDS | C12: 5. Country, partner, and geopolitical context | D12: Member states become non-collaborative after Africa CDC shows no responses to their request for assistance | E12: If the Division is not capable to respond to various requests outside of the donor mandated activities, then this could affect the credibilty of the organization with regard to his goal and commitment | F12: Insufficient resource mobilization Insufficient workforce in the division | G12: Reputational | H12: Certain | I12: =IFERROR(IF(H12="Unlikely",1,IF(H12="Possible",2,IF(H12="Likely",3,IF(H12="Almost Certain",4,IF(H12="Certain",5,""))))),"") -> 5 | J12: Critical | K12: =IFERROR(IF(J12="Negligible",1,IF(J12="Minor",2,IF(J12="Moderate",3,IF(J12="Major",4,IF(J12="Critical",5,""))))),"") -> 5 | L12: =IF(OR(I12="",K12=""),"",I12*K12) -> 25 | M12: Diversified and expanded resource mobilization to support long term implementation of integrated activities | O12: 45930 | P12: Open - Extended | Q12: Center Director at PHC/ Human Resource vision | U12: =IF(L12="","",IF(L12<=4,"Low",IF(L12<=9,"Medium",IF(L12<=15,"High","Critical")))) -> Critical | W12: =IF(I12="","",MAX(1,I12-(IF(V12="Limited",1,IF(V12="Partial",2,IF(V12="Substantial",3,IF(V12="Highly Effective",4,0))))))) -> 5 | X12: =IF(K12="","",MAX(1,K12-ROUNDDOWN((IF(V12="Limited",1,IF(V12="Partial",2,IF(V12="Substantial",3,IF(V12="Highly Effective",4,0)))))/2,0))) -> 5 | Y12: =IF(OR(W12="",X12=""),"",W12*X12) -> 25 | Z12: =IF(Y12="","",IF(Y12<=4,"Low",IF(Y12<=9,"Medium",IF(Y12<=15,"High","Critical")))) -> Critical | AA12: =IF(OR(L12="",Y12=""),"",IF(Y12<L12,"Reduced by "&(L12-Y12)&" pts",IF(Y12=L12,"No Change","Increased by "&(Y12-L12)&" pts"))) -> No Change | AB12: =IF(Y12="","",Y12+(ROW()/10000000)) -> 25.000001
A13: 8 | B13: PHC/IDDS | C13: 2. Workforce sustainability and institutional capability | D13: Loss of operational continuity due to high staff turn-over | E13: if the division continues to rely on high staff turn-over, then this could affect continuity and efficacity of activities implementation | F13: Length process of recruitment, uncertainty of grant fund, and shift in financial resource | G13: Operational | H13: Certain | I13: =IFERROR(IF(H13="Unlikely",1,IF(H13="Possible",2,IF(H13="Likely",3,IF(H13="Almost Certain",4,IF(H13="Certain",5,""))))),"") -> 5 | J13: Major | K13: =IFERROR(IF(J13="Negligible",1,IF(J13="Minor",2,IF(J13="Moderate",3,IF(J13="Major",4,IF(J13="Critical",5,""))))),"") -> 4 | L13: =IF(OR(I13="",K13=""),"",I13*K13) -> 20 | M13: Expanded resource mobilization Expedited recruitment process | O13: 45930 | P13: Open - Extended | Q13: Center Director at PHC / Partnership at External Relations | U13: =IF(L13="","",IF(L13<=4,"Low",IF(L13<=9,"Medium",IF(L13<=15,"High","Critical")))) -> Critical | W13: =IF(I13="","",MAX(1,I13-(IF(V13="Limited",1,IF(V13="Partial",2,IF(V13="Substantial",3,IF(V13="Highly Effective",4,0))))))) -> 5 | X13: =IF(K13="","",MAX(1,K13-ROUNDDOWN((IF(V13="Limited",1,IF(V13="Partial",2,IF(V13="Substantial",3,IF(V13="Highly Effective",4,0)))))/2,0))) -> 4 | Y13: =IF(OR(W13="",X13=""),"",W13*X13) -> 20 | Z13: =IF(Y13="","",IF(Y13<=4,"Low",IF(Y13<=9,"Medium",IF(Y13<=15,"High","Critical")))) -> Critical | AA13: =IF(OR(L13="",Y13=""),"",IF(Y13<L13,"Reduced by "&(L13-Y13)&" pts",IF(Y13=L13,"No Change","Increased by "&(Y13-L13)&" pts"))) -> No Change | AB13: =IF(Y13="","",Y13+(ROW()/10000000)) -> 20.000001
A14: 9 | B14: PHC/IDDS | C14: 4. Program execution and delivery | D14: Difficult collaboration with other ACDC centers in order to share knowledge and ensure internal alignment on critical projects | E14: If the division continues to relay only on itself, then this could affect the quality, relevance and delays in delivering interventions | F14: Corporate culture Lack of formal frameworks to foster inter-center collaboration | G14: Operational | H14: Likely | I14: =IFERROR(IF(H14="Unlikely",1,IF(H14="Possible",2,IF(H14="Likely",3,IF(H14="Almost Certain",4,IF(H14="Certain",5,""))))),"") -> 3 | J14: Major | K14: =IFERROR(IF(J14="Negligible",1,IF(J14="Minor",2,IF(J14="Moderate",3,IF(J14="Major",4,IF(J14="Critical",5,""))))),"") -> 4 | L14: =IF(OR(I14="",K14=""),"",I14*K14) -> 12 | M14: Instaurer un cadre de collaboration continu inter-centres | O14: 45930 | P14: Open - Extended | Q14: Center Director at PHC | U14: =IF(L14="","",IF(L14<=4,"Low",IF(L14<=9,"Medium",IF(L14<=15,"High","Critical")))) -> High | W14: =IF(I14="","",MAX(1,I14-(IF(V14="Limited",1,IF(V14="Partial",2,IF(V14="Substantial",3,IF(V14="Highly Effective",4,0))))))) -> 3 | X14: =IF(K14="","",MAX(1,K14-ROUNDDOWN((IF(V14="Limited",1,IF(V14="Partial",2,IF(V14="Substantial",3,IF(V14="Highly Effective",4,0)))))/2,0))) -> 4 | Y14: =IF(OR(W14="",X14=""),"",W14*X14) -> 12 | Z14: =IF(Y14="","",IF(Y14<=4,"Low",IF(Y14<=9,"Medium",IF(Y14<=15,"High","Critical")))) -> High | AA14: =IF(OR(L14="",Y14=""),"",IF(Y14<L14,"Reduced by "&(L14-Y14)&" pts",IF(Y14=L14,"No Change","Increased by "&(Y14-L14)&" pts"))) -> No Change | AB14: =IF(Y14="","",Y14+(ROW()/10000000)) -> 12.000001
A15: 10 | B15: PHC/IDDS | C15: 9. Emergency readiness, duty of care, and biosafety/biosecurity | D15: Unsafe pratices: technical staffs have to travel from headquarters with a lot of CASH to support activities in ME | E15: If the organization continues to relay of unsafe practices regarding finances, then this could impact it's safety staff and finances | F15: Limitation options due to complicated processes | G15: Operational | H15: Certain | I15: =IFERROR(IF(H15="Unlikely",1,IF(H15="Possible",2,IF(H15="Likely",3,IF(H15="Almost Certain",4,IF(H15="Certain",5,""))))),"") -> 5 | J15: Critical | K15: =IFERROR(IF(J15="Negligible",1,IF(J15="Minor",2,IF(J15="Moderate",3,IF(J15="Major",4,IF(J15="Critical",5,""))))),"") -> 5 | L15: =IF(OR(I15="",K15=""),"",I15*K15) -> 25 | M15: Relax procedures: involve RCCs or national coordinators in the management of financial flows or send money to the MOH. | O15: 45930 | P15: Open - Extended | Q15: Finances | U15: =IF(L15="","",IF(L15<=4,"Low",IF(L15<=9,"Medium",IF(L15<=15,"High","Critical")))) -> Critical | W15: =IF(I15="","",MAX(1,I15-(IF(V15="Limited",1,IF(V15="Partial",2,IF(V15="Substantial",3,IF(V15="Highly Effective",4,0))))))) -> 5 | X15: =IF(K15="","",MAX(1,K15-ROUNDDOWN((IF(V15="Limited",1,IF(V15="Partial",2,IF(V15="Substantial",3,IF(V15="Highly Effective",4,0)))))/2,0))) -> 5 | Y15: =IF(OR(W15="",X15=""),"",W15*X15) -> 25 | Z15: =IF(Y15="","",IF(Y15<=4,"Low",IF(Y15<=9,"Medium",IF(Y15<=15,"High","Critical")))) -> Critical | AA15: =IF(OR(L15="",Y15=""),"",IF(Y15<L15,"Reduced by "&(L15-Y15)&" pts",IF(Y15=L15,"No Change","Increased by "&(Y15-L15)&" pts"))) -> No Change | AB15: =IF(Y15="","",Y15+(ROW()/10000000)) -> 25.000001
A16: 11 | B16: SRMNCAH | C16: 2. Workforce sustainability and institutional capability | D16: Short contract of staff | E16: Pause of programme activities | F16: Limited budget to cover staff cost | G16: Project | H16: Certain | I16: =IFERROR(IF(H16="Unlikely",1,IF(H16="Possible",2,IF(H16="Likely",3,IF(H16="Almost Certain",4,IF(H16="Certain",5,""))))),"") -> 5 | J16: Critical | K16: =IFERROR(IF(J16="Negligible",1,IF(J16="Minor",2,IF(J16="Moderate",3,IF(J16="Major",4,IF(J16="Critical",5,""))))),"") -> 5 | L16: =IF(OR(I16="",K16=""),"",I16*K16) -> 25 | O16: 45930 | P16: Open - Extended | U16: =IF(L16="","",IF(L16<=4,"Low",IF(L16<=9,"Medium",IF(L16<=15,"High","Critical")))) -> Critical | W16: =IF(I16="","",MAX(1,I16-(IF(V16="Limited",1,IF(V16="Partial",2,IF(V16="Substantial",3,IF(V16="Highly Effective",4,0))))))) -> 5 | X16: =IF(K16="","",MAX(1,K16-ROUNDDOWN((IF(V16="Limited",1,IF(V16="Partial",2,IF(V16="Substantial",3,IF(V16="Highly Effective",4,0)))))/2,0))) -> 5 | Y16: =IF(OR(W16="",X16=""),"",W16*X16) -> 25 | Z16: =IF(Y16="","",IF(Y16<=4,"Low",IF(Y16<=9,"Medium",IF(Y16<=15,"High","Critical")))) -> Critical | AA16: =IF(OR(L16="",Y16=""),"",IF(Y16<L16,"Reduced by "&(L16-Y16)&" pts",IF(Y16=L16,"No Change","Increased by "&(Y16-L16)&" pts"))) -> No Change | AB16: =IF(Y16="","",Y16+(ROW()/10000000)) -> 25.000002
A17: 12 | B17: SRNMCAH | C17: 1. Sustainable financing and resource mobilization | D17: Priorities annual new activity delaly | E17: Slow progress on the implementation of RMNH unit annual priorities | F17: No funding to fund activities | G17: Operational | H17: Almost Certain | I17: =IFERROR(IF(H17="Unlikely",1,IF(H17="Possible",2,IF(H17="Likely",3,IF(H17="Almost Certain",4,IF(H17="Certain",5,""))))),"") -> 4 | J17: Major | K17: =IFERROR(IF(J17="Negligible",1,IF(J17="Minor",2,IF(J17="Moderate",3,IF(J17="Major",4,IF(J17="Critical",5,""))))),"") -> 4 | L17: =IF(OR(I17="",K17=""),"",I17*K17) -> 16 | O17: 45930 | P17: Open - Extended | U17: =IF(L17="","",IF(L17<=4,"Low",IF(L17<=9,"Medium",IF(L17<=15,"High","Critical")))) -> Critical | W17: =IF(I17="","",MAX(1,I17-(IF(V17="Limited",1,IF(V17="Partial",2,IF(V17="Substantial",3,IF(V17="Highly Effective",4,0))))))) -> 4 | X17: =IF(K17="","",MAX(1,K17-ROUNDDOWN((IF(V17="Limited",1,IF(V17="Partial",2,IF(V17="Substantial",3,IF(V17="Highly Effective",4,0)))))/2,0))) -> 4 | Y17: =IF(OR(W17="",X17=""),"",W17*X17) -> 16 | Z17: =IF(Y17="","",IF(Y17<=4,"Low",IF(Y17<=9,"Medium",IF(Y17<=15,"High","Critical")))) -> Critical | AA17: =IF(OR(L17="",Y17=""),"",IF(Y17<L17,"Reduced by "&(L17-Y17)&" pts",IF(Y17=L17,"No Change","Increased by "&(Y17-L17)&" pts"))) -> No Change | AB17: =IF(Y17="","",Y17+(ROW()/10000000)) -> 16.000002
A18: 13 | B18: SRNMCAH | C18: 4. Program execution and delivery | D18: Non-alignment of the different units of the division | G18: Strategic | H18: Likely | I18: =IFERROR(IF(H18="Unlikely",1,IF(H18="Possible",2,IF(H18="Likely",3,IF(H18="Almost Certain",4,IF(H18="Certain",5,""))))),"") -> 3 | J18: Major | K18: =IFERROR(IF(J18="Negligible",1,IF(J18="Minor",2,IF(J18="Moderate",3,IF(J18="Major",4,IF(J18="Critical",5,""))))),"") -> 4 | L18: =IF(OR(I18="",K18=""),"",I18*K18) -> 12 | O18: 45930 | P18: Open - Extended | U18: =IF(L18="","",IF(L18<=4,"Low",IF(L18<=9,"Medium",IF(L18<=15,"High","Critical")))) -> High | W18: =IF(I18="","",MAX(1,I18-(IF(V18="Limited",1,IF(V18="Partial",2,IF(V18="Substantial",3,IF(V18="Highly Effective",4,0))))))) -> 3 | X18: =IF(K18="","",MAX(1,K18-ROUNDDOWN((IF(V18="Limited",1,IF(V18="Partial",2,IF(V18="Substantial",3,IF(V18="Highly Effective",4,0)))))/2,0))) -> 4 | Y18: =IF(OR(W18="",X18=""),"",W18*X18) -> 12 | Z18: =IF(Y18="","",IF(Y18<=4,"Low",IF(Y18<=9,"Medium",IF(Y18<=15,"High","Critical")))) -> High | AA18: =IF(OR(L18="",Y18=""),"",IF(Y18<L18,"Reduced by "&(L18-Y18)&" pts",IF(Y18=L18,"No Change","Increased by "&(Y18-L18)&" pts"))) -> No Change | AB18: =IF(Y18="","",Y18+(ROW()/10000000)) -> 12.000002
A19: 14 | B19: PHC/NCDIMH | C19: 2. Workforce sustainability and institutional capability | D19: Inadequate staff to effectively deliver on division goal | F19: need for additional staff to cover the prgrammes and projects delivered by the division | G19: Operational | H19: Possible | I19: =IFERROR(IF(H19="Unlikely",1,IF(H19="Possible",2,IF(H19="Likely",3,IF(H19="Almost Certain",4,IF(H19="Certain",5,""))))),"") -> 2 | J19: Minor | K19: =IFERROR(IF(J19="Negligible",1,IF(J19="Minor",2,IF(J19="Moderate",3,IF(J19="Major",4,IF(J19="Critical",5,""))))),"") -> 2 | L19: =IF(OR(I19="",K19=""),"",I19*K19) -> 4 | M19: Resource mobilization to meet staff costs and advocate for Member States Funding | O19: 45930 | P19: Open - Extended | U19: =IF(L19="","",IF(L19<=4,"Low",IF(L19<=9,"Medium",IF(L19<=15,"High","Critical")))) -> Low | W19: =IF(I19="","",MAX(1,I19-(IF(V19="Limited",1,IF(V19="Partial",2,IF(V19="Substantial",3,IF(V19="Highly Effective",4,0))))))) -> 2 | X19: =IF(K19="","",MAX(1,K19-ROUNDDOWN((IF(V19="Limited",1,IF(V19="Partial",2,IF(V19="Substantial",3,IF(V19="Highly Effective",4,0)))))/2,0))) -> 2 | Y19: =IF(OR(W19="",X19=""),"",W19*X19) -> 4 | Z19: =IF(Y19="","",IF(Y19<=4,"Low",IF(Y19<=9,"Medium",IF(Y19<=15,"High","Critical")))) -> Low | AA19: =IF(OR(L19="",Y19=""),"",IF(Y19<L19,"Reduced by "&(L19-Y19)&" pts",IF(Y19=L19,"No Change","Increased by "&(Y19-L19)&" pts"))) -> No Change | AB19: =IF(Y19="","",Y19+(ROW()/10000000)) -> 4.0000019
A20: 15 | B20: PHC/NCDIMH | C20: 2. Workforce sustainability and institutional capability | D20: Short-term contract for recruited staff | E20: If majority of staff have short term contracts of less than 2 years, then the division faces operational challenges leading to disturbances in implementation of planned activities and impacts on the organizational mandate. | F20: Limited budget to cover staff cost and budgets being avaialbel on annual basis. | G20: Operational | H20: Almost Certain | I20: =IFERROR(IF(H20="Unlikely",1,IF(H20="Possible",2,IF(H20="Likely",3,IF(H20="Almost Certain",4,IF(H20="Certain",5,""))))),"") -> 4 | J20: Major | K20: =IFERROR(IF(J20="Negligible",1,IF(J20="Minor",2,IF(J20="Moderate",3,IF(J20="Major",4,IF(J20="Critical",5,""))))),"") -> 4 | L20: =IF(OR(I20="",K20=""),"",I20*K20) -> 16 | M20: To negotiate for long-term staff contracts according to funding availability and have extended grants | O20: 45930 | P20: Open - Extended | Q20: PHC Centre Director, HR Director and Director of Strategic Operation | U20: =IF(L20="","",IF(L20<=4,"Low",IF(L20<=9,"Medium",IF(L20<=15,"High","Critical")))) -> Critical | W20: =IF(I20="","",MAX(1,I20-(IF(V20="Limited",1,IF(V20="Partial",2,IF(V20="Substantial",3,IF(V20="Highly Effective",4,0))))))) -> 4 | X20: =IF(K20="","",MAX(1,K20-ROUNDDOWN((IF(V20="Limited",1,IF(V20="Partial",2,IF(V20="Substantial",3,IF(V20="Highly Effective",4,0)))))/2,0))) -> 4 | Y20: =IF(OR(W20="",X20=""),"",W20*X20) -> 16 | Z20: =IF(Y20="","",IF(Y20<=4,"Low",IF(Y20<=9,"Medium",IF(Y20<=15,"High","Critical")))) -> Critical | AA20: =IF(OR(L20="",Y20=""),"",IF(Y20<L20,"Reduced by "&(L20-Y20)&" pts",IF(Y20=L20,"No Change","Increased by "&(Y20-L20)&" pts"))) -> No Change | AB20: =IF(Y20="","",Y20+(ROW()/10000000)) -> 16.000002
A21: 16 | B21: PHC/NCDIMH | C21: 4. Program execution and delivery | D21: Misalignment between the NCDIMH division and other divisions under PHC | E21: If there is inadequate internal alignment with the overall PHC structure, then there will be duplication of efforts, verticalisation, and fragmentation of support to member states and the succefull implentation of programmes which increases administrative costs, indicate silo working ethic and undermines the effectiveness of the PHC centre . | F21: 1. Lack of interdisciplinary teamwork and shared objectives 2. Divisions/ Units/ Teams operate in isolation, with limited coordination or collaboration undermining the integrated PHC approach 3. lack of technical meeting between divisions under PHC for aligning and do cross division support. | G21: Strategic | H21: Likely | I21: =IFERROR(IF(H21="Unlikely",1,IF(H21="Possible",2,IF(H21="Likely",3,IF(H21="Almost Certain",4,IF(H21="Certain",5,""))))),"") -> 3 | J21: Moderate | K21: =IFERROR(IF(J21="Negligible",1,IF(J21="Minor",2,IF(J21="Moderate",3,IF(J21="Major",4,IF(J21="Critical",5,""))))),"") -> 3 | L21: =IF(OR(I21="",K21=""),"",I21*K21) -> 9 | M21: Establish/Introducing weekly PHC technical meetings for Divisions to share updates and create Programmatic communication SOP. | O21: 45930 | P21: Open - Extended | Q21: PHC Centre Director and Heads of Divisions | U21: =IF(L21="","",IF(L21<=4,"Low",IF(L21<=9,"Medium",IF(L21<=15,"High","Critical")))) -> Medium | W21: =IF(I21="","",MAX(1,I21-(IF(V21="Limited",1,IF(V21="Partial",2,IF(V21="Substantial",3,IF(V21="Highly Effective",4,0))))))) -> 3 | X21: =IF(K21="","",MAX(1,K21-ROUNDDOWN((IF(V21="Limited",1,IF(V21="Partial",2,IF(V21="Substantial",3,IF(V21="Highly Effective",4,0)))))/2,0))) -> 3 | Y21: =IF(OR(W21="",X21=""),"",W21*X21) -> 9 | Z21: =IF(Y21="","",IF(Y21<=4,"Low",IF(Y21<=9,"Medium",IF(Y21<=15,"High","Critical")))) -> Medium | AA21: =IF(OR(L21="",Y21=""),"",IF(Y21<L21,"Reduced by "&(L21-Y21)&" pts",IF(Y21=L21,"No Change","Increased by "&(Y21-L21)&" pts"))) -> No Change | AB21: =IF(Y21="","",Y21+(ROW()/10000000)) -> 9.0000021
A22: 17 | B22: PHC/NCDIMH | C22: 4. Program execution and delivery | D22: Delayed implementation of division projects | E22: If there are continued delays in project related activities, which may result in delayed implementation of planned activities which may result in organizational project and reputational risk and public negative communication about programme | F22: 1. Lack of intercenter teamwork and prioritization of activities 2. Delayed and non action on shared task and action points regarding projects. | G22: Project | H22: Possible | I22: =IFERROR(IF(H22="Unlikely",1,IF(H22="Possible",2,IF(H22="Likely",3,IF(H22="Almost Certain",4,IF(H22="Certain",5,""))))),"") -> 2 | J22: Moderate | K22: =IFERROR(IF(J22="Negligible",1,IF(J22="Minor",2,IF(J22="Moderate",3,IF(J22="Major",4,IF(J22="Critical",5,""))))),"") -> 3 | L22: =IF(OR(I22="",K22=""),"",I22*K22) -> 6 | M22: Improved Approval process and internal systems | O22: 45930 | P22: Open - Extended | Q22: PHC Centre Director, other Center directors and Executive Office | U22: =IF(L22="","",IF(L22<=4,"Low",IF(L22<=9,"Medium",IF(L22<=15,"High","Critical")))) -> Medium | W22: =IF(I22="","",MAX(1,I22-(IF(V22="Limited",1,IF(V22="Partial",2,IF(V22="Substantial",3,IF(V22="Highly Effective",4,0))))))) -> 2 | X22: =IF(K22="","",MAX(1,K22-ROUNDDOWN((IF(V22="Limited",1,IF(V22="Partial",2,IF(V22="Substantial",3,IF(V22="Highly Effective",4,0)))))/2,0))) -> 3 | Y22: =IF(OR(W22="",X22=""),"",W22*X22) -> 6 | Z22: =IF(Y22="","",IF(Y22<=4,"Low",IF(Y22<=9,"Medium",IF(Y22<=15,"High","Critical")))) -> Medium | AA22: =IF(OR(L22="",Y22=""),"",IF(Y22<L22,"Reduced by "&(L22-Y22)&" pts",IF(Y22=L22,"No Change","Increased by "&(Y22-L22)&" pts"))) -> No Change | AB22: =IF(Y22="","",Y22+(ROW()/10000000)) -> 6.0000022
A23: 18 | B23: EPR | C23: 2. Workforce sustainability and institutional capability | D23: Unstable contracts for 90% of the Division staff | E23: If the division continues to rely on more than 90% staff with unstable contract, then it faces a significant risk of operational disruption should the staff move away from Africa CDC. | F23: Lack of a diversified donor strategy – No structured plan to attract multiple donors for human resource funding. Inadequate resource mobilization capacity – No dedicated team/personnel to develop and execute funding strategies. Over-reliance on short-term project-based funding – Human resource costs are linked to time-bound donor projects. Absence of institutional core funding – The organization lacks a core budget to support staff independently of external donors. Weak donor relationship management – Insufficient engagement with other donors to expand the funding base. Organizational culture focused on program delivery over sustainability – Emphasis on outputs without strategic planning for long-term viability. | G23: Operational | H23: Likely | I23: =IFERROR(IF(H23="Unlikely",1,IF(H23="Possible",2,IF(H23="Likely",3,IF(H23="Almost Certain",4,IF(H23="Certain",5,""))))),"") -> 3 | J23: Critical | K23: =IFERROR(IF(J23="Negligible",1,IF(J23="Minor",2,IF(J23="Moderate",3,IF(J23="Major",4,IF(J23="Critical",5,""))))),"") -> 5 | L23: =IF(OR(I23="",K23=""),"",I23*K23) -> 15 | M23: -Provide a long duration contract, at least one year. - Ensure inclusion of HR in each project during grant proposal discussion | O23: 45930 | P23: Open - Extended | Q23: Organization wide, Head of division, HR, Partnership | U23: =IF(L23="","",IF(L23<=4,"Low",IF(L23<=9,"Medium",IF(L23<=15,"High","Critical")))) -> High | W23: =IF(I23="","",MAX(1,I23-(IF(V23="Limited",1,IF(V23="Partial",2,IF(V23="Substantial",3,IF(V23="Highly Effective",4,0))))))) -> 3 | X23: =IF(K23="","",MAX(1,K23-ROUNDDOWN((IF(V23="Limited",1,IF(V23="Partial",2,IF(V23="Substantial",3,IF(V23="Highly Effective",4,0)))))/2,0))) -> 5 | Y23: =IF(OR(W23="",X23=""),"",W23*X23) -> 15 | Z23: =IF(Y23="","",IF(Y23<=4,"Low",IF(Y23<=9,"Medium",IF(Y23<=15,"High","Critical")))) -> High | AA23: =IF(OR(L23="",Y23=""),"",IF(Y23<L23,"Reduced by "&(L23-Y23)&" pts",IF(Y23=L23,"No Change","Increased by "&(Y23-L23)&" pts"))) -> No Change | AB23: =IF(Y23="","",Y23+(ROW()/10000000)) -> 15.000002
A24: 19 | B24: EPR | C24: 4. Program execution and delivery | D24: Inadequate knowledge & awareness of perceived written procedures for the Division operations | E24: If staff have limited knowledge or unawareness of SOPs that govern the day-to-day division operations, then it faces a significant risk of non-compliance and reputation | F24: Lack of Awareness and Resistance to Change: staff may not fully understand the importance of SOPs and how they contribute to consistency and efficiency and then prefer informal workflows and resist documentation, fearing rigid processes Rapid Growth: The division has experienced rapid expansion since the period of Covid-19 (a lot initiatives, projects and processes have been introduced) and may struggle to formalize the processes. Limited Resources: Creating SOPs requires time, effort, and expertise, which may not be prioritized due to resource constraints. Over-Reliance on Individual Expertise: Preference to depend too much on the experience of key staff instead of formalizing best practices. Lack of Leadership Support: Without top management driving the need for SOPs, staff may not see their necessity. | G24: Operational | H24: Likely | I24: =IFERROR(IF(H24="Unlikely",1,IF(H24="Possible",2,IF(H24="Likely",3,IF(H24="Almost Certain",4,IF(H24="Certain",5,""))))),"") -> 3 | J24: Critical | K24: =IFERROR(IF(J24="Negligible",1,IF(J24="Minor",2,IF(J24="Moderate",3,IF(J24="Major",4,IF(J24="Critical",5,""))))),"") -> 5 | L24: =IF(OR(I24="",K24=""),"",I24*K24) -> 15 | M24: - Organize regular mentorship (awareness creation) on internal procedures - Put in place champions on some of routine operations (rwitting memo, reports…) | O24: 45930 | P24: Open - Extended | Q24: Heads of units, EPR | U24: =IF(L24="","",IF(L24<=4,"Low",IF(L24<=9,"Medium",IF(L24<=15,"High","Critical")))) -> High | W24: =IF(I24="","",MAX(1,I24-(IF(V24="Limited",1,IF(V24="Partial",2,IF(V24="Substantial",3,IF(V24="Highly Effective",4,0))))))) -> 3 | X24: =IF(K24="","",MAX(1,K24-ROUNDDOWN((IF(V24="Limited",1,IF(V24="Partial",2,IF(V24="Substantial",3,IF(V24="Highly Effective",4,0)))))/2,0))) -> 5 | Y24: =IF(OR(W24="",X24=""),"",W24*X24) -> 15 | Z24: =IF(Y24="","",IF(Y24<=4,"Low",IF(Y24<=9,"Medium",IF(Y24<=15,"High","Critical")))) -> High | AA24: =IF(OR(L24="",Y24=""),"",IF(Y24<L24,"Reduced by "&(L24-Y24)&" pts",IF(Y24=L24,"No Change","Increased by "&(Y24-L24)&" pts"))) -> No Change | AB24: =IF(Y24="","",Y24+(ROW()/10000000)) -> 15.000002
A25: 20 | B25: EPR | C25: 8. Integrity, compliance, and safeguarding | D25: Sexual Exploitation, Abuse and Harassment by Health emergency Responders (staffs, AVoHC RRT) during deplpyment for Health Emergency Response. | E25: If Health Emergenccy Responders commit SEA, SH during deployment, Africa CDC faces a significate reputational risks. | F25: Weak Enforcement of Policies: Gaps in implementation or enforcement of Africa CDC directives on SEAH prevention, may allow misconduct to persist. Power Imbalances: AVoHC responders operate in vulnerable communities where individuals may even prompt the responders to these kind of practices Cultural & Social Norms: In some African regions, deeply ingrained gender inequalities may contribute to tolerance or underreporting of SEAH incidents Reporting Mechanisms: Lack or limited access to safe reporting channels, preventing tthe victims from seeking justice. Failure to Monitor & Hold Perpetrators Accountable: Weak oversight and insufficient disciplinary measures can create an environment where misconduct goes unchecked | G25: Reputational | H25: Likely | I25: =IFERROR(IF(H25="Unlikely",1,IF(H25="Possible",2,IF(H25="Likely",3,IF(H25="Almost Certain",4,IF(H25="Certain",5,""))))),"") -> 3 | J25: Critical | K25: =IFERROR(IF(J25="Negligible",1,IF(J25="Minor",2,IF(J25="Moderate",3,IF(J25="Major",4,IF(J25="Critical",5,""))))),"") -> 5 | L25: =IF(OR(I25="",K25=""),"",I25*K25) -> 15 | M25: - Regular briefing on prevention of SEAH before deoloyment using WHO standars for example -Systematically ensure all responders sign and adhere to a code that explicitly prohibits SEAH. -Establish confidential mechanism for victims and witnesses to report misconduct safely. | O25: 45930 | P25: Open - Extended | Q25: AVoHC Program lead, HR, Legal | U25: =IF(L25="","",IF(L25<=4,"Low",IF(L25<=9,"Medium",IF(L25<=15,"High","Critical")))) -> High | W25: =IF(I25="","",MAX(1,I25-(IF(V25="Limited",1,IF(V25="Partial",2,IF(V25="Substantial",3,IF(V25="Highly Effective",4,0))))))) -> 3 | X25: =IF(K25="","",MAX(1,K25-ROUNDDOWN((IF(V25="Limited",1,IF(V25="Partial",2,IF(V25="Substantial",3,IF(V25="Highly Effective",4,0)))))/2,0))) -> 5 | Y25: =IF(OR(W25="",X25=""),"",W25*X25) -> 15 | Z25: =IF(Y25="","",IF(Y25<=4,"Low",IF(Y25<=9,"Medium",IF(Y25<=15,"High","Critical")))) -> High | AA25: =IF(OR(L25="",Y25=""),"",IF(Y25<L25,"Reduced by "&(L25-Y25)&" pts",IF(Y25=L25,"No Change","Increased by "&(Y25-L25)&" pts"))) -> No Change | AB25: =IF(Y25="","",Y25+(ROW()/10000000)) -> 15.000003
A26: 21 | B26: EPR | C26: 1. Sustainable financing and resource mobilization | D26: Insuficient fundings | E26: If the division does not have sufficient funds, if faces significant risk to not achieving the strategic goals/objectives | F26: Declining External Support: Official Development Assistance (ODA) to Africa has decreased by 70% in recent years, reducing financial resources for health security. Limited Domestic Investment: Few African Union Member States meet the Abuja target of allocating 15% of national budgets to healthcare, leading to reliance on external donors, and therefore a lot of request for assistance during health emeregencies Rising Health Emergencies: The continent continiouselly experiences an increase in public health emergencies, stretching available funds Lack of Sustainable Financing Models: Traditional funding mechanisms (mainly donors) are unpredictable, making it difficult to maintain consistent financial support. | G26: Strategic | H26: Certain | I26: =IFERROR(IF(H26="Unlikely",1,IF(H26="Possible",2,IF(H26="Likely",3,IF(H26="Almost Certain",4,IF(H26="Certain",5,""))))),"") -> 5 | J26: Critical | K26: =IFERROR(IF(J26="Negligible",1,IF(J26="Minor",2,IF(J26="Moderate",3,IF(J26="Major",4,IF(J26="Critical",5,""))))),"") -> 5 | L26: =IF(OR(I26="",K26=""),"",I26*K26) -> 25 | M26: -Ensure efficient management of existing funds using data driven allocation (prioritzation and integration) - Mobilize more ressources based on strategic vision and clear goal and objectives - At least have two or tree partners engaged and incoperated in our planning early enough (example ECDC, UK-HSA) | O26: 45930 | P26: Open - Extended | Q26: Head of division, Head of units, Partnership | U26: =IF(L26="","",IF(L26<=4,"Low",IF(L26<=9,"Medium",IF(L26<=15,"High","Critical")))) -> Critical | W26: =IF(I26="","",MAX(1,I26-(IF(V26="Limited",1,IF(V26="Partial",2,IF(V26="Substantial",3,IF(V26="Highly Effective",4,0))))))) -> 5 | X26: =IF(K26="","",MAX(1,K26-ROUNDDOWN((IF(V26="Limited",1,IF(V26="Partial",2,IF(V26="Substantial",3,IF(V26="Highly Effective",4,0)))))/2,0))) -> 5 | Y26: =IF(OR(W26="",X26=""),"",W26*X26) -> 25 | Z26: =IF(Y26="","",IF(Y26<=4,"Low",IF(Y26<=9,"Medium",IF(Y26<=15,"High","Critical")))) -> Critical | AA26: =IF(OR(L26="",Y26=""),"",IF(Y26<L26,"Reduced by "&(L26-Y26)&" pts",IF(Y26=L26,"No Change","Increased by "&(Y26-L26)&" pts"))) -> No Change | AB26: =IF(Y26="","",Y26+(ROW()/10000000)) -> 25.000003
A27: 22 | B27: EPR | C27: 9. Emergency readiness, duty of care, and biosafety/biosecurity | D27: Deployment of AVoHC responders to an outbreak without medical or insurance cover | E27: If AVoHC responder falls sick, gets infected by the disease they are responding to or even dies, this may expose Africa CDC to legal proceedures that may turnish the reputation of the organization | F27: -Reactive deployment operations: In fast-moving outbreaks, responders may be deployed quickly without completion of all administrative processes, including insurance arrangements. - Short duration of deployment: Many insurance companies require a minimum contract period (often 12 months) for coverage, while AVoHC deployments typically last only three months. This mismatch makes it difficult to secure appropriate insurance plans for short-term responders. | G27: Public Health Emergency Response | H27: Almost Certain | I27: =IFERROR(IF(H27="Unlikely",1,IF(H27="Possible",2,IF(H27="Likely",3,IF(H27="Almost Certain",4,IF(H27="Certain",5,""))))),"") -> 4 | J27: Critical | K27: =IFERROR(IF(J27="Negligible",1,IF(J27="Minor",2,IF(J27="Moderate",3,IF(J27="Major",4,IF(J27="Critical",5,""))))),"") -> 5 | L27: =IF(OR(I27="",K27=""),"",I27*K27) -> 20 | M27: -Identify the mechanism for systematically provide health insurance before deployment - Establish a stand-by framework agreement with health issurance | O27: 45930 | P27: Open - Extended | Q27: AVoHC Program lead, HR | U27: =IF(L27="","",IF(L27<=4,"Low",IF(L27<=9,"Medium",IF(L27<=15,"High","Critical")))) -> Critical | W27: =IF(I27="","",MAX(1,I27-(IF(V27="Limited",1,IF(V27="Partial",2,IF(V27="Substantial",3,IF(V27="Highly Effective",4,0))))))) -> 4 | X27: =IF(K27="","",MAX(1,K27-ROUNDDOWN((IF(V27="Limited",1,IF(V27="Partial",2,IF(V27="Substantial",3,IF(V27="Highly Effective",4,0)))))/2,0))) -> 5 | Y27: =IF(OR(W27="",X27=""),"",W27*X27) -> 20 | Z27: =IF(Y27="","",IF(Y27<=4,"Low",IF(Y27<=9,"Medium",IF(Y27<=15,"High","Critical")))) -> Critical | AA27: =IF(OR(L27="",Y27=""),"",IF(Y27<L27,"Reduced by "&(L27-Y27)&" pts",IF(Y27=L27,"No Change","Increased by "&(Y27-L27)&" pts"))) -> No Change | AB27: =IF(Y27="","",Y27+(ROW()/10000000)) -> 20.000003
A28: 23 | B28: EPR | C28: 9. Emergency readiness, duty of care, and biosafety/biosecurity | D28: Emergency Response in a complexe humanitarian context | E28: If Africa CDC deploys experts in a complex humanitarian setting where disease outbreaks are reported to provide live saving response activities, it can make it difficult for Africa CDC to have meaningful presence on the ground. | F28: -Limited/lack of collaboration with AUC Peace and Security department -There is no Travel Security Information File for Africa CDC staff travelling to MS | G28: Public Health Emergency Response | H28: Possible | I28: =IFERROR(IF(H28="Unlikely",1,IF(H28="Possible",2,IF(H28="Likely",3,IF(H28="Almost Certain",4,IF(H28="Certain",5,""))))),"") -> 2 | J28: Critical | K28: =IFERROR(IF(J28="Negligible",1,IF(J28="Minor",2,IF(J28="Moderate",3,IF(J28="Major",4,IF(J28="Critical",5,""))))),"") -> 5 | L28: =IF(OR(I28="",K28=""),"",I28*K28) -> 10 | M28: -Joint deployment with AUC Peace and security department - Getting security clearence before deploying in humanitarian seeting | O28: 45930 | P28: Open - Extended | Q28: PHEOC | U28: =IF(L28="","",IF(L28<=4,"Low",IF(L28<=9,"Medium",IF(L28<=15,"High","Critical")))) -> High | W28: =IF(I28="","",MAX(1,I28-(IF(V28="Limited",1,IF(V28="Partial",2,IF(V28="Substantial",3,IF(V28="Highly Effective",4,0))))))) -> 2 | X28: =IF(K28="","",MAX(1,K28-ROUNDDOWN((IF(V28="Limited",1,IF(V28="Partial",2,IF(V28="Substantial",3,IF(V28="Highly Effective",4,0)))))/2,0))) -> 5 | Y28: =IF(OR(W28="",X28=""),"",W28*X28) -> 10 | Z28: =IF(Y28="","",IF(Y28<=4,"Low",IF(Y28<=9,"Medium",IF(Y28<=15,"High","Critical")))) -> High | AA28: =IF(OR(L28="",Y28=""),"",IF(Y28<L28,"Reduced by "&(L28-Y28)&" pts",IF(Y28=L28,"No Change","Increased by "&(Y28-L28)&" pts"))) -> No Change | AB28: =IF(Y28="","",Y28+(ROW()/10000000)) -> 10.000003
A29: 24 | B29: EPR | C29: 9. Emergency readiness, duty of care, and biosafety/biosecurity | D29: Cumbersome internal approval process and late response to MS requests | E29: If the division delays or fails to response timely of the request made by the MS or providing support especially during health emergencies, that crerate a lack of trust from the MS which in turn can cause a significant reputational risk | F29: -Change of priorities based on PHE occurency and dynamics - Limited funds for emergency response interventions - Delays in getting the timely internal approvals which cause unnecessary delays in responding to emergenciew | G29: Public Health Emergency Response | H29: Likely | I29: =IFERROR(IF(H29="Unlikely",1,IF(H29="Possible",2,IF(H29="Likely",3,IF(H29="Almost Certain",4,IF(H29="Certain",5,""))))),"") -> 3 | J29: Critical | K29: =IFERROR(IF(J29="Negligible",1,IF(J29="Minor",2,IF(J29="Moderate",3,IF(J29="Major",4,IF(J29="Critical",5,""))))),"") -> 5 | L29: =IF(OR(I29="",K29=""),"",I29*K29) -> 15 | M29: -Always make sure the availability of funds before any commitment of support to MS - Increase funding for emergency response | O29: 45930 | P29: Open - Extended | Q29: Executive Office, HoD, Heads of Units, Partnership division | U29: =IF(L29="","",IF(L29<=4,"Low",IF(L29<=9,"Medium",IF(L29<=15,"High","Critical")))) -> High | W29: =IF(I29="","",MAX(1,I29-(IF(V29="Limited",1,IF(V29="Partial",2,IF(V29="Substantial",3,IF(V29="Highly Effective",4,0))))))) -> 3 | X29: =IF(K29="","",MAX(1,K29-ROUNDDOWN((IF(V29="Limited",1,IF(V29="Partial",2,IF(V29="Substantial",3,IF(V29="Highly Effective",4,0)))))/2,0))) -> 5 | Y29: =IF(OR(W29="",X29=""),"",W29*X29) -> 15 | Z29: =IF(Y29="","",IF(Y29<=4,"Low",IF(Y29<=9,"Medium",IF(Y29<=15,"High","Critical")))) -> High | AA29: =IF(OR(L29="",Y29=""),"",IF(Y29<L29,"Reduced by "&(L29-Y29)&" pts",IF(Y29=L29,"No Change","Increased by "&(Y29-L29)&" pts"))) -> No Change | AB29: =IF(Y29="","",Y29+(ROW()/10000000)) -> 15.000003
A30: 25 | B30: Lab | C30: 9. Emergency readiness, duty of care, and biosafety/biosecurity | D30: Limited implementation of biosafety and biosecurity regulations across AU Member States | E30: Increased risk of accidental or intentional release of biological agents; reputational damage to Africa CDC; hindered regional preparedness. | F30: Lack of political support from AU Member States. Lack of technical assistance and resource mobilization for implementation. | G30: Strategic | H30: Almost Certain | I30: =IFERROR(IF(H30="Unlikely",1,IF(H30="Possible",2,IF(H30="Likely",3,IF(H30="Almost Certain",4,IF(H30="Certain",5,""))))),"") -> 4 | J30: Critical | K30: =IFERROR(IF(J30="Negligible",1,IF(J30="Minor",2,IF(J30="Moderate",3,IF(J30="Major",4,IF(J30="Critical",5,""))))),"") -> 5 | L30: =IF(OR(I30="",K30=""),"",I30*K30) -> 20 | M30: Promote harmonized regulatory frameworks. Build capacity in biosafety/biosecurity at national levels. | O30: 45930 | P30: Open - Extended | Q30: Africa CDC - Lab | U30: =IF(L30="","",IF(L30<=4,"Low",IF(L30<=9,"Medium",IF(L30<=15,"High","Critical")))) -> Critical | W30: =IF(I30="","",MAX(1,I30-(IF(V30="Limited",1,IF(V30="Partial",2,IF(V30="Substantial",3,IF(V30="Highly Effective",4,0))))))) -> 4 | X30: =IF(K30="","",MAX(1,K30-ROUNDDOWN((IF(V30="Limited",1,IF(V30="Partial",2,IF(V30="Substantial",3,IF(V30="Highly Effective",4,0)))))/2,0))) -> 5 | Y30: =IF(OR(W30="",X30=""),"",W30*X30) -> 20 | Z30: =IF(Y30="","",IF(Y30<=4,"Low",IF(Y30<=9,"Medium",IF(Y30<=15,"High","Critical")))) -> Critical | AA30: =IF(OR(L30="",Y30=""),"",IF(Y30<L30,"Reduced by "&(L30-Y30)&" pts",IF(Y30=L30,"No Change","Increased by "&(Y30-L30)&" pts"))) -> No Change | AB30: =IF(Y30="","",Y30+(ROW()/10000000)) -> 20.000003
A31: 26 | B31: Lab | C31: 7. Data governance and management reporting | D31: Data sovereignty, security and sharing issues among Member States | E31: Delayed or fragmented genomic surveillance; ethical and legal disputes. | F31: lack of investment in the Member State I n terms of genomic infrastructure. | G31: Operational | H31: Possible | I31: =IFERROR(IF(H31="Unlikely",1,IF(H31="Possible",2,IF(H31="Likely",3,IF(H31="Almost Certain",4,IF(H31="Certain",5,""))))),"") -> 2 | J31: Major | K31: =IFERROR(IF(J31="Negligible",1,IF(J31="Minor",2,IF(J31="Moderate",3,IF(J31="Major",4,IF(J31="Critical",5,""))))),"") -> 4 | L31: =IF(OR(I31="",K31=""),"",I31*K31) -> 8 | M31: Develop AU-wide data governance policies. Promote ethical, legal and social frameworks. Strengthen in-country capacity for data storage and analysis | O31: 45930 | P31: Open - Extended | Q31: Africa CDC - Lab | U31: =IF(L31="","",IF(L31<=4,"Low",IF(L31<=9,"Medium",IF(L31<=15,"High","Critical")))) -> Medium | W31: =IF(I31="","",MAX(1,I31-(IF(V31="Limited",1,IF(V31="Partial",2,IF(V31="Substantial",3,IF(V31="Highly Effective",4,0))))))) -> 2 | X31: =IF(K31="","",MAX(1,K31-ROUNDDOWN((IF(V31="Limited",1,IF(V31="Partial",2,IF(V31="Substantial",3,IF(V31="Highly Effective",4,0)))))/2,0))) -> 4 | Y31: =IF(OR(W31="",X31=""),"",W31*X31) -> 8 | Z31: =IF(Y31="","",IF(Y31<=4,"Low",IF(Y31<=9,"Medium",IF(Y31<=15,"High","Critical")))) -> Medium | AA31: =IF(OR(L31="",Y31=""),"",IF(Y31<L31,"Reduced by "&(L31-Y31)&" pts",IF(Y31=L31,"No Change","Increased by "&(Y31-L31)&" pts"))) -> No Change | AB31: =IF(Y31="","",Y31+(ROW()/10000000)) -> 8.0000031
... A37: 32 | B37: SDI | C37: 5. Country, partner, and geopolitical context | D37: Changing surveillance priorities of MS e.g routine program vs emergency response | E37: The surveillance priorities of the Member states keep changing during the implemantation year of Africa CDC. For example planned routine surveillance activites are often disrupted during outbreak/ emergency response. This in turn leads to data gaps, reduced program effectivenes and delayed detection | F37: Public health emergency events such as outbreaks requiring urgent attention. Reallocation of limited resources Donor-driven priorities Change of leadership with in the ministries responsible for health in MS | G37: Strategic | H37: Likely | I37: =IFERROR(IF(H37="Unlikely",1,IF(H37="Possible",2,IF(H37="Likely",3,IF(H37="Almost Certain",4,IF(H37="Certain",5,""))))),"") -> 3 | J37: Major | K37: =IFERROR(IF(J37="Negligible",1,IF(J37="Minor",2,IF(J37="Moderate",3,IF(J37="Major",4,IF(J37="Critical",5,""))))),"") -> 4 | L37: =IF(OR(I37="",K37=""),"",I37*K37) -> 12 | M37: Developing flexible operational plans to always cater for emergencies Advocate for integrated surveillance systems and employ a one health approach Develop early warning systems for resource shifts | O37: 45992 | P37: Open - Extended | Q37: Senior leadership Head of Division Head of Units | U37: =IF(L37="","",IF(L37<=4,"Low",IF(L37<=9,"Medium",IF(L37<=15,"High","Critical")))) -> High | W37: =IF(I37="","",MAX(1,I37-(IF(V37="Limited",1,IF(V37="Partial",2,IF(V37="Substantial",3,IF(V37="Highly Effective",4,0))))))) -> 3 | X37: =IF(K37="","",MAX(1,K37-ROUNDDOWN((IF(V37="Limited",1,IF(V37="Partial",2,IF(V37="Substantial",3,IF(V37="Highly Effective",4,0)))))/2,0))) -> 4 | Y37: =IF(OR(W37="",X37=""),"",W37*X37) -> 12 | Z37: =IF(Y37="","",IF(Y37<=4,"Low",IF(Y37<=9,"Medium",IF(Y37<=15,"High","Critical")))) -> High | AA37: =IF(OR(L37="",Y37=""),"",IF(Y37<L37,"Reduced by "&(L37-Y37)&" pts",IF(Y37=L37,"No Change","Increased by "&(Y37-L37)&" pts"))) -> No Change | AB37: =IF(Y37="","",Y37+(ROW()/10000000)) -> 12.000004
A38: 33 | B38: SDI | C38: 7. Data governance and management reporting | D38: Lack of Data sharing with MS | E38: Data sharing agreement has been an ongoing effort to secure MS commitment to share data regularly with Africa CDC, however the progress is slow | F38: Public health emergency events such as outbreaks are sensitive to share data for both political and economic reason low confidence and trust to the Africa CDC systems for protection of the data lack of visible support and investiment in the data systems of MS to ask for data sharing tangeble insentive to MS for sharing their data | G38: Strategic | H38: Almost Certain | I38: =IFERROR(IF(H38="Unlikely",1,IF(H38="Possible",2,IF(H38="Likely",3,IF(H38="Almost Certain",4,IF(H38="Certain",5,""))))),"") -> 4 | J38: Major | K38: =IFERROR(IF(J38="Negligible",1,IF(J38="Minor",2,IF(J38="Moderate",3,IF(J38="Major",4,IF(J38="Critical",5,""))))),"") -> 4 | L38: =IF(OR(I38="",K38=""),"",I38*K38) -> 16 | O38: 45930 | P38: Open - Extended | Q38: Senior leadership Legal Division Head of Division Head of Units | U38: =IF(L38="","",IF(L38<=4,"Low",IF(L38<=9,"Medium",IF(L38<=15,"High","Critical")))) -> Critical | W38: =IF(I38="","",MAX(1,I38-(IF(V38="Limited",1,IF(V38="Partial",2,IF(V38="Substantial",3,IF(V38="Highly Effective",4,0))))))) -> 4 | X38: =IF(K38="","",MAX(1,K38-ROUNDDOWN((IF(V38="Limited",1,IF(V38="Partial",2,IF(V38="Substantial",3,IF(V38="Highly Effective",4,0)))))/2,0))) -> 4 | Y38: =IF(OR(W38="",X38=""),"",W38*X38) -> 16 | Z38: =IF(Y38="","",IF(Y38<=4,"Low",IF(Y38<=9,"Medium",IF(Y38<=15,"High","Critical")))) -> Critical | AA38: =IF(OR(L38="",Y38=""),"",IF(Y38<L38,"Reduced by "&(L38-Y38)&" pts",IF(Y38=L38,"No Change","Increased by "&(Y38-L38)&" pts"))) -> No Change | AB38: =IF(Y38="","",Y38+(ROW()/10000000)) -> 16.000004
A39: 34 | B39: SDI | C39: 2. Workforce sustainability and institutional capability | D39: Limited workforce ;for a highly demanding Division mandate | E39: Limited workforce capacity may hinder the Division’s ability to deliver on its complex and growing mandate, causing delays, reduced quality, or missed strategic opportunities | F39: Budgetary constraints limiting hiring Lengthy recruitment processes Expansion of mandate without matching resource increases | G39: Strategic | H39: Certain | I39: =IFERROR(IF(H39="Unlikely",1,IF(H39="Possible",2,IF(H39="Likely",3,IF(H39="Almost Certain",4,IF(H39="Certain",5,""))))),"") -> 5 | J39: Critical | K39: =IFERROR(IF(J39="Negligible",1,IF(J39="Minor",2,IF(J39="Moderate",3,IF(J39="Major",4,IF(J39="Critical",5,""))))),"") -> 5 | L39: =IF(OR(I39="",K39=""),"",I39*K39) -> 25 | M39: Advocate for increased staffing and budget allocations Prioritize tasks based on needs assessment Strengthen partnerships to support workload | O39: 45930 | P39: Open - Extended | Q39: Head of Division HR Senior Leadership Head of Units | U39: =IF(L39="","",IF(L39<=4,"Low",IF(L39<=9,"Medium",IF(L39<=15,"High","Critical")))) -> Critical | W39: =IF(I39="","",MAX(1,I39-(IF(V39="Limited",1,IF(V39="Partial",2,IF(V39="Substantial",3,IF(V39="Highly Effective",4,0))))))) -> 5 | X39: =IF(K39="","",MAX(1,K39-ROUNDDOWN((IF(V39="Limited",1,IF(V39="Partial",2,IF(V39="Substantial",3,IF(V39="Highly Effective",4,0)))))/2,0))) -> 5 | Y39: =IF(OR(W39="",X39=""),"",W39*X39) -> 25 | Z39: =IF(Y39="","",IF(Y39<=4,"Low",IF(Y39<=9,"Medium",IF(Y39<=15,"High","Critical")))) -> Critical | AA39: =IF(OR(L39="",Y39=""),"",IF(Y39<L39,"Reduced by "&(L39-Y39)&" pts",IF(Y39=L39,"No Change","Increased by "&(Y39-L39)&" pts"))) -> No Change | AB39: =IF(Y39="","",Y39+(ROW()/10000000)) -> 25.000004
A40: 35 | B40: SDI | C40: 1. Sustainable financing and resource mobilization | D40: Majority of the staff funded by one project donor | E40: the division continues to rely on a donor to fund majority of its human resources, then it faces a significant risk of operational disruption should the donor reduce or withdraw funding affecting sustainability | F40: Absence of institutional core funding – The organization lacks a core budget to support staff independently of external donors. Over-reliance on short-term project-based funding – Human resource costs are linked to time-bound donor projects. Inadequate resource mobilization capacity – No dedicated team/personnel to develop and execute funding strategies. Weak donor relationship management – Insufficient engagement with other donors to expand the funding base. Organizational culture focused on program delivery over sustainability – Emphasis on outputs without strategic planning for long-term viability. | G40: Operational | H40: Likely | I40: =IFERROR(IF(H40="Unlikely",1,IF(H40="Possible",2,IF(H40="Likely",3,IF(H40="Almost Certain",4,IF(H40="Certain",5,""))))),"") -> 3 | J40: Critical | K40: =IFERROR(IF(J40="Negligible",1,IF(J40="Minor",2,IF(J40="Moderate",3,IF(J40="Major",4,IF(J40="Critical",5,""))))),"") -> 5 | L40: =IF(OR(I40="",K40=""),"",I40*K40) -> 15 | M40: 1• Advocate for increased internal budget allocation from core funding or Member States to support key HR roles. 2• Proactively engage with multiple donors and international partners to broaden the funding base for HR. 3• Design a phased HR sustainability plan that outlines how positions will transition from donor-funded to institutionally funded. 4• Negotiate longer-term funding commitments with donors (e.g., 3–5 years) with renewal clauses. 5• Document key processes, SOPs, and knowledge from donor-funded staff in central systems. 6• Upskill locally funded or regular staff to gradually fill donor-funded roles. • Create a contingency or reserve fund to cover staff costs temporarily in case of donor withdrawal. • Include this risk in the division’s quarterly performance reviews and escalate changes to senior management. | O40: 45930 | P40: Open - Extended | Q40: Senior Leadership Head of Division HR Head of Units | U40: =IF(L40="","",IF(L40<=4,"Low",IF(L40<=9,"Medium",IF(L40<=15,"High","Critical")))) -> High | W40: =IF(I40="","",MAX(1,I40-(IF(V40="Limited",1,IF(V40="Partial",2,IF(V40="Substantial",3,IF(V40="Highly Effective",4,0))))))) -> 3 | X40: =IF(K40="","",MAX(1,K40-ROUNDDOWN((IF(V40="Limited",1,IF(V40="Partial",2,IF(V40="Substantial",3,IF(V40="Highly Effective",4,0)))))/2,0))) -> 5 | Y40: =IF(OR(W40="",X40=""),"",W40*X40) -> 15 | Z40: =IF(Y40="","",IF(Y40<=4,"Low",IF(Y40<=9,"Medium",IF(Y40<=15,"High","Critical")))) -> High | AA40: =IF(OR(L40="",Y40=""),"",IF(Y40<L40,"Reduced by "&(L40-Y40)&" pts",IF(Y40=L40,"No Change","Increased by "&(Y40-L40)&" pts"))) -> No Change | AB40: =IF(Y40="","",Y40+(ROW()/10000000)) -> 15.000004
A41: 36 | B41: SDI | C41: 7. Data governance and management reporting | D41: Fragmented disease surveillance platforms | E41: Fragmented disease surveillance platforms across programs (e.g., HIV, TB, malaria, outbreak surveillance) result in inefficiencies, duplication of efforts, poor data integration, and delayed detection and response | F41: Program-specific funding and reporting requirements Lack of national interoperability standards Weak governance and coordination Limited ICT infrastructure or capacity | G41: Operational | H41: Possible | I41: =IFERROR(IF(H41="Unlikely",1,IF(H41="Possible",2,IF(H41="Likely",3,IF(H41="Almost Certain",4,IF(H41="Certain",5,""))))),"") -> 2 | J41: Major | K41: =IFERROR(IF(J41="Negligible",1,IF(J41="Minor",2,IF(J41="Moderate",3,IF(J41="Major",4,IF(J41="Critical",5,""))))),"") -> 4 | L41: =IF(OR(I41="",K41=""),"",I41*K41) -> 8 | M41: Integrate and harmonize systems; align with health information exchange frameworks Advocate for integrated funding streams Build capacity for integrated data management | O41: 45930 | P41: Open - Extended | Q41: Head of Division Senior Leadership Head of Units | U41: =IF(L41="","",IF(L41<=4,"Low",IF(L41<=9,"Medium",IF(L41<=15,"High","Critical")))) -> Medium | W41: =IF(I41="","",MAX(1,I41-(IF(V41="Limited",1,IF(V41="Partial",2,IF(V41="Substantial",3,IF(V41="Highly Effective",4,0))))))) -> 2 | X41: =IF(K41="","",MAX(1,K41-ROUNDDOWN((IF(V41="Limited",1,IF(V41="Partial",2,IF(V41="Substantial",3,IF(V41="Highly Effective",4,0)))))/2,0))) -> 4 | Y41: =IF(OR(W41="",X41=""),"",W41*X41) -> 8 | Z41: =IF(Y41="","",IF(Y41<=4,"Low",IF(Y41<=9,"Medium",IF(Y41<=15,"High","Critical")))) -> Medium | AA41: =IF(OR(L41="",Y41=""),"",IF(Y41<L41,"Reduced by "&(L41-Y41)&" pts",IF(Y41=L41,"No Change","Increased by "&(Y41-L41)&" pts"))) -> No Change | AB41: =IF(Y41="","",Y41+(ROW()/10000000)) -> 8.0000041
A42: 37 | B42: SDI | C42: 7. Data governance and management reporting | D42: Data Quality; Underreporting and data inconsistency from MS | E42: Inconsistent and incomplete reporting of surveillance data by Member States leads to poor data quality, limiting effective analysis, decision-making, and timely response | F42: Weak health information systems Limited capacity in data collection, analysis, and reporting Lack of standardization in indicators and formats | G42: Operational | H42: Likely | I42: =IFERROR(IF(H42="Unlikely",1,IF(H42="Possible",2,IF(H42="Likely",3,IF(H42="Almost Certain",4,IF(H42="Certain",5,""))))),"") -> 3 | J42: Major | K42: =IFERROR(IF(J42="Negligible",1,IF(J42="Minor",2,IF(J42="Moderate",3,IF(J42="Major",4,IF(J42="Critical",5,""))))),"") -> 4 | L42: =IF(OR(I42="",K42=""),"",I42*K42) -> 12 | M42: Standardize reporting templates Conduct periodic refresher training and system audits | O42: 45930 | P42: Open - Extended | Q42: Head of Division Head of Units Senior leadership Technical staff | U42: =IF(L42="","",IF(L42<=4,"Low",IF(L42<=9,"Medium",IF(L42<=15,"High","Critical")))) -> High | W42: =IF(I42="","",MAX(1,I42-(IF(V42="Limited",1,IF(V42="Partial",2,IF(V42="Substantial",3,IF(V42="Highly Effective",4,0))))))) -> 3 | X42: =IF(K42="","",MAX(1,K42-ROUNDDOWN((IF(V42="Limited",1,IF(V42="Partial",2,IF(V42="Substantial",3,IF(V42="Highly Effective",4,0)))))/2,0))) -> 4 | Y42: =IF(OR(W42="",X42=""),"",W42*X42) -> 12 | Z42: =IF(Y42="","",IF(Y42<=4,"Low",IF(Y42<=9,"Medium",IF(Y42<=15,"High","Critical")))) -> High | AA42: =IF(OR(L42="",Y42=""),"",IF(Y42<L42,"Reduced by "&(L42-Y42)&" pts",IF(Y42=L42,"No Change","Increased by "&(Y42-L42)&" pts"))) -> No Change | AB42: =IF(Y42="","",Y42+(ROW()/10000000)) -> 12.000004
A43: 38 | B43: PHAHM | C43: 4. Program execution and delivery | D43: Achieving PAVM milestones faces significant risks related to infrastructure development, funding, technology transfer, regulatory alignment, and workforce capacity. | E43: Inability for Africa CDC to demonstrate results by 2025, 2030 and ultimately 2040 targets. | F43: 1. Funding of Manufacturing Projects underway 2. Market 3. Regulatory support - Achieving WHO PQ | G43: Project | H43: Certain | I43: =IFERROR(IF(H43="Unlikely",1,IF(H43="Possible",2,IF(H43="Likely",3,IF(H43="Almost Certain",4,IF(H43="Certain",5,""))))),"") -> 5 | J43: Major | K43: =IFERROR(IF(J43="Negligible",1,IF(J43="Minor",2,IF(J43="Moderate",3,IF(J43="Major",4,IF(J43="Critical",5,""))))),"") -> 4 | L43: =IF(OR(I43="",K43=""),"",I43*K43) -> 20 | M43: Through the mapping conducted by Africa CDC, in collaboration with CHAI and PATH, it was found 8 antigens are expected to secure WHO PQ and enter continental market between 2025 - 2030. Therefore, Africa CDC is working to see the 8 antigens to the finish line and promoting their uptake by AU Member States. | O43: 45930 | P43: Open - Extended | Q43: PHAHM Team | U43: =IF(L43="","",IF(L43<=4,"Low",IF(L43<=9,"Medium",IF(L43<=15,"High","Critical")))) -> Critical | W43: =IF(I43="","",MAX(1,I43-(IF(V43="Limited",1,IF(V43="Partial",2,IF(V43="Substantial",3,IF(V43="Highly Effective",4,0))))))) -> 5 | X43: =IF(K43="","",MAX(1,K43-ROUNDDOWN((IF(V43="Limited",1,IF(V43="Partial",2,IF(V43="Substantial",3,IF(V43="Highly Effective",4,0)))))/2,0))) -> 4 | Y43: =IF(OR(W43="",X43=""),"",W43*X43) -> 20 | Z43: =IF(Y43="","",IF(Y43<=4,"Low",IF(Y43<=9,"Medium",IF(Y43<=15,"High","Critical")))) -> Critical | AA43: =IF(OR(L43="",Y43=""),"",IF(Y43<L43,"Reduced by "&(L43-Y43)&" pts",IF(Y43=L43,"No Change","Increased by "&(Y43-L43)&" pts"))) -> No Change | AB43: =IF(Y43="","",Y43+(ROW()/10000000)) -> 20.000004
A44: 39 | B44: PHAHM | C44: 4. Program execution and delivery | D44: Lack of market for the African made vaccines | E44: Failure of Vaccine manufacturing initiative which will impact PAVM FFA targets of 60% by 2040 | F44: Member states uptake | G44: Project | H44: Possible | I44: =IFERROR(IF(H44="Unlikely",1,IF(H44="Possible",2,IF(H44="Likely",3,IF(H44="Almost Certain",4,IF(H44="Certain",5,""))))),"") -> 2 | J44: Major | K44: =IFERROR(IF(J44="Negligible",1,IF(J44="Minor",2,IF(J44="Moderate",3,IF(J44="Major",4,IF(J44="Critical",5,""))))),"") -> 4 | L44: =IF(OR(I44="",K44=""),"",I44*K44) -> 8 | M44: Extensive engagements with Member States , sensitization and promoting African made vaccines | O44: 45930 | P44: Open - Extended | Q44: PHAHM Team | U44: =IF(L44="","",IF(L44<=4,"Low",IF(L44<=9,"Medium",IF(L44<=15,"High","Critical")))) -> Medium | W44: =IF(I44="","",MAX(1,I44-(IF(V44="Limited",1,IF(V44="Partial",2,IF(V44="Substantial",3,IF(V44="Highly Effective",4,0))))))) -> 2 | X44: =IF(K44="","",MAX(1,K44-ROUNDDOWN((IF(V44="Limited",1,IF(V44="Partial",2,IF(V44="Substantial",3,IF(V44="Highly Effective",4,0)))))/2,0))) -> 4 | Y44: =IF(OR(W44="",X44=""),"",W44*X44) -> 8 | Z44: =IF(Y44="","",IF(Y44<=4,"Low",IF(Y44<=9,"Medium",IF(Y44<=15,"High","Critical")))) -> Medium | AA44: =IF(OR(L44="",Y44=""),"",IF(Y44<L44,"Reduced by "&(L44-Y44)&" pts",IF(Y44=L44,"No Change","Increased by "&(Y44-L44)&" pts"))) -> No Change | AB44: =IF(Y44="","",Y44+(ROW()/10000000)) -> 8.0000044
A45: 40 | B45: PHAHM | C45: 6. Procurement and supply chain resilience | D45: Member states not procuring through the APPM | E45: Operationalization of the APPM delayed | F45: Lack of understanding, | G45: Operational | H45: Possible | I45: =IFERROR(IF(H45="Unlikely",1,IF(H45="Possible",2,IF(H45="Likely",3,IF(H45="Almost Certain",4,IF(H45="Certain",5,""))))),"") -> 2 | J45: Critical | K45: =IFERROR(IF(J45="Negligible",1,IF(J45="Minor",2,IF(J45="Moderate",3,IF(J45="Major",4,IF(J45="Critical",5,""))))),"") -> 5 | L45: =IF(OR(I45="",K45=""),"",I45*K45) -> 10 | M45: Engagement with Member states Sensitization of Manufacturers to supply the APPM and DFIs to invest in APPM | O45: 45930 | P45: Open - Extended | Q45: PHAHM Team | U45: =IF(L45="","",IF(L45<=4,"Low",IF(L45<=9,"Medium",IF(L45<=15,"High","Critical")))) -> High | W45: =IF(I45="","",MAX(1,I45-(IF(V45="Limited",1,IF(V45="Partial",2,IF(V45="Substantial",3,IF(V45="Highly Effective",4,0))))))) -> 2 | X45: =IF(K45="","",MAX(1,K45-ROUNDDOWN((IF(V45="Limited",1,IF(V45="Partial",2,IF(V45="Substantial",3,IF(V45="Highly Effective",4,0)))))/2,0))) -> 5 | Y45: =IF(OR(W45="",X45=""),"",W45*X45) -> 10 | Z45: =IF(Y45="","",IF(Y45<=4,"Low",IF(Y45<=9,"Medium",IF(Y45<=15,"High","Critical")))) -> High | AA45: =IF(OR(L45="",Y45=""),"",IF(Y45<L45,"Reduced by "&(L45-Y45)&" pts",IF(Y45=L45,"No Change","Increased by "&(Y45-L45)&" pts"))) -> No Change | AB45: =IF(Y45="","",Y45+(ROW()/10000000)) -> 10.000004
A46: 41 | B46: PHAHM | C46: 1. Sustainable financing and resource mobilization | D46: Lack of adequate ressources to conduct all activities to support local manufacturing ecosystem | E46: Delay in procurement of Lab Equipments for African NRAs, thus hampering their regulatory functions | F46: Budget ceiling challenges + lack of appropriate ressources | G46: Financial | H46: Likely | I46: =IFERROR(IF(H46="Unlikely",1,IF(H46="Possible",2,IF(H46="Likely",3,IF(H46="Almost Certain",4,IF(H46="Certain",5,""))))),"") -> 3 | J46: Moderate | K46: =IFERROR(IF(J46="Negligible",1,IF(J46="Minor",2,IF(J46="Moderate",3,IF(J46="Major",4,IF(J46="Critical",5,""))))),"") -> 3 | L46: =IF(OR(I46="",K46=""),"",I46*K46) -> 9 | M46: Active ressource mobilization to support a maximum of NRAs | O46: 45930 | P46: Open - Extended | Q46: PHAHM Team | U46: =IF(L46="","",IF(L46<=4,"Low",IF(L46<=9,"Medium",IF(L46<=15,"High","Critical")))) -> Medium | W46: =IF(I46="","",MAX(1,I46-(IF(V46="Limited",1,IF(V46="Partial",2,IF(V46="Substantial",3,IF(V46="Highly Effective",4,0))))))) -> 3 | X46: =IF(K46="","",MAX(1,K46-ROUNDDOWN((IF(V46="Limited",1,IF(V46="Partial",2,IF(V46="Substantial",3,IF(V46="Highly Effective",4,0)))))/2,0))) -> 3 | Y46: =IF(OR(W46="",X46=""),"",W46*X46) -> 9 | Z46: =IF(Y46="","",IF(Y46<=4,"Low",IF(Y46<=9,"Medium",IF(Y46<=15,"High","Critical")))) -> Medium | AA46: =IF(OR(L46="",Y46=""),"",IF(Y46<L46,"Reduced by "&(L46-Y46)&" pts",IF(Y46=L46,"No Change","Increased by "&(Y46-L46)&" pts"))) -> No Change | AB46: =IF(Y46="","",Y46+(ROW()/10000000)) -> 9.0000046
A47: 42 | B47: PHAHM | C47: 2. Workforce sustainability and institutional capability | D47: Lack of Adequate HR at PHAHM | E47: 1. Delay in implementation of Projects 2. Staff overwhelmed and unable to follow up on all tasks 3. Quality of work 4. Strained Staff 5. Reputational damage internally and externally. | F47: Lack of Funding | G47: Operational | H47: Possible | I47: =IFERROR(IF(H47="Unlikely",1,IF(H47="Possible",2,IF(H47="Likely",3,IF(H47="Almost Certain",4,IF(H47="Certain",5,""))))),"") -> 2 | J47: Moderate | K47: =IFERROR(IF(J47="Negligible",1,IF(J47="Minor",2,IF(J47="Moderate",3,IF(J47="Major",4,IF(J47="Critical",5,""))))),"") -> 3 | L47: =IF(OR(I47="",K47=""),"",I47*K47) -> 6 | M47: 1. Develop an HR plan for PHAHM to take on additional responsabilities 2. Reaching out to partners for more support to hire more staff 3. Establishing support system between Team members to mitigate ovewhelming | O47: 45930 | P47: Open - Extended | Q47: PHAHM Team + Executive Office | U47: =IF(L47="","",IF(L47<=4,"Low",IF(L47<=9,"Medium",IF(L47<=15,"High","Critical")))) -> Medium | W47: =IF(I47="","",MAX(1,I47-(IF(V47="Limited",1,IF(V47="Partial",2,IF(V47="Substantial",3,IF(V47="Highly Effective",4,0))))))) -> 2 | X47: =IF(K47="","",MAX(1,K47-ROUNDDOWN((IF(V47="Limited",1,IF(V47="Partial",2,IF(V47="Substantial",3,IF(V47="Highly Effective",4,0)))))/2,0))) -> 3 | Y47: =IF(OR(W47="",X47=""),"",W47*X47) -> 6 | Z47: =IF(Y47="","",IF(Y47<=4,"Low",IF(Y47<=9,"Medium",IF(Y47<=15,"High","Critical")))) -> Medium | AA47: =IF(OR(L47="",Y47=""),"",IF(Y47<L47,"Reduced by "&(L47-Y47)&" pts",IF(Y47=L47,"No Change","Increased by "&(Y47-L47)&" pts"))) -> No Change | AB47: =IF(Y47="","",Y47+(ROW()/10000000)) -> 6.0000047
A48: 43 | B48: PHAHM | C48: 4. Program execution and delivery | D48: Lot of Initiatives on Local Manufacturing of health products in Africa | E48: 1. Inaccurate reporting of results 2. Loss of credibility of the Agenda 3. Reputational risk with donors. | F48: 1. Inconsistency in targets 2. Lack of coordination mechanism | G48: Contextual | H48: Likely | I48: =IFERROR(IF(H48="Unlikely",1,IF(H48="Possible",2,IF(H48="Likely",3,IF(H48="Almost Certain",4,IF(H48="Certain",5,""))))),"") -> 3 | J48: Major | K48: =IFERROR(IF(J48="Negligible",1,IF(J48="Minor",2,IF(J48="Moderate",3,IF(J48="Major",4,IF(J48="Critical",5,""))))),"") -> 4 | L48: =IF(OR(I48="",K48=""),"",I48*K48) -> 12 | M48: Engagement with all stakeholders working on Health Products Manufacturing in Africa for alignements and collaboration | O48: 45930 | P48: Open - Extended | Q48: PHAHM Team + Executive Office | U48: =IF(L48="","",IF(L48<=4,"Low",IF(L48<=9,"Medium",IF(L48<=15,"High","Critical")))) -> High | W48: =IF(I48="","",MAX(1,I48-(IF(V48="Limited",1,IF(V48="Partial",2,IF(V48="Substantial",3,IF(V48="Highly Effective",4,0))))))) -> 3 | X48: =IF(K48="","",MAX(1,K48-ROUNDDOWN((IF(V48="Limited",1,IF(V48="Partial",2,IF(V48="Substantial",3,IF(V48="Highly Effective",4,0)))))/2,0))) -> 4 | Y48: =IF(OR(W48="",X48=""),"",W48*X48) -> 12 | Z48: =IF(Y48="","",IF(Y48<=4,"Low",IF(Y48<=9,"Medium",IF(Y48<=15,"High","Critical")))) -> High | AA48: =IF(OR(L48="",Y48=""),"",IF(Y48<L48,"Reduced by "&(L48-Y48)&" pts",IF(Y48=L48,"No Change","Increased by "&(Y48-L48)&" pts"))) -> No Change | AB48: =IF(Y48="","",Y48+(ROW()/10000000)) -> 12.000005
A49: 44 | B49: PHAHM | C49: 4. Program execution and delivery | D49: Slow Approval processes of Activities | E49: Affect flexibility and rapidity to implement activities | F49: Internal delays and bottlenecks | G49: Operational | H49: Possible | I49: =IFERROR(IF(H49="Unlikely",1,IF(H49="Possible",2,IF(H49="Likely",3,IF(H49="Almost Certain",4,IF(H49="Certain",5,""))))),"") -> 2 | J49: Moderate | K49: =IFERROR(IF(J49="Negligible",1,IF(J49="Minor",2,IF(J49="Moderate",3,IF(J49="Major",4,IF(J49="Critical",5,""))))),"") -> 3 | L49: =IF(OR(I49="",K49=""),"",I49*K49) -> 6 | M49: Early planning and Approvals of activities | O49: 45930 | P49: Open - Extended | Q49: PHAHM Team | U49: =IF(L49="","",IF(L49<=4,"Low",IF(L49<=9,"Medium",IF(L49<=15,"High","Critical")))) -> Medium | W49: =IF(I49="","",MAX(1,I49-(IF(V49="Limited",1,IF(V49="Partial",2,IF(V49="Substantial",3,IF(V49="Highly Effective",4,0))))))) -> 2 | X49: =IF(K49="","",MAX(1,K49-ROUNDDOWN((IF(V49="Limited",1,IF(V49="Partial",2,IF(V49="Substantial",3,IF(V49="Highly Effective",4,0)))))/2,0))) -> 3 | Y49: =IF(OR(W49="",X49=""),"",W49*X49) -> 6 | Z49: =IF(Y49="","",IF(Y49<=4,"Low",IF(Y49<=9,"Medium",IF(Y49<=15,"High","Critical")))) -> Medium | AA49: =IF(OR(L49="",Y49=""),"",IF(Y49<L49,"Reduced by "&(L49-Y49)&" pts",IF(Y49=L49,"No Change","Increased by "&(Y49-L49)&" pts"))) -> No Change | AB49: =IF(Y49="","",Y49+(ROW()/10000000)) -> 6.0000049
A50: 45 | B50: PHAHM | C50: 6. Procurement and supply chain resilience | D50: Quality of Products procured through the APPM | E50: AU Member states not trusting Africa CDC processes and potential harming patients who consumes the products | F50: Substandards of products | G50: Reputational | H50: Possible | I50: =IFERROR(IF(H50="Unlikely",1,IF(H50="Possible",2,IF(H50="Likely",3,IF(H50="Almost Certain",4,IF(H50="Certain",5,""))))),"") -> 2 | J50: Major | K50: =IFERROR(IF(J50="Negligible",1,IF(J50="Minor",2,IF(J50="Moderate",3,IF(J50="Major",4,IF(J50="Critical",5,""))))),"") -> 4 | L50: =IF(OR(I50="",K50=""),"",I50*K50) -> 8 | M50: Africa CDC is developing Quality Assurance Framework that will ensure that products procured through APPM are of High quality and standards | O50: 45930 | P50: Open - Extended | Q50: PHAHM Team + DAC (Diagnostics) + Science Office | U50: =IF(L50="","",IF(L50<=4,"Low",IF(L50<=9,"Medium",IF(L50<=15,"High","Critical")))) -> Medium | W50: =IF(I50="","",MAX(1,I50-(IF(V50="Limited",1,IF(V50="Partial",2,IF(V50="Substantial",3,IF(V50="Highly Effective",4,0))))))) -> 2 | X50: =IF(K50="","",MAX(1,K50-ROUNDDOWN((IF(V50="Limited",1,IF(V50="Partial",2,IF(V50="Substantial",3,IF(V50="Highly Effective",4,0)))))/2,0))) -> 4 | Y50: =IF(OR(W50="",X50=""),"",W50*X50) -> 8 | Z50: =IF(Y50="","",IF(Y50<=4,"Low",IF(Y50<=9,"Medium",IF(Y50<=15,"High","Critical")))) -> Medium | AA50: =IF(OR(L50="",Y50=""),"",IF(Y50<L50,"Reduced by "&(L50-Y50)&" pts",IF(Y50=L50,"No Change","Increased by "&(Y50-L50)&" pts"))) -> No Change | AB50: =IF(Y50="","",Y50+(ROW()/10000000)) -> 8.000005
... A65: 60 | B65: Digital Health | C65: 9. Emergency readiness, duty of care, and biosafety/biosecurity | D65: Downtime and Reliability Failures | E65: Delayed responses ​ Loss of operational continuity | F65: Hardware failures, inadequate redundancy | G65: Operational | H65: Certain | I65: =IFERROR(IF(H65="Unlikely",1,IF(H65="Possible",2,IF(H65="Likely",3,IF(H65="Almost Certain",4,IF(H65="Certain",5,""))))),"") -> 5 | J65: Major | K65: =IFERROR(IF(J65="Negligible",1,IF(J65="Minor",2,IF(J65="Moderate",3,IF(J65="Major",4,IF(J65="Critical",5,""))))),"") -> 4 | L65: =IF(OR(I65="",K65=""),"",I65*K65) -> 20 | M65: Establish high availability architecture with redundancy​ Implement disaster recovery and backup plans​ Set up real-time monitoring and alerts​ Regularly test failover procedures​ | O65: 46022 | P65: Open - Extended | Q65: Africa CDC - Procurement | U65: =IF(L65="","",IF(L65<=4,"Low",IF(L65<=9,"Medium",IF(L65<=15,"High","Critical")))) -> Critical | W65: =IF(I65="","",MAX(1,I65-(IF(V65="Limited",1,IF(V65="Partial",2,IF(V65="Substantial",3,IF(V65="Highly Effective",4,0))))))) -> 5 | X65: =IF(K65="","",MAX(1,K65-ROUNDDOWN((IF(V65="Limited",1,IF(V65="Partial",2,IF(V65="Substantial",3,IF(V65="Highly Effective",4,0)))))/2,0))) -> 4 | Y65: =IF(OR(W65="",X65=""),"",W65*X65) -> 20 | Z65: =IF(Y65="","",IF(Y65<=4,"Low",IF(Y65<=9,"Medium",IF(Y65<=15,"High","Critical")))) -> Critical | AA65: =IF(OR(L65="",Y65=""),"",IF(Y65<L65,"Reduced by "&(L65-Y65)&" pts",IF(Y65=L65,"No Change","Increased by "&(Y65-L65)&" pts"))) -> No Change | AB65: =IF(Y65="","",Y65+(ROW()/10000000)) -> 20.000007
A66: 61 | B66: Digital Health | C66: 7. Data governance and management reporting | D66: Data Breaches & Privacy Violations | E66: Data leakage exposing confidential information and violate privacy regulations​ Loss of stakeholder trust | F66: Weak authentication, poor encryption, misconfigured cloud systems, inadequate access controls, or misconfigured cloud services, | G66: Operational | H66: Certain | I66: =IFERROR(IF(H66="Unlikely",1,IF(H66="Possible",2,IF(H66="Likely",3,IF(H66="Almost Certain",4,IF(H66="Certain",5,""))))),"") -> 5 | J66: Critical | K66: =IFERROR(IF(J66="Negligible",1,IF(J66="Minor",2,IF(J66="Moderate",3,IF(J66="Major",4,IF(J66="Critical",5,""))))),"") -> 5 | L66: =IF(OR(I66="",K66=""),"",I66*K66) -> 25 | M66: Enforce access control policies ​ Conduct regular audits and security training​ Use Multi-Factor Authentication (MFA) | O66: 46022 | P66: Open - Extended | U66: =IF(L66="","",IF(L66<=4,"Low",IF(L66<=9,"Medium",IF(L66<=15,"High","Critical")))) -> Critical | W66: =IF(I66="","",MAX(1,I66-(IF(V66="Limited",1,IF(V66="Partial",2,IF(V66="Substantial",3,IF(V66="Highly Effective",4,0))))))) -> 5 | X66: =IF(K66="","",MAX(1,K66-ROUNDDOWN((IF(V66="Limited",1,IF(V66="Partial",2,IF(V66="Substantial",3,IF(V66="Highly Effective",4,0)))))/2,0))) -> 5 | Y66: =IF(OR(W66="",X66=""),"",W66*X66) -> 25 | Z66: =IF(Y66="","",IF(Y66<=4,"Low",IF(Y66<=9,"Medium",IF(Y66<=15,"High","Critical")))) -> Critical | AA66: =IF(OR(L66="",Y66=""),"",IF(Y66<L66,"Reduced by "&(L66-Y66)&" pts",IF(Y66=L66,"No Change","Increased by "&(Y66-L66)&" pts"))) -> No Change | AB66: =IF(Y66="","",Y66+(ROW()/10000000)) -> 25.000007
A67: 62 | B67: Digital Health | C67: 7. Data governance and management reporting | D67: Malware & Ransomware Attacks | E67: Loss of sensitive data​ Service disruption​ Financial loss due to ransom payments​ Reputation damage | F67: Unpatched systems, weak endpoint protection | G67: Operational | H67: Certain | I67: =IFERROR(IF(H67="Unlikely",1,IF(H67="Possible",2,IF(H67="Likely",3,IF(H67="Almost Certain",4,IF(H67="Certain",5,""))))),"") -> 5 | J67: Critical | K67: =IFERROR(IF(J67="Negligible",1,IF(J67="Minor",2,IF(J67="Moderate",3,IF(J67="Major",4,IF(J67="Critical",5,""))))),"") -> 5 | L67: =IF(OR(I67="",K67=""),"",I67*K67) -> 25 | M67: Maintain regular, secure backups stored offline​ Conduct staff awareness training​ Patch systems and apps regularly​ incident response plan, backup infrastructure | O67: 46022 | P67: Open - Extended | U67: =IF(L67="","",IF(L67<=4,"Low",IF(L67<=9,"Medium",IF(L67<=15,"High","Critical")))) -> Critical | W67: =IF(I67="","",MAX(1,I67-(IF(V67="Limited",1,IF(V67="Partial",2,IF(V67="Substantial",3,IF(V67="Highly Effective",4,0))))))) -> 5 | X67: =IF(K67="","",MAX(1,K67-ROUNDDOWN((IF(V67="Limited",1,IF(V67="Partial",2,IF(V67="Substantial",3,IF(V67="Highly Effective",4,0)))))/2,0))) -> 5 | Y67: =IF(OR(W67="",X67=""),"",W67*X67) -> 25 | Z67: =IF(Y67="","",IF(Y67<=4,"Low",IF(Y67<=9,"Medium",IF(Y67<=15,"High","Critical")))) -> Critical | AA67: =IF(OR(L67="",Y67=""),"",IF(Y67<L67,"Reduced by "&(L67-Y67)&" pts",IF(Y67=L67,"No Change","Increased by "&(Y67-L67)&" pts"))) -> No Change | AB67: =IF(Y67="","",Y67+(ROW()/10000000)) -> 25.000007
A68: 63 | B68: Digital Health | C68: 7. Data governance and management reporting | D68: Weak Credential Management | E68: Unauthorized system access​ Privilege abuse​ System manipulation ​ Data leaks or loss | F68: Lack of MFA, shared or reused credentials | G68: Operational | H68: Certain | I68: =IFERROR(IF(H68="Unlikely",1,IF(H68="Possible",2,IF(H68="Likely",3,IF(H68="Almost Certain",4,IF(H68="Certain",5,""))))),"") -> 5 | J68: Major | K68: =IFERROR(IF(J68="Negligible",1,IF(J68="Minor",2,IF(J68="Moderate",3,IF(J68="Major",4,IF(J68="Critical",5,""))))),"") -> 4 | L68: =IF(OR(I68="",K68=""),"",I68*K68) -> 20 | M68: Enforce strong password policies ​ Implement MFA for all systems​ Provide user training on credential security​ BitLockers | O68: 46022 | P68: Open - Extended | U68: =IF(L68="","",IF(L68<=4,"Low",IF(L68<=9,"Medium",IF(L68<=15,"High","Critical")))) -> Critical | W68: =IF(I68="","",MAX(1,I68-(IF(V68="Limited",1,IF(V68="Partial",2,IF(V68="Substantial",3,IF(V68="Highly Effective",4,0))))))) -> 5 | X68: =IF(K68="","",MAX(1,K68-ROUNDDOWN((IF(V68="Limited",1,IF(V68="Partial",2,IF(V68="Substantial",3,IF(V68="Highly Effective",4,0)))))/2,0))) -> 4 | Y68: =IF(OR(W68="",X68=""),"",W68*X68) -> 20 | Z68: =IF(Y68="","",IF(Y68<=4,"Low",IF(Y68<=9,"Medium",IF(Y68<=15,"High","Critical")))) -> Critical | AA68: =IF(OR(L68="",Y68=""),"",IF(Y68<L68,"Reduced by "&(L68-Y68)&" pts",IF(Y68=L68,"No Change","Increased by "&(Y68-L68)&" pts"))) -> No Change | AB68: =IF(Y68="","",Y68+(ROW()/10000000)) -> 20.000007
A69: 64 | B69: Digital Health | C69: 7. Data governance and management reporting | D69: Security Misconfigurations | E69: Data exposure, access by unauthorized users​ Regulatory compliance issues​ Increased attack surface | F69: Lack of security audits, human error | G69: Operational | H69: Certain | I69: =IFERROR(IF(H69="Unlikely",1,IF(H69="Possible",2,IF(H69="Likely",3,IF(H69="Almost Certain",4,IF(H69="Certain",5,""))))),"") -> 5 | J69: Major | K69: =IFERROR(IF(J69="Negligible",1,IF(J69="Minor",2,IF(J69="Moderate",3,IF(J69="Major",4,IF(J69="Critical",5,""))))),"") -> 4 | L69: =IF(OR(I69="",K69=""),"",I69*K69) -> 20 | M69: Use security baselines and configuration templates​ Implement automated tools to detect and fix misconfigurations ​ Conduct regular configuration audits and penetration testing | O69: 46022 | P69: Open - Extended | U69: =IF(L69="","",IF(L69<=4,"Low",IF(L69<=9,"Medium",IF(L69<=15,"High","Critical")))) -> Critical | W69: =IF(I69="","",MAX(1,I69-(IF(V69="Limited",1,IF(V69="Partial",2,IF(V69="Substantial",3,IF(V69="Highly Effective",4,0))))))) -> 5 | X69: =IF(K69="","",MAX(1,K69-ROUNDDOWN((IF(V69="Limited",1,IF(V69="Partial",2,IF(V69="Substantial",3,IF(V69="Highly Effective",4,0)))))/2,0))) -> 4 | Y69: =IF(OR(W69="",X69=""),"",W69*X69) -> 20 | Z69: =IF(Y69="","",IF(Y69<=4,"Low",IF(Y69<=9,"Medium",IF(Y69<=15,"High","Critical")))) -> Critical | AA69: =IF(OR(L69="",Y69=""),"",IF(Y69<L69,"Reduced by "&(L69-Y69)&" pts",IF(Y69=L69,"No Change","Increased by "&(Y69-L69)&" pts"))) -> No Change | AB69: =IF(Y69="","",Y69+(ROW()/10000000)) -> 20.000007
A70: 65 | B70: Digital Health | C70: 7. Data governance and management reporting | D70: Non-Compliance with Data Laws | E70: Fines and legal action​ Suspension of operations​ Loss of public trust and credibility​ Exclusion from partnerships or funding opportunities | F70: Unclear policies, lack of legal expertise | G70: Compliance | H70: Certain | I70: =IFERROR(IF(H70="Unlikely",1,IF(H70="Possible",2,IF(H70="Likely",3,IF(H70="Almost Certain",4,IF(H70="Certain",5,""))))),"") -> 5 | J70: Major | K70: =IFERROR(IF(J70="Negligible",1,IF(J70="Minor",2,IF(J70="Moderate",3,IF(J70="Major",4,IF(J70="Critical",5,""))))),"") -> 4 | L70: =IF(OR(I70="",K70=""),"",I70*K70) -> 20 | M70: Regularly train staff on data privacy regulations​ Perform Data Protection Impact Assessments ​ Working with Legal experts for compliance​ | O70: 46022 | P70: Open - Extended | U70: =IF(L70="","",IF(L70<=4,"Low",IF(L70<=9,"Medium",IF(L70<=15,"High","Critical")))) -> Critical | W70: =IF(I70="","",MAX(1,I70-(IF(V70="Limited",1,IF(V70="Partial",2,IF(V70="Substantial",3,IF(V70="Highly Effective",4,0))))))) -> 5 | X70: =IF(K70="","",MAX(1,K70-ROUNDDOWN((IF(V70="Limited",1,IF(V70="Partial",2,IF(V70="Substantial",3,IF(V70="Highly Effective",4,0)))))/2,0))) -> 4 | Y70: =IF(OR(W70="",X70=""),"",W70*X70) -> 20 | Z70: =IF(Y70="","",IF(Y70<=4,"Low",IF(Y70<=9,"Medium",IF(Y70<=15,"High","Critical")))) -> Critical | AA70: =IF(OR(L70="",Y70=""),"",IF(Y70<L70,"Reduced by "&(L70-Y70)&" pts",IF(Y70=L70,"No Change","Increased by "&(Y70-L70)&" pts"))) -> No Change | AB70: =IF(Y70="","",Y70+(ROW()/10000000)) -> 20.000007
A71: 66 | B71: Digital Health | C71: 4. Program execution and delivery | D71: Lack of Standardized Best Practices | E71: Security loopholes​ Audit failures​ Increased rework and technical debt​ Project delivery delays | F71: No secure SDLC framework, absence of standards like OWASP | G71: Operational | H71: Certain | I71: =IFERROR(IF(H71="Unlikely",1,IF(H71="Possible",2,IF(H71="Likely",3,IF(H71="Almost Certain",4,IF(H71="Certain",5,""))))),"") -> 5 | J71: Moderate | K71: =IFERROR(IF(J71="Negligible",1,IF(J71="Minor",2,IF(J71="Moderate",3,IF(J71="Major",4,IF(J71="Critical",5,""))))),"") -> 3 | L71: =IF(OR(I71="",K71=""),"",I71*K71) -> 15 | M71: Develop and enforce SOPs and coding guidelines​ Conduct peer reviews and quality assurance checks​ Internal documentation | O71: 46022 | P71: Open - Extended | U71: =IF(L71="","",IF(L71<=4,"Low",IF(L71<=9,"Medium",IF(L71<=15,"High","Critical")))) -> High | W71: =IF(I71="","",MAX(1,I71-(IF(V71="Limited",1,IF(V71="Partial",2,IF(V71="Substantial",3,IF(V71="Highly Effective",4,0))))))) -> 5 | X71: =IF(K71="","",MAX(1,K71-ROUNDDOWN((IF(V71="Limited",1,IF(V71="Partial",2,IF(V71="Substantial",3,IF(V71="Highly Effective",4,0)))))/2,0))) -> 3 | Y71: =IF(OR(W71="",X71=""),"",W71*X71) -> 15 | Z71: =IF(Y71="","",IF(Y71<=4,"Low",IF(Y71<=9,"Medium",IF(Y71<=15,"High","Critical")))) -> High | AA71: =IF(OR(L71="",Y71=""),"",IF(Y71<L71,"Reduced by "&(L71-Y71)&" pts",IF(Y71=L71,"No Change","Increased by "&(Y71-L71)&" pts"))) -> No Change | AB71: =IF(Y71="","",Y71+(ROW()/10000000)) -> 15.000007
A72: 67 | B72: Digital Health | C72: 2. Workforce sustainability and institutional capability | D72: Limited Staff Capacity | E72: High error rates​ Slow implementations​ Increased system downtime​ Lack of fully functional Data Centre/CDR | F72: Limited training programs | G72: Strategic | H72: Certain | I72: =IFERROR(IF(H72="Unlikely",1,IF(H72="Possible",2,IF(H72="Likely",3,IF(H72="Almost Certain",4,IF(H72="Certain",5,""))))),"") -> 5 | J72: Major | K72: =IFERROR(IF(J72="Negligible",1,IF(J72="Minor",2,IF(J72="Moderate",3,IF(J72="Major",4,IF(J72="Critical",5,""))))),"") -> 4 | L72: =IF(OR(I72="",K72=""),"",I72*K72) -> 20 | M72: Recruit more qualified personnel or consider outsourcing​ Offer continuous training and mentoring​ Promote knowledge-sharing and cross-training​ Budget for recruitment and training​ Phaseout approach to Operationalization of Facilities | O72: 46022 | P72: Open - Extended | U72: =IF(L72="","",IF(L72<=4,"Low",IF(L72<=9,"Medium",IF(L72<=15,"High","Critical")))) -> Critical | W72: =IF(I72="","",MAX(1,I72-(IF(V72="Limited",1,IF(V72="Partial",2,IF(V72="Substantial",3,IF(V72="Highly Effective",4,0))))))) -> 5 | X72: =IF(K72="","",MAX(1,K72-ROUNDDOWN((IF(V72="Limited",1,IF(V72="Partial",2,IF(V72="Substantial",3,IF(V72="Highly Effective",4,0)))))/2,0))) -> 4 | Y72: =IF(OR(W72="",X72=""),"",W72*X72) -> 20 | Z72: =IF(Y72="","",IF(Y72<=4,"Low",IF(Y72<=9,"Medium",IF(Y72<=15,"High","Critical")))) -> Critical | AA72: =IF(OR(L72="",Y72=""),"",IF(Y72<L72,"Reduced by "&(L72-Y72)&" pts",IF(Y72=L72,"No Change","Increased by "&(Y72-L72)&" pts"))) -> No Change | AB72: =IF(Y72="","",Y72+(ROW()/10000000)) -> 20.000007
A73: 68 | B73: Digital Health | C73: 9. Emergency readiness, duty of care, and biosafety/biosecurity | D73: Overreliance on Technology | E73: Service interruptions or paralysis during outages​ Inability to operate manually​ Delays in service delivery or decision-making | F73: No fallback processes | G73: Operational | H73: Likely | I73: =IFERROR(IF(H73="Unlikely",1,IF(H73="Possible",2,IF(H73="Likely",3,IF(H73="Almost Certain",4,IF(H73="Certain",5,""))))),"") -> 3 | J73: Moderate | K73: =IFERROR(IF(J73="Negligible",1,IF(J73="Minor",2,IF(J73="Moderate",3,IF(J73="Major",4,IF(J73="Critical",5,""))))),"") -> 3 | L73: =IF(OR(I73="",K73=""),"",I73*K73) -> 9 | M73: Develop and test business continuity plans (BCPs) and manual fallback procedures​ Conduct regular system health checks and failover testing​ Train staff on non-digital procedures​ Backup infrastructure and offline tools | O73: 46022 | P73: Open - Extended | U73: =IF(L73="","",IF(L73<=4,"Low",IF(L73<=9,"Medium",IF(L73<=15,"High","Critical")))) -> Medium | W73: =IF(I73="","",MAX(1,I73-(IF(V73="Limited",1,IF(V73="Partial",2,IF(V73="Substantial",3,IF(V73="Highly Effective",4,0))))))) -> 3 | X73: =IF(K73="","",MAX(1,K73-ROUNDDOWN((IF(V73="Limited",1,IF(V73="Partial",2,IF(V73="Substantial",3,IF(V73="Highly Effective",4,0)))))/2,0))) -> 3 | Y73: =IF(OR(W73="",X73=""),"",W73*X73) -> 9 | Z73: =IF(Y73="","",IF(Y73<=4,"Low",IF(Y73<=9,"Medium",IF(Y73<=15,"High","Critical")))) -> Medium | AA73: =IF(OR(L73="",Y73=""),"",IF(Y73<L73,"Reduced by "&(L73-Y73)&" pts",IF(Y73=L73,"No Change","Increased by "&(Y73-L73)&" pts"))) -> No Change | AB73: =IF(Y73="","",Y73+(ROW()/10000000)) -> 9.0000073
A74: 69 | B74: Digital Health | C74: 7. Data governance and management reporting | D74: Biased or unsafe recommendations from algorithms | E74: Inequitable outcomes​ loss of trust | F74: raining data issues, lack of explainability | G74: Operational | H74: Possible | I74: =IFERROR(IF(H74="Unlikely",1,IF(H74="Possible",2,IF(H74="Likely",3,IF(H74="Almost Certain",4,IF(H74="Certain",5,""))))),"") -> 2 | J74: Moderate | K74: =IFERROR(IF(J74="Negligible",1,IF(J74="Minor",2,IF(J74="Moderate",3,IF(J74="Major",4,IF(J74="Critical",5,""))))),"") -> 3 | L74: =IF(OR(I74="",K74=""),"",I74*K74) -> 6 | M74: Audit models for fairness, accountability, and transparency​ Implement human-in-the-loop validation​ | O74: 46022 | P74: Open - Extended | U74: =IF(L74="","",IF(L74<=4,"Low",IF(L74<=9,"Medium",IF(L74<=15,"High","Critical")))) -> Medium | W74: =IF(I74="","",MAX(1,I74-(IF(V74="Limited",1,IF(V74="Partial",2,IF(V74="Substantial",3,IF(V74="Highly Effective",4,0))))))) -> 2 | X74: =IF(K74="","",MAX(1,K74-ROUNDDOWN((IF(V74="Limited",1,IF(V74="Partial",2,IF(V74="Substantial",3,IF(V74="Highly Effective",4,0)))))/2,0))) -> 3 | Y74: =IF(OR(W74="",X74=""),"",W74*X74) -> 6 | Z74: =IF(Y74="","",IF(Y74<=4,"Low",IF(Y74<=9,"Medium",IF(Y74<=15,"High","Critical")))) -> Medium | AA74: =IF(OR(L74="",Y74=""),"",IF(Y74<L74,"Reduced by "&(L74-Y74)&" pts",IF(Y74=L74,"No Change","Increased by "&(Y74-L74)&" pts"))) -> No Change | AB74: =IF(Y74="","",Y74+(ROW()/10000000)) -> 6.0000074
A75: 70 | B75: Digital Health | C75: 2. Workforce sustainability and institutional capability | D75: Staff risk | E75: Compromise accuracy , security and reliability data​ Breaches or loss of sensitive data​ Regulatory violations​ Loss of trust | F75: nadequate staff training Lack of awareness of policies and procedures Human error due to carelessness or fatigue Poor supervision and oversight High workload or understaffing Low motivation or job dissatisfaction Absence of accountability mechanisms Ineffective or overly complex systems Lack of automation or error-checking tools No incident reporting or learning process | G75: Operational | H75: Possible | I75: =IFERROR(IF(H75="Unlikely",1,IF(H75="Possible",2,IF(H75="Likely",3,IF(H75="Almost Certain",4,IF(H75="Certain",5,""))))),"") -> 2 | J75: Moderate | K75: =IFERROR(IF(J75="Negligible",1,IF(J75="Minor",2,IF(J75="Moderate",3,IF(J75="Major",4,IF(J75="Critical",5,""))))),"") -> 3 | L75: =IF(OR(I75="",K75=""),"",I75*K75) -> 6 | M75: Training programs on data handling, system use, and security awareness​ Use data validation checks in systems to minimize input errors​ Implement audit trails and accountability controls | O75: 46022 | P75: Open - Extended | U75: =IF(L75="","",IF(L75<=4,"Low",IF(L75<=9,"Medium",IF(L75<=15,"High","Critical")))) -> Medium | W75: =IF(I75="","",MAX(1,I75-(IF(V75="Limited",1,IF(V75="Partial",2,IF(V75="Substantial",3,IF(V75="Highly Effective",4,0))))))) -> 2 | X75: =IF(K75="","",MAX(1,K75-ROUNDDOWN((IF(V75="Limited",1,IF(V75="Partial",2,IF(V75="Substantial",3,IF(V75="Highly Effective",4,0)))))/2,0))) -> 3 | Y75: =IF(OR(W75="",X75=""),"",W75*X75) -> 6 | Z75: =IF(Y75="","",IF(Y75<=4,"Low",IF(Y75<=9,"Medium",IF(Y75<=15,"High","Critical")))) -> Medium | AA75: =IF(OR(L75="",Y75=""),"",IF(Y75<L75,"Reduced by "&(L75-Y75)&" pts",IF(Y75=L75,"No Change","Increased by "&(Y75-L75)&" pts"))) -> No Change | AB75: =IF(Y75="","",Y75+(ROW()/10000000)) -> 6.0000075
A76: 71 | B76: Digital Health | C76: 3. Fiduciary stewardship and internal control | D76: Loss of Computing Equipment | E76: Data loss (unrecoverable files, disrupted operations).​ Delayed outbreak reporting (analysis interrupted).​ Financial costs (replacement, recovery).​ Breach of sensitive MS health data (if stolen) and reputational damage | F76: Lack of asset tracking and inventory management Failure to enforce equipment handling policies Aging or outdated hardware with no replacement plan Lack of insurance or backup equipment Negligence or mishandling by staff | G76: Operational | H76: Likely | I76: =IFERROR(IF(H76="Unlikely",1,IF(H76="Possible",2,IF(H76="Likely",3,IF(H76="Almost Certain",4,IF(H76="Certain",5,""))))),"") -> 3 | J76: Major | K76: =IFERROR(IF(J76="Negligible",1,IF(J76="Minor",2,IF(J76="Moderate",3,IF(J76="Major",4,IF(J76="Critical",5,""))))),"") -> 4 | L76: =IF(OR(I76="",K76=""),"",I76*K76) -> 12 | M76: Physical Security: Locked storage, CCTV, and equipment tracking (e.g., RFID tags).​ Data Backups: Automated daily cloud backups + offline storage.​ Maintenance: Regular hardware checks and IT support contracts.​ Insurance: Cover for theft/damage of critical equipment.​ BYOD Policy: Allow staff to use secured personal devices as backup. | O76: 46022 | P76: Open - Extended | U76: =IF(L76="","",IF(L76<=4,"Low",IF(L76<=9,"Medium",IF(L76<=15,"High","Critical")))) -> High | W76: =IF(I76="","",MAX(1,I76-(IF(V76="Limited",1,IF(V76="Partial",2,IF(V76="Substantial",3,IF(V76="Highly Effective",4,0))))))) -> 3 | X76: =IF(K76="","",MAX(1,K76-ROUNDDOWN((IF(V76="Limited",1,IF(V76="Partial",2,IF(V76="Substantial",3,IF(V76="Highly Effective",4,0)))))/2,0))) -> 4 | Y76: =IF(OR(W76="",X76=""),"",W76*X76) -> 12 | Z76: =IF(Y76="","",IF(Y76<=4,"Low",IF(Y76<=9,"Medium",IF(Y76<=15,"High","Critical")))) -> High | AA76: =IF(OR(L76="",Y76=""),"",IF(Y76<L76,"Reduced by "&(L76-Y76)&" pts",IF(Y76=L76,"No Change","Increased by "&(Y76-L76)&" pts"))) -> No Change | AB76: =IF(Y76="","",Y76+(ROW()/10000000)) -> 12.000008
A77: 72 | B77: Digital Health | C77: 9. Emergency readiness, duty of care, and biosafety/biosecurity | D77: Non-Compliance with Disaster Recovery and Business Continuity Plan | E77: Prolonged outages​ Loss of critical data​ Delays in service restoration​ Ineffective disaster response​ Extended service downtime​ Loss of critical data or access | F77: Lack of awareness or training on the plan Inadequate enforcement or oversight mechanisms Outdated or poorly communicated procedures Limited testing or simulation of the recovery plan | G77: Operational | H77: Likely | I77: =IFERROR(IF(H77="Unlikely",1,IF(H77="Possible",2,IF(H77="Likely",3,IF(H77="Almost Certain",4,IF(H77="Certain",5,""))))),"") -> 3 | J77: Major | K77: =IFERROR(IF(J77="Negligible",1,IF(J77="Minor",2,IF(J77="Moderate",3,IF(J77="Major",4,IF(J77="Critical",5,""))))),"") -> 4 | L77: =IF(OR(I77="",K77=""),"",I77*K77) -> 12 | M77: Recovery infrastructure:Offsite backup recovery ​ Test and update recovery plans​ Refine the plan based on lessons from test outcomes​ Integrate DRP testing as part of the BCP process​ | O77: 46022 | P77: Open - Extended | U77: =IF(L77="","",IF(L77<=4,"Low",IF(L77<=9,"Medium",IF(L77<=15,"High","Critical")))) -> High | W77: =IF(I77="","",MAX(1,I77-(IF(V77="Limited",1,IF(V77="Partial",2,IF(V77="Substantial",3,IF(V77="Highly Effective",4,0))))))) -> 3 | X77: =IF(K77="","",MAX(1,K77-ROUNDDOWN((IF(V77="Limited",1,IF(V77="Partial",2,IF(V77="Substantial",3,IF(V77="Highly Effective",4,0)))))/2,0))) -> 4 | Y77: =IF(OR(W77="",X77=""),"",W77*X77) -> 12 | Z77: =IF(Y77="","",IF(Y77<=4,"Low",IF(Y77<=9,"Medium",IF(Y77<=15,"High","Critical")))) -> High | AA77: =IF(OR(L77="",Y77=""),"",IF(Y77<L77,"Reduced by "&(L77-Y77)&" pts",IF(Y77=L77,"No Change","Increased by "&(Y77-L77)&" pts"))) -> No Change | AB77: =IF(Y77="","",Y77+(ROW()/10000000)) -> 12.000008
... A106: 101 | B106: Supply Chain/ Procurement | C106: 6. Procurement and supply chain resilience | D106: Fragmentation of Supply Chain Systems Across Countries | E106: If supply chain activities remain fragmented, then each country will continue to “go it alone,” leading to duplication of efforts, higher collective costs, and inconsistency in supply availability. For instance, one country might experience surplus vaccine wastage while a neighbor faces a shortage, simply because systems aren’t linked to redistribute supplies. Fragmentation also means that successful innovations or practices in one program may not be transferred to others, slowing overall improvement in Africa’s health supply chain performance. | F106: Historical siloed approaches to health programs; programs and donors working independently within countries; lack of interoperable systems and standards; limited incentives for countries to share resources or align procurement especially as Africa CDC move to implement the Africa pool procurement mechanism | G106: Strategic | H106: Almost Certain | I106: =IFERROR(IF(H106="Unlikely",1,IF(H106="Possible",2,IF(H106="Likely",3,IF(H106="Almost Certain",4,IF(H106="Certain",5,""))))),"") -> 4 | J106: Moderate | K106: =IFERROR(IF(J106="Negligible",1,IF(J106="Minor",2,IF(J106="Moderate",3,IF(J106="Major",4,IF(J106="Critical",5,""))))),"") -> 3 | L106: =IF(OR(I106="",K106=""),"",I106*K106) -> 12 | M106: Complete the continental supply chain snapshot profile assesement to determine continental and Member states supply chain maturity Expedite operationalisation of the Africa CDC Pooled Procurement Mechanism Facilitate the development and deployment of interoperable supply chain data platforms that allow for shared inventory tracking, demand forecasting, and logistics planning across borders. Promote bilateral and multilateral logistics coordination agreements (e.g., joint warehousing, shared distribution routes) among neighboring countries and RECs. Establish a continental supply chain integration taskforce under Africa CDC to guide harmonization of standards, policies, and platforms. Launch regional joint planning forums involving ministries of health, finance, customs, and logistics providers to align supply chain investments and operations. Develop and support regional supply chain hubs capable of serving multiple countries with warehousing, prepositioning, and cold chain infrastructure. Support policy harmonization across Member States for regulatory alignment in procurement, customs clearance, and emergency response logistics. | O106: 46022 | P106: In Progress | U106: =IF(L106="","",IF(L106<=4,"Low",IF(L106<=9,"Medium",IF(L106<=15,"High","Critical")))) -> High | W106: =IF(I106="","",MAX(1,I106-(IF(V106="Limited",1,IF(V106="Partial",2,IF(V106="Substantial",3,IF(V106="Highly Effective",4,0))))))) -> 4 | X106: =IF(K106="","",MAX(1,K106-ROUNDDOWN((IF(V106="Limited",1,IF(V106="Partial",2,IF(V106="Substantial",3,IF(V106="Highly Effective",4,0)))))/2,0))) -> 3 | Y106: =IF(OR(W106="",X106=""),"",W106*X106) -> 12 | Z106: =IF(Y106="","",IF(Y106<=4,"Low",IF(Y106<=9,"Medium",IF(Y106<=15,"High","Critical")))) -> High | AA106: =IF(OR(L106="",Y106=""),"",IF(Y106<L106,"Reduced by "&(L106-Y106)&" pts",IF(Y106=L106,"No Change","Increased by "&(Y106-L106)&" pts"))) -> No Change | AB106: =IF(Y106="","",Y106+(ROW()/10000000)) -> 12.000011
A107: 102 | B107: Supply Chain/ Procurement | C107: 6. Procurement and supply chain resilience | D107: Inadequate Infrastructure (Warehousing, Cold Chain, and Logistics) | E107: If warehousing capacity remains low and cold chain equipment is lacking, then essential medicines and vaccines may not be stored or transported under proper conditions, leading to stockouts or unusable (spoiled) medical products. In practical terms, during a health crisis, supplies might pile up at central depots unable to reach peripheral clinics in time, or vaccines could arrive damaged due to broken cold chains. Routine health programs would also suffer, as inadequate storage and transport cause chronic delays in delivering supplies to hospitals and patients. Unavailability of central and regional warehouse for Africa CDC limits the ability to preposition stocks for emergencies. | F107: Historical underinvestment in health supply chain infrastructure; insufficient cold chain equipment for vaccines and temperature-sensitive goods; poor maintenance of existing warehouses or fleet; lack of regional and central continental warehouse for Africa CDC; geographic challenges (remote areas hard to reach); lack of capital for new infrastructure development; unreliable utilities (power for cold storage | G107: Project | H107: Likely | I107: =IFERROR(IF(H107="Unlikely",1,IF(H107="Possible",2,IF(H107="Likely",3,IF(H107="Almost Certain",4,IF(H107="Certain",5,""))))),"") -> 3 | J107: Major | K107: =IFERROR(IF(J107="Negligible",1,IF(J107="Minor",2,IF(J107="Moderate",3,IF(J107="Major",4,IF(J107="Critical",5,""))))),"") -> 4 | L107: =IF(OR(I107="",K107=""),"",I107*K107) -> 12 | M107: validate and finalise warehouse landscape analysis and Africa CDC warehouse strategy. Establish regional and continental warehousing hubs for Africa CDC in strategic locations to support buffer stock management and faster deployment of emergency commodities. Support procurement and deployment of solar-powered cold chain equipment in areas with unreliable power supply. Integrate infrastructure resilience into national supply chain master plans, encouraging governments to adopt long-term investment strategies. Promote a continental logistics network framework for harmonized movement and storage of medical commodities, ensuring interoperability across countries thorough the MEDFLOW Africa Project of the SUpply Chain Division | P107: In Progress | U107: =IF(L107="","",IF(L107<=4,"Low",IF(L107<=9,"Medium",IF(L107<=15,"High","Critical")))) -> High | W107: =IF(I107="","",MAX(1,I107-(IF(V107="Limited",1,IF(V107="Partial",2,IF(V107="Substantial",3,IF(V107="Highly Effective",4,0))))))) -> 3 | X107: =IF(K107="","",MAX(1,K107-ROUNDDOWN((IF(V107="Limited",1,IF(V107="Partial",2,IF(V107="Substantial",3,IF(V107="Highly Effective",4,0)))))/2,0))) -> 4 | Y107: =IF(OR(W107="",X107=""),"",W107*X107) -> 12 | Z107: =IF(Y107="","",IF(Y107<=4,"Low",IF(Y107<=9,"Medium",IF(Y107<=15,"High","Critical")))) -> High | AA107: =IF(OR(L107="",Y107=""),"",IF(Y107<L107,"Reduced by "&(L107-Y107)&" pts",IF(Y107=L107,"No Change","Increased by "&(Y107-L107)&" pts"))) -> No Change | AB107: =IF(Y107="","",Y107+(ROW()/10000000)) -> 12.000011
A108: 103 | B108: Supply Chain/ Procurement | C108: 6. Procurement and supply chain resilience | D108: Late Submission of Travel Requests | E108: If travel requests are not submitted on time, then flights may become more expensive, impacting cost-efficiency and potentially leading to overspending. If preferred flights are unavailable, then field missions may be delayed or rescheduled, affecting delivery of technical assistance, field coordination, or emergency response timelines. | G108: Operational | H108: Likely | I108: =IFERROR(IF(H108="Unlikely",1,IF(H108="Possible",2,IF(H108="Likely",3,IF(H108="Almost Certain",4,IF(H108="Certain",5,""))))),"") -> 3 | J108: Moderate | K108: =IFERROR(IF(J108="Negligible",1,IF(J108="Minor",2,IF(J108="Moderate",3,IF(J108="Major",4,IF(J108="Critical",5,""))))),"") -> 3 | L108: =IF(OR(I108="",K108=""),"",I108*K108) -> 9 | P108: In Progress | U108: =IF(L108="","",IF(L108<=4,"Low",IF(L108<=9,"Medium",IF(L108<=15,"High","Critical")))) -> Medium | W108: =IF(I108="","",MAX(1,I108-(IF(V108="Limited",1,IF(V108="Partial",2,IF(V108="Substantial",3,IF(V108="Highly Effective",4,0))))))) -> 3 | X108: =IF(K108="","",MAX(1,K108-ROUNDDOWN((IF(V108="Limited",1,IF(V108="Partial",2,IF(V108="Substantial",3,IF(V108="Highly Effective",4,0)))))/2,0))) -> 3 | Y108: =IF(OR(W108="",X108=""),"",W108*X108) -> 9 | Z108: =IF(Y108="","",IF(Y108<=4,"Low",IF(Y108<=9,"Medium",IF(Y108<=15,"High","Critical")))) -> Medium | AA108: =IF(OR(L108="",Y108=""),"",IF(Y108<L108,"Reduced by "&(L108-Y108)&" pts",IF(Y108=L108,"No Change","Increased by "&(Y108-L108)&" pts"))) -> No Change | AB108: =IF(Y108="","",Y108+(ROW()/10000000)) -> 9.0000108
A109: 104 | B109: Supply Chain/ Procurement | C109: 8. Integrity, compliance, and safeguarding | D109: Non Compliance of Travel Policy in relation to submission date, number of travel days etc. | E109: If policy non-compliance continues undetected, the institution may be subject to internal or external audit issues, incur excessive travel costs, or weaken its institutional accountability posture. If manual systems persist, policy violations may become normalized, undermining AU-wide harmonization efforts. | F109: Absence of SAP configuration to enforce the 21-day mission duration limit. Manual travel request processes without digital policy checks. Weak tracking and oversight of cumulative mission durations. Limited awareness of the policy by planners or supervisors. | G109: Compliance | H109: Likely | I109: =IFERROR(IF(H109="Unlikely",1,IF(H109="Possible",2,IF(H109="Likely",3,IF(H109="Almost Certain",4,IF(H109="Certain",5,""))))),"") -> 3 | J109: Moderate | K109: =IFERROR(IF(J109="Negligible",1,IF(J109="Minor",2,IF(J109="Moderate",3,IF(J109="Major",4,IF(J109="Critical",5,""))))),"") -> 3 | L109: =IF(OR(I109="",K109=""),"",I109*K109) -> 9 | M109: Develop IT tool to automatically enforce or flag violations of the travel duration policy. Include triggers that prevent approval of non compliant submissions unless exempted categories apply. Train administrative officers, HR, logistics planners, and program leads on the AU travel policy, with regular refreshers and job aids on compliance responsibilities. Develop and disseminate simplified policy guidance documents to ensure wide staff awareness—highlighting allowable exceptions and consequences for violations. Institutionalize travel audits as part of quarterly operational reviews, with findings shared with directors and unit heads. | P109: Not Started | U109: =IF(L109="","",IF(L109<=4,"Low",IF(L109<=9,"Medium",IF(L109<=15,"High","Critical")))) -> Medium | W109: =IF(I109="","",MAX(1,I109-(IF(V109="Limited",1,IF(V109="Partial",2,IF(V109="Substantial",3,IF(V109="Highly Effective",4,0))))))) -> 3 | X109: =IF(K109="","",MAX(1,K109-ROUNDDOWN((IF(V109="Limited",1,IF(V109="Partial",2,IF(V109="Substantial",3,IF(V109="Highly Effective",4,0)))))/2,0))) -> 3 | Y109: =IF(OR(W109="",X109=""),"",W109*X109) -> 9 | Z109: =IF(Y109="","",IF(Y109<=4,"Low",IF(Y109<=9,"Medium",IF(Y109<=15,"High","Critical")))) -> Medium | AA109: =IF(OR(L109="",Y109=""),"",IF(Y109<L109,"Reduced by "&(L109-Y109)&" pts",IF(Y109=L109,"No Change","Increased by "&(Y109-L109)&" pts"))) -> No Change | AB109: =IF(Y109="","",Y109+(ROW()/10000000)) -> 9.0000109
A110: 105 | B110: Supply Chain/ Procurement | C110: 6. Procurement and supply chain resilience | D110: Poor Supplier Performance and Contract Management | E110: If supplier issues are not addressed proactively, then repeated service failures may occur, affecting project timelines, increasing operational costs, leading to emergency procurement or supplier blacklisting, and ultimately damaging organizational credibility. | G110: Operational | H110: Likely | I110: =IFERROR(IF(H110="Unlikely",1,IF(H110="Possible",2,IF(H110="Likely",3,IF(H110="Almost Certain",4,IF(H110="Certain",5,""))))),"") -> 3 | J110: Major | K110: =IFERROR(IF(J110="Negligible",1,IF(J110="Minor",2,IF(J110="Moderate",3,IF(J110="Major",4,IF(J110="Critical",5,""))))),"") -> 4 | L110: =IF(OR(I110="",K110=""),"",I110*K110) -> 12 | M110: Establish a centralized supplier prequalification system, including due diligence criteria such as financial capacity, past performance, references, and technical capability. Introduce detailed Service Level Agreements (SLAs) and Key Performance Indicators (KPIs) into procurement contracts to define acceptable service and delivery timelines. Conduct regular supplier performance reviews (e.g., quarterly evaluations) and maintain a performance scorecard to inform future contracting decisions. Develop a supplier grievance redress mechanism and escalation matrix to swiftly address disputes, delays, or contract breaches. Include penalty clauses and incentives in contracts to reinforce compliance and reward superior performance. Train procurement and contract management officers on vendor risk management, contract negotiation, and monitoring frameworks. Digitize procurement processes, integrating supplier evaluation tools into e-procurement platforms for continuous monitoring and reporting. Engage in vendor development programs to build the capacity of local/regional suppliers and reduce reliance on underperforming contractors. Collaborate with other AU bodies, RECs, and donor agencies to share blacklists, preferred vendor lists, and procurement intelligence. | P110: Open - Extended | U110: =IF(L110="","",IF(L110<=4,"Low",IF(L110<=9,"Medium",IF(L110<=15,"High","Critical")))) -> High | W110: =IF(I110="","",MAX(1,I110-(IF(V110="Limited",1,IF(V110="Partial",2,IF(V110="Substantial",3,IF(V110="Highly Effective",4,0))))))) -> 3 | X110: =IF(K110="","",MAX(1,K110-ROUNDDOWN((IF(V110="Limited",1,IF(V110="Partial",2,IF(V110="Substantial",3,IF(V110="Highly Effective",4,0)))))/2,0))) -> 4 | Y110: =IF(OR(W110="",X110=""),"",W110*X110) -> 12 | Z110: =IF(Y110="","",IF(Y110<=4,"Low",IF(Y110<=9,"Medium",IF(Y110<=15,"High","Critical")))) -> High | AA110: =IF(OR(L110="",Y110=""),"",IF(Y110<L110,"Reduced by "&(L110-Y110)&" pts",IF(Y110=L110,"No Change","Increased by "&(Y110-L110)&" pts"))) -> No Change | AB110: =IF(Y110="","",Y110+(ROW()/10000000)) -> 12.000011
A111: 106 | B111: Supply Chain/ Procurement | C111: 6. Procurement and supply chain resilience | D111: Lengthy Procurement Process and Approval Delays | E111: If procurement actions are significantly delayed, then critical project timelines may be missed, emergency interventions may fail to launch on time, partner confidence may decline, and the Africa CDC credibility could suffer. | G111: Operational | H111: Almost Certain | I111: =IFERROR(IF(H111="Unlikely",1,IF(H111="Possible",2,IF(H111="Likely",3,IF(H111="Almost Certain",4,IF(H111="Certain",5,""))))),"") -> 4 | J111: Major | K111: =IFERROR(IF(J111="Negligible",1,IF(J111="Minor",2,IF(J111="Moderate",3,IF(J111="Major",4,IF(J111="Critical",5,""))))),"") -> 4 | L111: =IF(OR(I111="",K111=""),"",I111*K111) -> 16 | M111: Review and update the Standard Operating Procedures (SOPs) for procurement and approvals, detailing clear process flows, timeframes, and responsibilities. Conduct a procurement process mapping and bottleneck analysis to identify and address redundant layers and approval delays. Establish Long-Term Agreements (LTAs)/Framework Contracts with pre-qualified suppliers for commonly procured goods and services to reduce repetitive bidding cycles. Review and streamline approval thresholds, delegating authority where appropriate to expedite lower-value procurement and operational purchases. Introduce automated procurement workflow tools (within SAP or equivalent platforms) to enable real-time tracking, digital approvals, and audit trails. Train procurement and program staff on efficient procurement planning, scheduling, and documentation to reduce rework and delays. Embed procurement planning into annual workplans and budgets, ensuring timely requisition and alignment with program implementation schedules. Integrate procurement risk management practices, including scenario planning for high-risk or urgent procurements. | P111: In Progress | U111: =IF(L111="","",IF(L111<=4,"Low",IF(L111<=9,"Medium",IF(L111<=15,"High","Critical")))) -> Critical | W111: =IF(I111="","",MAX(1,I111-(IF(V111="Limited",1,IF(V111="Partial",2,IF(V111="Substantial",3,IF(V111="Highly Effective",4,0))))))) -> 4 | X111: =IF(K111="","",MAX(1,K111-ROUNDDOWN((IF(V111="Limited",1,IF(V111="Partial",2,IF(V111="Substantial",3,IF(V111="Highly Effective",4,0)))))/2,0))) -> 4 | Y111: =IF(OR(W111="",X111=""),"",W111*X111) -> 16 | Z111: =IF(Y111="","",IF(Y111<=4,"Low",IF(Y111<=9,"Medium",IF(Y111<=15,"High","Critical")))) -> Critical | AA111: =IF(OR(L111="",Y111=""),"",IF(Y111<L111,"Reduced by "&(L111-Y111)&" pts",IF(Y111=L111,"No Change","Increased by "&(Y111-L111)&" pts"))) -> No Change | AB111: =IF(Y111="","",Y111+(ROW()/10000000)) -> 16.000011
A112: 107 | B112: Supply Chain/ Procurement | C112: 6. Procurement and supply chain resilience | D112: Delayed Payments to Suppliers | E112: If payments keep getting delayed, suppliers may lose trust and stop working with Africa CDC. This could lead to late delivery of important goods, the need to buy items urgently at higher prices, and possible legal issues because of delayed payment. | G112: Financial | H112: Certain | I112: =IFERROR(IF(H112="Unlikely",1,IF(H112="Possible",2,IF(H112="Likely",3,IF(H112="Almost Certain",4,IF(H112="Certain",5,""))))),"") -> 5 | J112: Major | K112: =IFERROR(IF(J112="Negligible",1,IF(J112="Minor",2,IF(J112="Moderate",3,IF(J112="Major",4,IF(J112="Critical",5,""))))),"") -> 4 | L112: =IF(OR(I112="",K112=""),"",I112*K112) -> 20 | M112: Establish a supplier payment tracking dashboard integrated with SAP or equivalent ERP systems to monitor real-time payment statuses and flag overdue transactions. Conduct an internal workflow audit of the end-to-end payment process to identify bottlenecks and areas causing delays (e.g., approval queues, documentation gaps, finance coordination). Create a supplier grievance redress mechanism, where payment issues can be flagged and resolved in a time-bound manner. Digitize the full procure-to-pay (P2P) process across all departments to eliminate manual documentation delays and improve transparency. Introduce advance payment mechanisms (e.g., partial advance or milestone payments) in critical supply contracts to mitigate supplier cash flow risks. | P112: In Progress | U112: =IF(L112="","",IF(L112<=4,"Low",IF(L112<=9,"Medium",IF(L112<=15,"High","Critical")))) -> Critical | W112: =IF(I112="","",MAX(1,I112-(IF(V112="Limited",1,IF(V112="Partial",2,IF(V112="Substantial",3,IF(V112="Highly Effective",4,0))))))) -> 5 | X112: =IF(K112="","",MAX(1,K112-ROUNDDOWN((IF(V112="Limited",1,IF(V112="Partial",2,IF(V112="Substantial",3,IF(V112="Highly Effective",4,0)))))/2,0))) -> 4 | Y112: =IF(OR(W112="",X112=""),"",W112*X112) -> 20 | Z112: =IF(Y112="","",IF(Y112<=4,"Low",IF(Y112<=9,"Medium",IF(Y112<=15,"High","Critical")))) -> Critical | AA112: =IF(OR(L112="",Y112=""),"",IF(Y112<L112,"Reduced by "&(L112-Y112)&" pts",IF(Y112=L112,"No Change","Increased by "&(Y112-L112)&" pts"))) -> No Change | AB112: =IF(Y112="","",Y112+(ROW()/10000000)) -> 20.000011
A113: 108 | B113: Supply Chain/ Procurement | C113: 2. Workforce sustainability and institutional capability | D113: Insufficient Procurement Manpower | E113: If manpower remains insufficient, then procurement cycles may be prolonged, strategic sourcing may suffer, and overall procurement compliance and efficiency may affect. This could result in service delivery delays, supplier dissatisfaction, and missed opportunities for value for money. | G113: Operational | H113: Certain | I113: =IFERROR(IF(H113="Unlikely",1,IF(H113="Possible",2,IF(H113="Likely",3,IF(H113="Almost Certain",4,IF(H113="Certain",5,""))))),"") -> 5 | J113: Major | K113: =IFERROR(IF(J113="Negligible",1,IF(J113="Minor",2,IF(J113="Moderate",3,IF(J113="Major",4,IF(J113="Critical",5,""))))),"") -> 4 | L113: =IF(OR(I113="",K113=""),"",I113*K113) -> 20 | U113: =IF(L113="","",IF(L113<=4,"Low",IF(L113<=9,"Medium",IF(L113<=15,"High","Critical")))) -> Critical | W113: =IF(I113="","",MAX(1,I113-(IF(V113="Limited",1,IF(V113="Partial",2,IF(V113="Substantial",3,IF(V113="Highly Effective",4,0))))))) -> 5 | X113: =IF(K113="","",MAX(1,K113-ROUNDDOWN((IF(V113="Limited",1,IF(V113="Partial",2,IF(V113="Substantial",3,IF(V113="Highly Effective",4,0)))))/2,0))) -> 4 | Y113: =IF(OR(W113="",X113=""),"",W113*X113) -> 20 | Z113: =IF(Y113="","",IF(Y113<=4,"Low",IF(Y113<=9,"Medium",IF(Y113<=15,"High","Critical")))) -> Critical | AA113: =IF(OR(L113="",Y113=""),"",IF(Y113<L113,"Reduced by "&(L113-Y113)&" pts",IF(Y113=L113,"No Change","Increased by "&(Y113-L113)&" pts"))) -> No Change | AB113: =IF(Y113="","",Y113+(ROW()/10000000)) -> 20.000011
A114: 109 | B114: Supply Chain/ Procurement | C114: 3. Fiduciary stewardship and internal control | D114: Delayed Fund Disbursement | E114: If fund disbursements are delayed, then procurement timelines will be negatively impacted, leading to missed project milestones, strained supplier relationships, potential penalties, and disruptions in program implementation. Create pressure and negative impact on staff wellbeing. | G114: Financial | H114: Almost Certain | I114: =IFERROR(IF(H114="Unlikely",1,IF(H114="Possible",2,IF(H114="Likely",3,IF(H114="Almost Certain",4,IF(H114="Certain",5,""))))),"") -> 4 | J114: Major | K114: =IFERROR(IF(J114="Negligible",1,IF(J114="Minor",2,IF(J114="Moderate",3,IF(J114="Major",4,IF(J114="Critical",5,""))))),"") -> 4 | L114: =IF(OR(I114="",K114=""),"",I114*K114) -> 16 | M114: Implement a financial disbursement monitoring dashboard to track the status of fund requests, approvals, and releases in real time. Establish fund release schedule alignment mechanisms between finance, procurement, and program teams to synchronize timelines and minimize delays. Introduce pre-authorization arrangements or standing financial approvals for recurring and urgent programmatic needs to reduce administrative lags. Set up quarterly cash flow forecasts and fund requirement plans to improve donor engagement and internal preparedness for upcoming disbursements. Designate a fund disbursement liaison officer to facilitate prompt follow-up between program units, finance departments, and donor reporting units. Automate internal approval workflows for fund disbursements using the Africa CDC ERP (SAP or equivalent) system to reduce manual bottlenecks. Establish framework agreements with donors and partners to enable timely drawdowns and flexible fund utilization mechanisms for ongoing grants. Develop risk-adjusted financial contingency plans, including buffer funding for priority interventions to bridge delays in disbursement cycles. Institutionalize regular donor-finance-program joint planning sessions to increase visibility and trust, reducing disbursement friction and ensuring synchronized resource deployment. | U114: =IF(L114="","",IF(L114<=4,"Low",IF(L114<=9,"Medium",IF(L114<=15,"High","Critical")))) -> Critical | W114: =IF(I114="","",MAX(1,I114-(IF(V114="Limited",1,IF(V114="Partial",2,IF(V114="Substantial",3,IF(V114="Highly Effective",4,0))))))) -> 4 | X114: =IF(K114="","",MAX(1,K114-ROUNDDOWN((IF(V114="Limited",1,IF(V114="Partial",2,IF(V114="Substantial",3,IF(V114="Highly Effective",4,0)))))/2,0))) -> 4 | Y114: =IF(OR(W114="",X114=""),"",W114*X114) -> 16 | Z114: =IF(Y114="","",IF(Y114<=4,"Low",IF(Y114<=9,"Medium",IF(Y114<=15,"High","Critical")))) -> Critical | AA114: =IF(OR(L114="",Y114=""),"",IF(Y114<L114,"Reduced by "&(L114-Y114)&" pts",IF(Y114=L114,"No Change","Increased by "&(Y114-L114)&" pts"))) -> No Change | AB114: =IF(Y114="","",Y114+(ROW()/10000000)) -> 16.000011
A115: 110 | B115: Supply Chain/ Procurement | C115: 6. Procurement and supply chain resilience | D115: Delayed Initiation of Procurement by Technical Divisions | E115: If divisions fail to initiate procurement in line with the procurement plan, then: Planned activities may be delayed or canceled Emergency procurement may become necessary, increasing risk and cost Supplier relationships may be strained by last-minute requests. Rushing to procurement process may open a door for suppliers to take advantage over costs, quality, and delivery factors. Procurement office will be positioned in a poor position to influence procurement processes and secure the best value for money. Procurement may not be able to secure the advantage of Africa CDC and secure the best value for money. Organizational credibility and donor trust may be compromised | G115: Operational | H115: Certain | I115: =IFERROR(IF(H115="Unlikely",1,IF(H115="Possible",2,IF(H115="Likely",3,IF(H115="Almost Certain",4,IF(H115="Certain",5,""))))),"") -> 5 | J115: Major | K115: =IFERROR(IF(J115="Negligible",1,IF(J115="Minor",2,IF(J115="Moderate",3,IF(J115="Major",4,IF(J115="Critical",5,""))))),"") -> 4 | L115: =IF(OR(I115="",K115=""),"",I115*K115) -> 20 | M115: Conduct regular training and sensitization sessions for technical divisions on procurement timelines, planning cycles, and standard operating procedures (SOPs). Develop and disseminate a user-friendly procurement calendar that clearly outlines deadlines, lead times, and required submission windows by activity type. Establish quarterly procurement planning meetings between the Procurement Unit and technical divisions to review progress against the approved plan and address bottlenecks. Set up a digital notification and tracking system within SAP or equivalent tools to alert divisions when procurement initiation deadlines are approaching or overdue. Develop procurement request templates and checklists that simplify initiation and reduce errors or back-and-forth during review. | U115: =IF(L115="","",IF(L115<=4,"Low",IF(L115<=9,"Medium",IF(L115<=15,"High","Critical")))) -> Critical | W115: =IF(I115="","",MAX(1,I115-(IF(V115="Limited",1,IF(V115="Partial",2,IF(V115="Substantial",3,IF(V115="Highly Effective",4,0))))))) -> 5 | X115: =IF(K115="","",MAX(1,K115-ROUNDDOWN((IF(V115="Limited",1,IF(V115="Partial",2,IF(V115="Substantial",3,IF(V115="Highly Effective",4,0)))))/2,0))) -> 4 | Y115: =IF(OR(W115="",X115=""),"",W115*X115) -> 20 | Z115: =IF(Y115="","",IF(Y115<=4,"Low",IF(Y115<=9,"Medium",IF(Y115<=15,"High","Critical")))) -> Critical | AA115: =IF(OR(L115="",Y115=""),"",IF(Y115<L115,"Reduced by "&(L115-Y115)&" pts",IF(Y115=L115,"No Change","Increased by "&(Y115-L115)&" pts"))) -> No Change | AB115: =IF(Y115="","",Y115+(ROW()/10000000)) -> 20.000011
A116: 111 | B116: Supply Chain/ Procurement | C116: 8. Integrity, compliance, and safeguarding | D116: Non-compliance with Procurement Policies and Procedures | E116: If there is non-compliance with Procurement Policies and Procedures then there will be Financial Loss – Poor value for money, payment for substandard goods or services. Delay in supplier payment caused by failure to strictly follow established procurement policies and procedures. Reduced Stakeholder Trust – Partners, donors, etc in the procurement process. Risk of breaching donor or internal audit requirements | G116: Compliance | H116: Likely | I116: =IFERROR(IF(H116="Unlikely",1,IF(H116="Possible",2,IF(H116="Likely",3,IF(H116="Almost Certain",4,IF(H116="Certain",5,""))))),"") -> 3 | J116: Critical | K116: =IFERROR(IF(J116="Negligible",1,IF(J116="Minor",2,IF(J116="Moderate",3,IF(J116="Major",4,IF(J116="Critical",5,""))))),"") -> 5 | L116: =IF(OR(I116="",K116=""),"",I116*K116) -> 15 | M116: Conduct mandatory procurement compliance training and refresher courses for all relevant staff, especially technical officers and project managers involved in initiating procurement. Circulate simplified procurement process flowcharts and checklists that summarize key policies and steps for internal use and display them prominently within divisions. Implement a procurement audit trail system to ensure traceability and accountability in procurement files, including version control and approvals. conduct annual procurement-specific audits to ensure alignment with donor and AU requirements. | U116: =IF(L116="","",IF(L116<=4,"Low",IF(L116<=9,"Medium",IF(L116<=15,"High","Critical")))) -> High | W116: =IF(I116="","",MAX(1,I116-(IF(V116="Limited",1,IF(V116="Partial",2,IF(V116="Substantial",3,IF(V116="Highly Effective",4,0))))))) -> 3 | X116: =IF(K116="","",MAX(1,K116-ROUNDDOWN((IF(V116="Limited",1,IF(V116="Partial",2,IF(V116="Substantial",3,IF(V116="Highly Effective",4,0)))))/2,0))) -> 5 | Y116: =IF(OR(W116="",X116=""),"",W116*X116) -> 15 | Z116: =IF(Y116="","",IF(Y116<=4,"Low",IF(Y116<=9,"Medium",IF(Y116<=15,"High","Critical")))) -> High | AA116: =IF(OR(L116="",Y116=""),"",IF(Y116<L116,"Reduced by "&(L116-Y116)&" pts",IF(Y116=L116,"No Change","Increased by "&(Y116-L116)&" pts"))) -> No Change | AB116: =IF(Y116="","",Y116+(ROW()/10000000)) -> 15.000012
A117: 112 | B117: Supply Chain/ Procurement | C117: 6. Procurement and supply chain resilience | D117: Incomplete or Poorly Defined Technical Specifications | E117: If there is Incomplete or Poorly Defined Technical Specifications then there will be delayed procurement resulting in the acquisition of unsuitable items, leading to rework, wastage of resources, or project failure | G117: Operational | H117: Likely | I117: =IFERROR(IF(H117="Unlikely",1,IF(H117="Possible",2,IF(H117="Likely",3,IF(H117="Almost Certain",4,IF(H117="Certain",5,""))))),"") -> 3 | J117: Major | K117: =IFERROR(IF(J117="Negligible",1,IF(J117="Minor",2,IF(J117="Moderate",3,IF(J117="Major",4,IF(J117="Critical",5,""))))),"") -> 4 | L117: =IF(OR(I117="",K117=""),"",I117*K117) -> 12 | M117: Develop and roll out standardized specification templates and Terms of Reference (ToR) checklists tailored to frequently procured goods and services. Organize hands-on training workshops for user departments on how to draft clear and comprehensive technical specifications and Statements of Work (SoWs). Assign dedicated procurement focal points or category specialists to provide early technical guidance during the procurement request development phase. Build an institutional Specification Bank or Catalogue, containing pre-vetted and reusable templates/specifications for common items and services. Institutionalize early procurement planning and forecasting exercises at the start of each program year, allowing adequate time for developing quality specifications. | U117: =IF(L117="","",IF(L117<=4,"Low",IF(L117<=9,"Medium",IF(L117<=15,"High","Critical")))) -> High | W117: =IF(I117="","",MAX(1,I117-(IF(V117="Limited",1,IF(V117="Partial",2,IF(V117="Substantial",3,IF(V117="Highly Effective",4,0))))))) -> 3 | X117: =IF(K117="","",MAX(1,K117-ROUNDDOWN((IF(V117="Limited",1,IF(V117="Partial",2,IF(V117="Substantial",3,IF(V117="Highly Effective",4,0)))))/2,0))) -> 4 | Y117: =IF(OR(W117="",X117=""),"",W117*X117) -> 12 | Z117: =IF(Y117="","",IF(Y117<=4,"Low",IF(Y117<=9,"Medium",IF(Y117<=15,"High","Critical")))) -> High | AA117: =IF(OR(L117="",Y117=""),"",IF(Y117<L117,"Reduced by "&(L117-Y117)&" pts",IF(Y117=L117,"No Change","Increased by "&(Y117-L117)&" pts"))) -> No Change | AB117: =IF(Y117="","",Y117+(ROW()/10000000)) -> 12.000012
A118: 113 | B118: Supply Chain/ Procurement | C118: 6. Procurement and supply chain resilience | D118: Over-Reliance on External Suppliers for Essential Health Products | E118: If access to external suppliers is disrupted, then procurement cycles will be prolonged, leading to delayed service delivery and disease control activities across Member States. If no resilient local manufacturing system exists, then regional public health supply chains will be continuously vulnerable during global emergencies. If dependency continues, then Africa CDC’s ability to implement rapid, equitable response mechanisms will be severely constrained. | G118: Operational | I118: =IFERROR(IF(H118="Unlikely",1,IF(H118="Possible",2,IF(H118="Likely",3,IF(H118="Almost Certain",4,IF(H118="Certain",5,""))))),"") | J118: Major | K118: =IFERROR(IF(J118="Negligible",1,IF(J118="Minor",2,IF(J118="Moderate",3,IF(J118="Major",4,IF(J118="Critical",5,""))))),"") -> 4 | L118: =IF(OR(I118="",K118=""),"",I118*K118) | M118: Support establishment and operationalization of regional manufacturing hubs (as part of PAVM platform and AU Pharma Manufacturing Strategy) Advocate for domestic financing policies and blended capital instruments for local suppliers Strengthen pooled procurement mechanisms to support local and regional sourcing Establish risk-sharing frameworks and technology transfer partnerships Incentivize Member States to create enabling environments for pharmaceutical manufacturing | U118: =IF(L118="","",IF(L118<=4,"Low",IF(L118<=9,"Medium",IF(L118<=15,"High","Critical")))) | W118: =IF(I118="","",MAX(1,I118-(IF(V118="Limited",1,IF(V118="Partial",2,IF(V118="Substantial",3,IF(V118="Highly Effective",4,0))))))) | X118: =IF(K118="","",MAX(1,K118-ROUNDDOWN((IF(V118="Limited",1,IF(V118="Partial",2,IF(V118="Substantial",3,IF(V118="Highly Effective",4,0)))))/2,0))) -> 4 | Y118: =IF(OR(W118="",X118=""),"",W118*X118) | Z118: =IF(Y118="","",IF(Y118<=4,"Low",IF(Y118<=9,"Medium",IF(Y118<=15,"High","Critical")))) | AA118: =IF(OR(L118="",Y118=""),"",IF(Y118<L118,"Reduced by "&(L118-Y118)&" pts",IF(Y118=L118,"No Change","Increased by "&(Y118-L118)&" pts"))) | AB118: =IF(Y118="","",Y118+(ROW()/10000000))
A119: 114 | B119: Supply Chain/ Procurement | C119: 6. Procurement and supply chain resilience | D119: Documentation Errors in Customs Clearance | E119: If documents are incomplete or incorrect, then clearance timelines are extended, leading to product expiration risks (especially cold chain items), stock-outs, and additional port charges. If delays persist, then program implementation timelines and donor confidence may be compromised. If errors go uncorrected, the institution could face sanctions or rejection of future clearances by port authorities. | G119: Financial | H119: Likely | I119: =IFERROR(IF(H119="Unlikely",1,IF(H119="Possible",2,IF(H119="Likely",3,IF(H119="Almost Certain",4,IF(H119="Certain",5,""))))),"") -> 3 | J119: Major | K119: =IFERROR(IF(J119="Negligible",1,IF(J119="Minor",2,IF(J119="Moderate",3,IF(J119="Major",4,IF(J119="Critical",5,""))))),"") -> 4 | L119: =IF(OR(I119="",K119=""),"",I119*K119) -> 12 | M119: Develop and disseminate standardized SOPs and a customs clearance checklist Establish a training program for supply chain and clearance personnel on import documentation requirements and procedures Implement a pre-clearance document verification tool or tracking system Maintain a database of commonly required documents by country/commodity to streamline processing Conduct annual reviews of customs delays and root cause analysis | U119: =IF(L119="","",IF(L119<=4,"Low",IF(L119<=9,"Medium",IF(L119<=15,"High","Critical")))) -> High | W119: =IF(I119="","",MAX(1,I119-(IF(V119="Limited",1,IF(V119="Partial",2,IF(V119="Substantial",3,IF(V119="Highly Effective",4,0))))))) -> 3 | X119: =IF(K119="","",MAX(1,K119-ROUNDDOWN((IF(V119="Limited",1,IF(V119="Partial",2,IF(V119="Substantial",3,IF(V119="Highly Effective",4,0)))))/2,0))) -> 4 | Y119: =IF(OR(W119="",X119=""),"",W119*X119) -> 12 | Z119: =IF(Y119="","",IF(Y119<=4,"Low",IF(Y119<=9,"Medium",IF(Y119<=15,"High","Critical")))) -> High | AA119: =IF(OR(L119="",Y119=""),"",IF(Y119<L119,"Reduced by "&(L119-Y119)&" pts",IF(Y119=L119,"No Change","Increased by "&(Y119-L119)&" pts"))) -> No Change | AB119: =IF(Y119="","",Y119+(ROW()/10000000)) -> 12.000012
A120: 115 | B120: Supply Chain/ Procurement | C120: 8. Integrity, compliance, and safeguarding | D120: Non-Compliance with Import/Export Regulations | E120: If goods are found non-compliant upon arrival, then permits may be denied, resulting in stock delays or returns. If regulatory breaches occur, then Africa CDC’s reputation may suffer with customs authorities and Member States, affecting future cooperation. If embargoed or unauthorized products are shipped, then Africa CDC could face legal, political, or donor scrutiny, undermining public trust. | G120: Compliance | H120: Likely | I120: =IFERROR(IF(H120="Unlikely",1,IF(H120="Possible",2,IF(H120="Likely",3,IF(H120="Almost Certain",4,IF(H120="Certain",5,""))))),"") -> 3 | J120: Major | K120: =IFERROR(IF(J120="Negligible",1,IF(J120="Minor",2,IF(J120="Moderate",3,IF(J120="Major",4,IF(J120="Critical",5,""))))),"") -> 4 | L120: =IF(OR(I120="",K120=""),"",I120*K120) -> 12 | M120: Develop and maintain a centralized Africa CDC Import/Export Regulatory requirement Database accessible to all clearance teams Include a regulatory compliance checklist in the SOP for all cross-border shipments Conduct quarterly regulatory update reviews and disseminate alerts across relevant technical and logistics teams Include a clause on compliance responsibilities in contracts with third-party brokers and freight forwarders | U120: =IF(L120="","",IF(L120<=4,"Low",IF(L120<=9,"Medium",IF(L120<=15,"High","Critical")))) -> High | W120: =IF(I120="","",MAX(1,I120-(IF(V120="Limited",1,IF(V120="Partial",2,IF(V120="Substantial",3,IF(V120="Highly Effective",4,0))))))) -> 3 | X120: =IF(K120="","",MAX(1,K120-ROUNDDOWN((IF(V120="Limited",1,IF(V120="Partial",2,IF(V120="Substantial",3,IF(V120="Highly Effective",4,0)))))/2,0))) -> 4 | Y120: =IF(OR(W120="",X120=""),"",W120*X120) -> 12 | Z120: =IF(Y120="","",IF(Y120<=4,"Low",IF(Y120<=9,"Medium",IF(Y120<=15,"High","Critical")))) -> High | AA120: =IF(OR(L120="",Y120=""),"",IF(Y120<L120,"Reduced by "&(L120-Y120)&" pts",IF(Y120=L120,"No Change","Increased by "&(Y120-L120)&" pts"))) -> No Change | AB120: =IF(Y120="","",Y120+(ROW()/10000000)) -> 12.000012
A121: 116 | B121: Supply Chain/ Procurement | C121: 6. Procurement and supply chain resilience | D121: Third-Party Errors by Freight Forwarders or Customs Brokers | E121: If customs documentation is incorrect or shipment procedures are mishandled, then cargo may be delayed at ports, resulting in late deliveries and unmet project timelines. If cargo is misrouted or lost, then Africa CDC may incur demurrage fees or emergency re-shipment costs. If repeated third-party errors occur, then stakeholder trust in Africa CDC’s logistics reliability may erode, affecting future collaboration with Member States or partners. | G121: Reputational | H121: Likely | I121: =IFERROR(IF(H121="Unlikely",1,IF(H121="Possible",2,IF(H121="Likely",3,IF(H121="Almost Certain",4,IF(H121="Certain",5,""))))),"") -> 3 | J121: Major | K121: =IFERROR(IF(J121="Negligible",1,IF(J121="Minor",2,IF(J121="Moderate",3,IF(J121="Major",4,IF(J121="Critical",5,""))))),"") -> 4 | L121: =IF(OR(I121="",K121=""),"",I121*K121) -> 12 | M121: Institute a performance monitoring system with KPIs for all freight forwarders and customs brokers Establish pre-engagement assessments and certification for logistics partners Develop and enforce SOPs for documentation, handover protocols, and compliance checks Include penalties or non-compliance clauses in contracts for repeated delays or errors Conduct regular review meetings with logistics providers to identify and address process gaps | U121: =IF(L121="","",IF(L121<=4,"Low",IF(L121<=9,"Medium",IF(L121<=15,"High","Critical")))) -> High | W121: =IF(I121="","",MAX(1,I121-(IF(V121="Limited",1,IF(V121="Partial",2,IF(V121="Substantial",3,IF(V121="Highly Effective",4,0))))))) -> 3 | X121: =IF(K121="","",MAX(1,K121-ROUNDDOWN((IF(V121="Limited",1,IF(V121="Partial",2,IF(V121="Substantial",3,IF(V121="Highly Effective",4,0)))))/2,0))) -> 4 | Y121: =IF(OR(W121="",X121=""),"",W121*X121) -> 12 | Z121: =IF(Y121="","",IF(Y121<=4,"Low",IF(Y121<=9,"Medium",IF(Y121<=15,"High","Critical")))) -> High | AA121: =IF(OR(L121="",Y121=""),"",IF(Y121<L121,"Reduced by "&(L121-Y121)&" pts",IF(Y121=L121,"No Change","Increased by "&(Y121-L121)&" pts"))) -> No Change | AB121: =IF(Y121="","",Y121+(ROW()/10000000)) -> 12.000012
A122: 117 | B122: Supply Chain/ Procurement | C122: 8. Integrity, compliance, and safeguarding | D122: Mis-declaration and Fraud in Customs Clearance | E122: If falsified documents are submitted during customs clearance, then the organization risks fines, seizures of critical supplies, or blacklisting by port authorities. If cases of smuggling or undeclared items are linked to Africa CDC shipments, then institutional credibility will be harmed, potentially affecting donor trust and partnerships. If sanctions or investigations occur, then clearance timelines for urgent shipments may be severely delayed, with cascading effects on national-level response operations. | G122: Financial | H122: Likely | I122: =IFERROR(IF(H122="Unlikely",1,IF(H122="Possible",2,IF(H122="Likely",3,IF(H122="Almost Certain",4,IF(H122="Certain",5,""))))),"") -> 3 | J122: Major | K122: =IFERROR(IF(J122="Negligible",1,IF(J122="Minor",2,IF(J122="Moderate",3,IF(J122="Major",4,IF(J122="Critical",5,""))))),"") -> 4 | L122: =IF(OR(I122="",K122=""),"",I122*K122) -> 12 | M122: Institute a dual-verification process for all customs documentation before submission Contract only prequalified, vetted customs brokers and agents with performance history and anti-fraud credentials Develop and deploy a clearance compliance checklist for all outgoing and incoming shipments Conduct periodic training and refresher sessions for logistics teams and third-party brokers on compliance with import/export regulations | U122: =IF(L122="","",IF(L122<=4,"Low",IF(L122<=9,"Medium",IF(L122<=15,"High","Critical")))) -> High | W122: =IF(I122="","",MAX(1,I122-(IF(V122="Limited",1,IF(V122="Partial",2,IF(V122="Substantial",3,IF(V122="Highly Effective",4,0))))))) -> 3 | X122: =IF(K122="","",MAX(1,K122-ROUNDDOWN((IF(V122="Limited",1,IF(V122="Partial",2,IF(V122="Substantial",3,IF(V122="Highly Effective",4,0)))))/2,0))) -> 4 | Y122: =IF(OR(W122="",X122=""),"",W122*X122) -> 12 | Z122: =IF(Y122="","",IF(Y122<=4,"Low",IF(Y122<=9,"Medium",IF(Y122<=15,"High","Critical")))) -> High | AA122: =IF(OR(L122="",Y122=""),"",IF(Y122<L122,"Reduced by "&(L122-Y122)&" pts",IF(Y122=L122,"No Change","Increased by "&(Y122-L122)&" pts"))) -> No Change | AB122: =IF(Y122="","",Y122+(ROW()/10000000)) -> 12.000012
A123: 118 | B123: Supply Chain/ Procurement | C123: 2. Workforce sustainability and institutional capability | D123: Loss of Key Supply Chain Staff Post-SLL Program | E123: If SLL-funded staff exit without transition plans, then procurement timelines will stall, CCE& ICL country support will be interrupted including ongoing technical support to members states, and knowledge transfer will be lost. If the Supply Chain Division lacks technical staffing during emergency activation, then Africa CDC’s ability to deliver timely medical countermeasures and commodities will be impaired. If skilled RCC focal persons are lost, then coordination with Member States will deteriorate, leading to fragmented implementation of regional priorities. | G123: Operational | H123: Certain | I123: =IFERROR(IF(H123="Unlikely",1,IF(H123="Possible",2,IF(H123="Likely",3,IF(H123="Almost Certain",4,IF(H123="Certain",5,""))))),"") -> 5 | J123: Critical | K123: =IFERROR(IF(J123="Negligible",1,IF(J123="Minor",2,IF(J123="Moderate",3,IF(J123="Major",4,IF(J123="Critical",5,""))))),"") -> 5 | L123: =IF(OR(I123="",K123=""),"",I123*K123) -> 25 | M123: Initiate a transition planning task team to map critical staff roles and develop continuity mechanisms. Propose phased absorption of SLL staff into Africa CDC’s institutional HR structure. Engage with HR and Partnerships Divisions to advocate for funding or reprogramming options with donor partners. Create a surge staffing pool or roving support structure to cover post-SLL operations in critical regions. Include supply chain workforce sustainability in Africa CDC’s resource mobilization strategy. | U123: =IF(L123="","",IF(L123<=4,"Low",IF(L123<=9,"Medium",IF(L123<=15,"High","Critical")))) -> Critical | W123: =IF(I123="","",MAX(1,I123-(IF(V123="Limited",1,IF(V123="Partial",2,IF(V123="Substantial",3,IF(V123="Highly Effective",4,0))))))) -> 5 | X123: =IF(K123="","",MAX(1,K123-ROUNDDOWN((IF(V123="Limited",1,IF(V123="Partial",2,IF(V123="Substantial",3,IF(V123="Highly Effective",4,0)))))/2,0))) -> 5 | Y123: =IF(OR(W123="",X123=""),"",W123*X123) -> 25 | Z123: =IF(Y123="","",IF(Y123<=4,"Low",IF(Y123<=9,"Medium",IF(Y123<=15,"High","Critical")))) -> Critical | AA123: =IF(OR(L123="",Y123=""),"",IF(Y123<L123,"Reduced by "&(L123-Y123)&" pts",IF(Y123=L123,"No Change","Increased by "&(Y123-L123)&" pts"))) -> No Change | AB123: =IF(Y123="","",Y123+(ROW()/10000000)) -> 25.000012
A124: 119 | B124: Partnerships | C124: 8. Integrity, compliance, and safeguarding | D124: Regulatory Non-Compliance Risk of non-adherence to Africa CDC or donor-specific policies and requirements, potentially jeopardizing funding and institutional credibility. | E124: 1.During audits, Africa CDC may receive a “qualified” opinion, signaling serious compliance issues to donors. 2.Weak compliance oversight can lead to an inability to track how funds are used or to hold partners accountable. 3.Donors may question the institution's credibility, potentially leading to strained relationships or funding cuts. 4.Africa CDC's ability to continue managing large-scale grants could be called into question, risking its institutional reputation | F124: 1.Many staff involved in grant management may not be fully aware of donor rules, policies, or contractual obligations due to limited or irregular training opportunities. 2.There are minimal or no structured compliance monitoring visits to verify adherence to grant agreements across implementing teams. 3.Existing legal frameworks (e.g., MoUs and contracts) may lack clarity or enforcement mechanisms to ensure partners uphold their commitments. 4.Limited oversight or audit visits allow issues to go undetected until formal reviews occur | G124: Compliance | H124: Certain | I124: =IFERROR(IF(H124="Unlikely",1,IF(H124="Possible",2,IF(H124="Likely",3,IF(H124="Almost Certain",4,IF(H124="Certain",5,""))))),"") -> 5 | J124: Critical | K124: =IFERROR(IF(J124="Negligible",1,IF(J124="Minor",2,IF(J124="Moderate",3,IF(J124="Major",4,IF(J124="Critical",5,""))))),"") -> 5 | L124: =IF(OR(I124="",K124=""),"",I124*K124) -> 25 | M124: 1.Deliver regular, mandatory training tailored regulatory compliance policies and requirements to the program and finance staff to build a shared understanding of compliance obligations. 2.Introduce scheduled compliance site visits and check-ins to assess adherence to donor rules and Africa CDC policies. 3.Strengthen legal review and oversight of all partnership agreements to ensure enforceability. 4.Introduce whistleblower policies and safe reporting channels to detect and address misconduct - office of the obudsman maybe | U124: =IF(L124="","",IF(L124<=4,"Low",IF(L124<=9,"Medium",IF(L124<=15,"High","Critical")))) -> Critical | W124: =IF(I124="","",MAX(1,I124-(IF(V124="Limited",1,IF(V124="Partial",2,IF(V124="Substantial",3,IF(V124="Highly Effective",4,0))))))) -> 5 | X124: =IF(K124="","",MAX(1,K124-ROUNDDOWN((IF(V124="Limited",1,IF(V124="Partial",2,IF(V124="Substantial",3,IF(V124="Highly Effective",4,0)))))/2,0))) -> 5 | Y124: =IF(OR(W124="",X124=""),"",W124*X124) -> 25 | Z124: =IF(Y124="","",IF(Y124<=4,"Low",IF(Y124<=9,"Medium",IF(Y124<=15,"High","Critical")))) -> Critical | AA124: =IF(OR(L124="",Y124=""),"",IF(Y124<L124,"Reduced by "&(L124-Y124)&" pts",IF(Y124=L124,"No Change","Increased by "&(Y124-L124)&" pts"))) -> No Change | AB124: =IF(Y124="","",Y124+(ROW()/10000000)) -> 25.000012
A125: 120 | B125: Partnerships | C125: 3. Fiduciary stewardship and internal control | D125: Lack of Real-Time Financial Oversight Inability to monitor grant expenditures in real time may lead to budget overruns, inefficiencies, or reporting gaps. | E125: 1.Decision-makers may rely on outdated or inaccurate financial data, leading to uninformed or risky programmatic decisions. 2. Discrepancies in expenditure reports can lead to audit findings or non-compliance with grant terms, affecting Africa CDC’s reputation. | F125: 1.Use of outdated or non-existent financial tracking systems - Budget excecution report 2.There is no consistent process to verify partner-reported expenses, especially for grants implemented through external partners (IPs). 3.Staff onboarding processes may not sufficiently emphasize financial management protocols, especially for newly recruited or rotating personnel. | G125: Operational | H125: Certain | I125: =IFERROR(IF(H125="Unlikely",1,IF(H125="Possible",2,IF(H125="Likely",3,IF(H125="Almost Certain",4,IF(H125="Certain",5,""))))),"") -> 5 | J125: Critical | K125: =IFERROR(IF(J125="Negligible",1,IF(J125="Minor",2,IF(J125="Moderate",3,IF(J125="Major",4,IF(J125="Critical",5,""))))),"") -> 5 | L125: =IF(OR(I125="",K125=""),"",I125*K125) -> 25 | M125: 1.Implement an integrated automated financial system linked with grants, procurement, and HR platforms for real-time oversight. 2.Establish verification routines for all partner expenses, including spot checks and regualr document reviews to confirm the reproted financial position at all times. 3.Strengthen orientation programs to ensure all new staff understand financial compliance expectations. | Q125: Grants Management unit/LegalEO | U125: =IF(L125="","",IF(L125<=4,"Low",IF(L125<=9,"Medium",IF(L125<=15,"High","Critical")))) -> Critical | W125: =IF(I125="","",MAX(1,I125-(IF(V125="Limited",1,IF(V125="Partial",2,IF(V125="Substantial",3,IF(V125="Highly Effective",4,0))))))) -> 5 | X125: =IF(K125="","",MAX(1,K125-ROUNDDOWN((IF(V125="Limited",1,IF(V125="Partial",2,IF(V125="Substantial",3,IF(V125="Highly Effective",4,0)))))/2,0))) -> 5 | Y125: =IF(OR(W125="",X125=""),"",W125*X125) -> 25 | Z125: =IF(Y125="","",IF(Y125<=4,"Low",IF(Y125<=9,"Medium",IF(Y125<=15,"High","Critical")))) -> Critical | AA125: =IF(OR(L125="",Y125=""),"",IF(Y125<L125,"Reduced by "&(L125-Y125)&" pts",IF(Y125=L125,"No Change","Increased by "&(Y125-L125)&" pts"))) -> No Change | AB125: =IF(Y125="","",Y125+(ROW()/10000000)) -> 25.000013
A126: 121 | B126: Partnerships | C126: 3. Fiduciary stewardship and internal control | D126: Inadequate Financial Reporting Delays or inaccuracies in financial reporting could undermine transparency and stakeholder confidence. | E126: 1.Missing or delaying financial reports can violate signed grant agreements, causing donors to question the institution’s fund management reliability. 2.Repeated reporting failures may lead to funding suspension or loss of future grant opportunities. | F126: 1.Teams responsible for financial reporting may lack the capacity or experience to prepare accurate, timely reports. 2.Reporting deadlines imposed by donors may be tight and difficult to meet given internal review cycles or competing responsibilities. | G126: Financial | H126: Possible | I126: =IFERROR(IF(H126="Unlikely",1,IF(H126="Possible",2,IF(H126="Likely",3,IF(H126="Almost Certain",4,IF(H126="Certain",5,""))))),"") -> 2 | J126: Moderate | K126: =IFERROR(IF(J126="Negligible",1,IF(J126="Minor",2,IF(J126="Moderate",3,IF(J126="Major",4,IF(J126="Critical",5,""))))),"") -> 3 | L126: =IF(OR(I126="",K126=""),"",I126*K126) -> 6 | M126: 1.Standardize reporting formats and templates to ease the preparation and review process. 2.Conduct regular training on financial reporting, emphasizing accuracy, timeliness, and donor expectations. 3.Automate grant tracking tools to send reminders and monitor deadlines to ensure timely submissions. | Q126: Grants Management unit | U126: =IF(L126="","",IF(L126<=4,"Low",IF(L126<=9,"Medium",IF(L126<=15,"High","Critical")))) -> Medium | W126: =IF(I126="","",MAX(1,I126-(IF(V126="Limited",1,IF(V126="Partial",2,IF(V126="Substantial",3,IF(V126="Highly Effective",4,0))))))) -> 2 | X126: =IF(K126="","",MAX(1,K126-ROUNDDOWN((IF(V126="Limited",1,IF(V126="Partial",2,IF(V126="Substantial",3,IF(V126="Highly Effective",4,0)))))/2,0))) -> 3 | Y126: =IF(OR(W126="",X126=""),"",W126*X126) -> 6 | Z126: =IF(Y126="","",IF(Y126<=4,"Low",IF(Y126<=9,"Medium",IF(Y126<=15,"High","Critical")))) -> Medium | AA126: =IF(OR(L126="",Y126=""),"",IF(Y126<L126,"Reduced by "&(L126-Y126)&" pts",IF(Y126=L126,"No Change","Increased by "&(Y126-L126)&" pts"))) -> No Change | AB126: =IF(Y126="","",Y126+(ROW()/10000000)) -> 6.0000126
A127: 122 | B127: Partnerships | C127: 3. Fiduciary stewardship and internal control | D127: Delayed Fund Disbursements Slow release of funds from donors may disrupt program timelines and operational continuity. | E127: Delays in releasing funds impact activity implementation, resulting in missed timelines or failure to achieve project milestones. | F127: 1.Internal bureaucratic processes and long approval chains slow down fund movement. 2.Weak documentation practices delay the clearance of expense reports and advance settlements. | G127: Financial | H127: Certain | I127: =IFERROR(IF(H127="Unlikely",1,IF(H127="Possible",2,IF(H127="Likely",3,IF(H127="Almost Certain",4,IF(H127="Certain",5,""))))),"") -> 5 | J127: Critical | K127: =IFERROR(IF(J127="Negligible",1,IF(J127="Minor",2,IF(J127="Moderate",3,IF(J127="Major",4,IF(J127="Critical",5,""))))),"") -> 5 | L127: =IF(OR(I127="",K127=""),"",I127*K127) -> 25 | M127: 1.Simplify and digitise the approval processes for faster decision-making - turnaroudn time management. 2.Train staff on proper documentation and streamline finance workflows to minimize bottlenecks. | Q127: Grants Management unit/MIS | U127: =IF(L127="","",IF(L127<=4,"Low",IF(L127<=9,"Medium",IF(L127<=15,"High","Critical")))) -> Critical | W127: =IF(I127="","",MAX(1,I127-(IF(V127="Limited",1,IF(V127="Partial",2,IF(V127="Substantial",3,IF(V127="Highly Effective",4,0))))))) -> 5 | X127: =IF(K127="","",MAX(1,K127-ROUNDDOWN((IF(V127="Limited",1,IF(V127="Partial",2,IF(V127="Substantial",3,IF(V127="Highly Effective",4,0)))))/2,0))) -> 5 | Y127: =IF(OR(W127="",X127=""),"",W127*X127) -> 25 | Z127: =IF(Y127="","",IF(Y127<=4,"Low",IF(Y127<=9,"Medium",IF(Y127<=15,"High","Critical")))) -> Critical | AA127: =IF(OR(L127="",Y127=""),"",IF(Y127<L127,"Reduced by "&(L127-Y127)&" pts",IF(Y127=L127,"No Change","Increased by "&(Y127-L127)&" pts"))) -> No Change | AB127: =IF(Y127="","",Y127+(ROW()/10000000)) -> 25.000013
A128: 123 | B128: Partnerships | C128: 8. Integrity, compliance, and safeguarding | D128: Financial Mismanagement or Fraud Potential misuse or mismanagement of grant funds may lead to reputational damage and corrective action by donors. | E128: 1.Donors may withdraw current or future support - "money management should feel safe'' 2.Africa CDC may face legal action, including mandatory reimbursement of misused funds. | F128: 1.Lax internal controls can allow financial malpractice to go unnoticed/unchecked - empower the system(hardware plus the users) to check and control fraud(policies, people) 2.Intentional fraud by staff or partners due to inadequate oversight or absence of deterrents. | G128: Financial | H128: Possible | I128: =IFERROR(IF(H128="Unlikely",1,IF(H128="Possible",2,IF(H128="Likely",3,IF(H128="Almost Certain",4,IF(H128="Certain",5,""))))),"") -> 2 | J128: Minor | K128: =IFERROR(IF(J128="Negligible",1,IF(J128="Minor",2,IF(J128="Moderate",3,IF(J128="Major",4,IF(J128="Critical",5,""))))),"") -> 2 | L128: =IF(OR(I128="",K128=""),"",I128*K128) -> 4 | M128: 1. Zero tolerance policy - staff and maganement implenting this 2.Strengthen internal controls and financial audits across all program units. 3.Introduce anonymous whistleblower mechanisms and fraud awareness campaigns. 4.Build a culture of accountability through leadership-led transparency initiatives. | Q128: Grants Management unit | U128: =IF(L128="","",IF(L128<=4,"Low",IF(L128<=9,"Medium",IF(L128<=15,"High","Critical")))) -> Low | W128: =IF(I128="","",MAX(1,I128-(IF(V128="Limited",1,IF(V128="Partial",2,IF(V128="Substantial",3,IF(V128="Highly Effective",4,0))))))) -> 2 | X128: =IF(K128="","",MAX(1,K128-ROUNDDOWN((IF(V128="Limited",1,IF(V128="Partial",2,IF(V128="Substantial",3,IF(V128="Highly Effective",4,0)))))/2,0))) -> 2 | Y128: =IF(OR(W128="",X128=""),"",W128*X128) -> 4 | Z128: =IF(Y128="","",IF(Y128<=4,"Low",IF(Y128<=9,"Medium",IF(Y128<=15,"High","Critical")))) -> Low | AA128: =IF(OR(L128="",Y128=""),"",IF(Y128<L128,"Reduced by "&(L128-Y128)&" pts",IF(Y128=L128,"No Change","Increased by "&(Y128-L128)&" pts"))) -> No Change | AB128: =IF(Y128="","",Y128+(ROW()/10000000)) -> 4.0000128
A129: 124 | B129: Partnerships | C129: 4. Program execution and delivery | D129: Misaligned Program Delivery Poor alignment of grant-funded activities with agreed objectives may result in missed targets and underperformance | E129: 1.Programs may drift away from grant priorities, leading to under-delivery and poor impact reporting. 2.Donors may view Africa CDC as an unreliable implementer, affecting future funding opportunities. | F129: 1.Absence of structured grant monitoring systems that flag misaligned activities early. | G129: Project | H129: Possible | I129: =IFERROR(IF(H129="Unlikely",1,IF(H129="Possible",2,IF(H129="Likely",3,IF(H129="Almost Certain",4,IF(H129="Certain",5,""))))),"") -> 2 | J129: Critical | K129: =IFERROR(IF(J129="Negligible",1,IF(J129="Minor",2,IF(J129="Moderate",3,IF(J129="Major",4,IF(J129="Critical",5,""))))),"") -> 5 | L129: =IF(OR(I129="",K129=""),"",I129*K129) -> 10 | M129: 1.Set up monthly monitoring systems, including program reviews and dashboard tracking. 2.Encourage adaptive planning based on implementation realities. | Q129: Grants Management unit | U129: =IF(L129="","",IF(L129<=4,"Low",IF(L129<=9,"Medium",IF(L129<=15,"High","Critical")))) -> High | W129: =IF(I129="","",MAX(1,I129-(IF(V129="Limited",1,IF(V129="Partial",2,IF(V129="Substantial",3,IF(V129="Highly Effective",4,0))))))) -> 2 | X129: =IF(K129="","",MAX(1,K129-ROUNDDOWN((IF(V129="Limited",1,IF(V129="Partial",2,IF(V129="Substantial",3,IF(V129="Highly Effective",4,0)))))/2,0))) -> 5 | Y129: =IF(OR(W129="",X129=""),"",W129*X129) -> 10 | Z129: =IF(Y129="","",IF(Y129<=4,"Low",IF(Y129<=9,"Medium",IF(Y129<=15,"High","Critical")))) -> High | AA129: =IF(OR(L129="",Y129=""),"",IF(Y129<L129,"Reduced by "&(L129-Y129)&" pts",IF(Y129=L129,"No Change","Increased by "&(Y129-L129)&" pts"))) -> No Change | AB129: =IF(Y129="","",Y129+(ROW()/10000000)) -> 10.000013
A130: 125 | B130: Partnerships | C130: 7. Data governance and management reporting | D130: Data Integrity Risks Inconsistent data collection, validation, or storage practices could compromise decision-making and donor reporting accuracy | E130: Inconsistent or unreliable data leads to poor planning, misleading reports, and reduced institutional credibility | F130: Data systems in place is fragmented, with no standardized method for storing, validating, or analyzing grant-related data. | G130: Project | H130: Certain | I130: =IFERROR(IF(H130="Unlikely",1,IF(H130="Possible",2,IF(H130="Likely",3,IF(H130="Almost Certain",4,IF(H130="Certain",5,""))))),"") -> 5 | J130: Critical | K130: =IFERROR(IF(J130="Negligible",1,IF(J130="Minor",2,IF(J130="Moderate",3,IF(J130="Major",4,IF(J130="Critical",5,""))))),"") -> 5 | L130: =IF(OR(I130="",K130=""),"",I130*K130) -> 25 | M130: 1.Establish a centralized grant data repository - Africa CDC connect 2.Implement clear data validation protocols and regular audits of key datasets. | Q130: Grants Management unit | U130: =IF(L130="","",IF(L130<=4,"Low",IF(L130<=9,"Medium",IF(L130<=15,"High","Critical")))) -> Critical | W130: =IF(I130="","",MAX(1,I130-(IF(V130="Limited",1,IF(V130="Partial",2,IF(V130="Substantial",3,IF(V130="Highly Effective",4,0))))))) -> 5 | X130: =IF(K130="","",MAX(1,K130-ROUNDDOWN((IF(V130="Limited",1,IF(V130="Partial",2,IF(V130="Substantial",3,IF(V130="Highly Effective",4,0)))))/2,0))) -> 5 | Y130: =IF(OR(W130="",X130=""),"",W130*X130) -> 25 | Z130: =IF(Y130="","",IF(Y130<=4,"Low",IF(Y130<=9,"Medium",IF(Y130<=15,"High","Critical")))) -> Critical | AA130: =IF(OR(L130="",Y130=""),"",IF(Y130<L130,"Reduced by "&(L130-Y130)&" pts",IF(Y130=L130,"No Change","Increased by "&(Y130-L130)&" pts"))) -> No Change | AB130: =IF(Y130="","",Y130+(ROW()/10000000)) -> 25.000013
A131: 126 | B131: Partnerships | C131: 2. Workforce sustainability and institutional capability | D131: Human Resource deficiencies Insufficient staffing or lack of specialized expertise may hinder effective grant implementation and oversight. | E131: This limitation may lead to burnout, missed deadlines, and inefficient low quality implementation of grant activities | F131: Budgeting for staffing numbers does not still meet the need and capacity of the organsiation to allow for seamless grant management | G131: Operational | H131: Certain | I131: =IFERROR(IF(H131="Unlikely",1,IF(H131="Possible",2,IF(H131="Likely",3,IF(H131="Almost Certain",4,IF(H131="Certain",5,""))))),"") -> 5 | J131: Critical | K131: =IFERROR(IF(J131="Negligible",1,IF(J131="Minor",2,IF(J131="Moderate",3,IF(J131="Major",4,IF(J131="Critical",5,""))))),"") -> 5 | L131: =IF(OR(I131="",K131=""),"",I131*K131) -> 25 | M131: 1.Use standardized grant budgeting tools that prioritize skilled staffing in the organisation. 2.Business Units to Align with HR during budgeting to align Organisation needs with program needs from the proposal stage. | Q131: Grants Management unit | U131: =IF(L131="","",IF(L131<=4,"Low",IF(L131<=9,"Medium",IF(L131<=15,"High","Critical")))) -> Critical | W131: =IF(I131="","",MAX(1,I131-(IF(V131="Limited",1,IF(V131="Partial",2,IF(V131="Substantial",3,IF(V131="Highly Effective",4,0))))))) -> 5 | X131: =IF(K131="","",MAX(1,K131-ROUNDDOWN((IF(V131="Limited",1,IF(V131="Partial",2,IF(V131="Substantial",3,IF(V131="Highly Effective",4,0)))))/2,0))) -> 5 | Y131: =IF(OR(W131="",X131=""),"",W131*X131) -> 25 | Z131: =IF(Y131="","",IF(Y131<=4,"Low",IF(Y131<=9,"Medium",IF(Y131<=15,"High","Critical")))) -> Critical | AA131: =IF(OR(L131="",Y131=""),"",IF(Y131<L131,"Reduced by "&(L131-Y131)&" pts",IF(Y131=L131,"No Change","Increased by "&(Y131-L131)&" pts"))) -> No Change | AB131: =IF(Y131="","",Y131+(ROW()/10000000)) -> 25.000013
A132: 127 | B132: Partnerships | C132: 4. Program execution and delivery | D132: Fragmented Stakeholder Communication Weak coordination and communication among partners may create duplication, delays, or oversight challenges. | E132: Confusion, duplication of efforts, and resource inefficiencies across teams. | F132: Absence of clearly documented business processes outlining who is responsible for what in grant execution at Africa CDC - disjointed approach to stakeholder manageemnt | G132: Operational | H132: Possible | I132: =IFERROR(IF(H132="Unlikely",1,IF(H132="Possible",2,IF(H132="Likely",3,IF(H132="Almost Certain",4,IF(H132="Certain",5,""))))),"") -> 2 | J132: Negligible | K132: =IFERROR(IF(J132="Negligible",1,IF(J132="Minor",2,IF(J132="Moderate",3,IF(J132="Major",4,IF(J132="Critical",5,""))))),"") -> 1 | L132: =IF(OR(I132="",K132=""),"",I132*K132) -> 2 | M132: Develop detailed implementation guidelines, role definitions, and SOPs for each grant. | Q132: Grants Management unit | U132: =IF(L132="","",IF(L132<=4,"Low",IF(L132<=9,"Medium",IF(L132<=15,"High","Critical")))) -> Low | W132: =IF(I132="","",MAX(1,I132-(IF(V132="Limited",1,IF(V132="Partial",2,IF(V132="Substantial",3,IF(V132="Highly Effective",4,0))))))) -> 2 | X132: =IF(K132="","",MAX(1,K132-ROUNDDOWN((IF(V132="Limited",1,IF(V132="Partial",2,IF(V132="Substantial",3,IF(V132="Highly Effective",4,0)))))/2,0))) -> 1 | Y132: =IF(OR(W132="",X132=""),"",W132*X132) -> 2 | Z132: =IF(Y132="","",IF(Y132<=4,"Low",IF(Y132<=9,"Medium",IF(Y132<=15,"High","Critical")))) -> Low | AA132: =IF(OR(L132="",Y132=""),"",IF(Y132<L132,"Reduced by "&(L132-Y132)&" pts",IF(Y132=L132,"No Change","Increased by "&(Y132-L132)&" pts"))) -> No Change | AB132: =IF(Y132="","",Y132+(ROW()/10000000)) -> 2.0000132
A133: 128 | B133: Partnerships | C133: 4. Program execution and delivery | D133: Weak Grant Close-Out Processes Incomplete or delayed grant closure procedures may affect final reporting, reconciliation, and institutional learning(knowledge management). | E133: 1. Without a structured grant close out process, there may be significant delays in closing a project, impacting financial reconciliation, reporting, and staff offboarding. 2. Failure to complete necessary financial and technical documentation may result in negative audit outcomes and unresolved compliance queries. 3.Poor knowledge management i.e.challenges, lessons learned and best practices transfer are often lost, limiting the organization’s ability to improve future grant performance and application. | F133: 1.Lack of Grant close-out procedures within Africa CDC’s grant management policy or individual grant agreements. 2. Program and finance teams may not be adequately trained or oriented on the importance, timing, and steps required during grant closure. 3. Close-out activities are often not considered during the early stages of grant implementation, leading to rushed or incomplete closure processes. 4.Disconnect between program, finance, and procurement unitswhen closing out resulting in delays or gaps in closing grant-related activities | G133: Compliance | H133: Certain | I133: =IFERROR(IF(H133="Unlikely",1,IF(H133="Possible",2,IF(H133="Likely",3,IF(H133="Almost Certain",4,IF(H133="Certain",5,""))))),"") -> 5 | J133: Critical | K133: =IFERROR(IF(J133="Negligible",1,IF(J133="Minor",2,IF(J133="Moderate",3,IF(J133="Major",4,IF(J133="Critical",5,""))))),"") -> 5 | L133: =IF(OR(I133="",K133=""),"",I133*K133) -> 25 | M133: 1.Develop and Institutionalize Grant close-out Procedures at Africa CDC and have it disseminated to staff at Grant kickoff meetings with follow up during implentation of the grant 2.Continuopusly train relevant staff on close-out requirements and assign clear accountability for executing each step of the process. 3. Establish and coordiante grant close-out review meetings between finance, program, and procurement teams to ensure alignment and timely resolution of pending actions. | Q133: Grants Management unit | U133: =IF(L133="","",IF(L133<=4,"Low",IF(L133<=9,"Medium",IF(L133<=15,"High","Critical")))) -> Critical | W133: =IF(I133="","",MAX(1,I133-(IF(V133="Limited",1,IF(V133="Partial",2,IF(V133="Substantial",3,IF(V133="Highly Effective",4,0))))))) -> 5 | X133: =IF(K133="","",MAX(1,K133-ROUNDDOWN((IF(V133="Limited",1,IF(V133="Partial",2,IF(V133="Substantial",3,IF(V133="Highly Effective",4,0)))))/2,0))) -> 5 | Y133: =IF(OR(W133="",X133=""),"",W133*X133) -> 25 | Z133: =IF(Y133="","",IF(Y133<=4,"Low",IF(Y133<=9,"Medium",IF(Y133<=15,"High","Critical")))) -> Critical | AA133: =IF(OR(L133="",Y133=""),"",IF(Y133<L133,"Reduced by "&(L133-Y133)&" pts",IF(Y133=L133,"No Change","Increased by "&(Y133-L133)&" pts"))) -> No Change | AB133: =IF(Y133="","",Y133+(ROW()/10000000)) -> 25.000013
A134: 129 | B134: Partnerships | C134: 5. Country, partner, and geopolitical context | D134: Limited Political Backing in Select Member States Risk of reduced government-level support in some Member States, which may hinder effective implementation of Africa CDC initiatives and slow regional health coordination efforts. | E134: 1.Disruption or delays in program implementation due to misaligned expectations or unclear directives in the MS. 2.Reduced regional cooperation and trust, affecting coordination on health emergencies or joint initiatives. | F134: 1.Inconsistent or delayed communication channels between Africa CDC and national health authorities. 2.Lack of structured feedback loops to maintain ongoing collaboration - 'silo effect'. | G134: Contextual | H134: Certain | I134: =IFERROR(IF(H134="Unlikely",1,IF(H134="Possible",2,IF(H134="Likely",3,IF(H134="Almost Certain",4,IF(H134="Certain",5,""))))),"") -> 5 | J134: Critical | K134: =IFERROR(IF(J134="Negligible",1,IF(J134="Minor",2,IF(J134="Moderate",3,IF(J134="Major",4,IF(J134="Critical",5,""))))),"") -> 5 | L134: =IF(OR(I134="",K134=""),"",I134*K134) -> 25 | M134: 1.Strengthen communication frameworks by establishing regular check-ins with Member State focal points. 2.Conduct targeted advocacy to secure country-level buy-in, including political and technical endorsement of Africa CDC-led programs. | Q134: Grants Management unit | U134: =IF(L134="","",IF(L134<=4,"Low",IF(L134<=9,"Medium",IF(L134<=15,"High","Critical")))) -> Critical | W134: =IF(I134="","",MAX(1,I134-(IF(V134="Limited",1,IF(V134="Partial",2,IF(V134="Substantial",3,IF(V134="Highly Effective",4,0))))))) -> 5 | X134: =IF(K134="","",MAX(1,K134-ROUNDDOWN((IF(V134="Limited",1,IF(V134="Partial",2,IF(V134="Substantial",3,IF(V134="Highly Effective",4,0)))))/2,0))) -> 5 | Y134: =IF(OR(W134="",X134=""),"",W134*X134) -> 25 | Z134: =IF(Y134="","",IF(Y134<=4,"Low",IF(Y134<=9,"Medium",IF(Y134<=15,"High","Critical")))) -> Critical | AA134: =IF(OR(L134="",Y134=""),"",IF(Y134<L134,"Reduced by "&(L134-Y134)&" pts",IF(Y134=L134,"No Change","Increased by "&(Y134-L134)&" pts"))) -> No Change | AB134: =IF(Y134="","",Y134+(ROW()/10000000)) -> 25.000013
A135: 130 | B135: Partnerships | C135: 5. Country, partner, and geopolitical context | D135: Political Instability in Member States Ongoing or sudden political unrest(wars,demonstartions etc) in certain countries may disrupt health programs, restrict access to affected regions, and delay implementation timelines. | E135: 1.Interrupted program continuity and disrupted partnerships at the country level. 2.Delayed execution of Africa CDC-supported programs or joint activities. | F135: 1.Changes in national leadership or restructuring of health ministries during electoral cycles. 2.Shift in MS policy priorities that alter significantly the regional health cooperation. | G135: Contextual | H135: Certain | I135: =IFERROR(IF(H135="Unlikely",1,IF(H135="Possible",2,IF(H135="Likely",3,IF(H135="Almost Certain",4,IF(H135="Certain",5,""))))),"") -> 5 | J135: Critical | K135: =IFERROR(IF(J135="Negligible",1,IF(J135="Minor",2,IF(J135="Moderate",3,IF(J135="Major",4,IF(J135="Critical",5,""))))),"") -> 5 | L135: =IF(OR(I135="",K135=""),"",I135*K135) -> 25 | M135: 1.Maintain strong, country-specific advocacy strategies tailored to varying political environments. 2.Develop engagement briefs and transition toolkits for onboarding new country officials into Africa CDC platforms. | Q135: Partnerships Unit | U135: =IF(L135="","",IF(L135<=4,"Low",IF(L135<=9,"Medium",IF(L135<=15,"High","Critical")))) -> Critical | W135: =IF(I135="","",MAX(1,I135-(IF(V135="Limited",1,IF(V135="Partial",2,IF(V135="Substantial",3,IF(V135="Highly Effective",4,0))))))) -> 5 | X135: =IF(K135="","",MAX(1,K135-ROUNDDOWN((IF(V135="Limited",1,IF(V135="Partial",2,IF(V135="Substantial",3,IF(V135="Highly Effective",4,0)))))/2,0))) -> 5 | Y135: =IF(OR(W135="",X135=""),"",W135*X135) -> 25 | Z135: =IF(Y135="","",IF(Y135<=4,"Low",IF(Y135<=9,"Medium",IF(Y135<=15,"High","Critical")))) -> Critical | AA135: =IF(OR(L135="",Y135=""),"",IF(Y135<L135,"Reduced by "&(L135-Y135)&" pts",IF(Y135=L135,"No Change","Increased by "&(Y135-L135)&" pts"))) -> No Change | AB135: =IF(Y135="","",Y135+(ROW()/10000000)) -> 25.000014
A136: 131 | B136: Partnerships | C136: 7. Data governance and management reporting | D136: Inconsistent Data Sharing by Member States Risk of irregular or incomplete data submission from Member States, which can compromise timely decision-making, continental surveillance, and Africa CDC’s ability to provide accurate guidance. | E136: 1.Delays in Africa CDC’s response to health crises due to limited operational access or information flow. 2.Fragmentation of continental disease surveillance and control timely efforts. | F136: 1.Emerging national policies that impose limitations on cross-border data flow, workforce mobility, or partner operations. 2.Sovereignty concerns or political sensitivities affecting external engagement | G136: Strategic | H136: Possible | I136: =IFERROR(IF(H136="Unlikely",1,IF(H136="Possible",2,IF(H136="Likely",3,IF(H136="Almost Certain",4,IF(H136="Certain",5,""))))),"") -> 2 | J136: Moderate | K136: =IFERROR(IF(J136="Negligible",1,IF(J136="Minor",2,IF(J136="Moderate",3,IF(J136="Major",4,IF(J136="Critical",5,""))))),"") -> 3 | L136: =IF(OR(I136="",K136=""),"",I136*K136) -> 6 | M136: 1.Promote early adoption of multilateral data-sharing agreements. 2.Undertake diplomatic and technical advocacy to strengthen mutual trust and transparency with Member States. | Q136: Partnerships Unit | U136: =IF(L136="","",IF(L136<=4,"Low",IF(L136<=9,"Medium",IF(L136<=15,"High","Critical")))) -> Medium | W136: =IF(I136="","",MAX(1,I136-(IF(V136="Limited",1,IF(V136="Partial",2,IF(V136="Substantial",3,IF(V136="Highly Effective",4,0))))))) -> 2 | X136: =IF(K136="","",MAX(1,K136-ROUNDDOWN((IF(V136="Limited",1,IF(V136="Partial",2,IF(V136="Substantial",3,IF(V136="Highly Effective",4,0)))))/2,0))) -> 3 | Y136: =IF(OR(W136="",X136=""),"",W136*X136) -> 6 | Z136: =IF(Y136="","",IF(Y136<=4,"Low",IF(Y136<=9,"Medium",IF(Y136<=15,"High","Critical")))) -> Medium | AA136: =IF(OR(L136="",Y136=""),"",IF(Y136<L136,"Reduced by "&(L136-Y136)&" pts",IF(Y136=L136,"No Change","Increased by "&(Y136-L136)&" pts"))) -> No Change | AB136: =IF(Y136="","",Y136+(ROW()/10000000)) -> 6.0000136
... A158: 153 | B158: HR | C158: 2. Workforce sustainability and institutional capability | D158: Frequent departure of staff in critical roles leads to loss of institutional memory, disrupts programme implementation and delivery, reduces staff morale, high cost of recruitment and onboarding to repalce staff. | E158: Loss of experienced staff, impacting organizational knowledge and consistency Disruption in operations, knowledge loss, increased hiring costs | F158: 1. Job insecurity 2. Poor work-life balance and workload pressure 3. Lack of career development and growth opportunities 4. Challenges in employee/supervisor relations impact morale and retention 5. Lack of employee engagement 6. Funding constraints for staffing 7. Slow contract renewal processes 8. Unsatisfactor work environment organizational culture 9. Lack of harmonized and competitive compensation | G158: Operational | H158: Almost Certain | I158: =IFERROR(IF(H158="Unlikely",1,IF(H158="Possible",2,IF(H158="Likely",3,IF(H158="Almost Certain",4,IF(H158="Certain",5,""))))),"") -> 4 | J158: Critical | K158: =IFERROR(IF(J158="Negligible",1,IF(J158="Minor",2,IF(J158="Moderate",3,IF(J158="Major",4,IF(J158="Critical",5,""))))),"") -> 5 | L158: =IF(OR(I158="",K158=""),"",I158*K158) -> 20 | M158: 1. Conduct exit interviews to identify causes, enhance employee engagement, and establish retention programs focused on critical roles 2.Improve retention programs, 3. Harmonized compensation, employee engagement programs, 4. career development initiatives | Q158: Head of Division HR Senior Leadership | U158: =IF(L158="","",IF(L158<=4,"Low",IF(L158<=9,"Medium",IF(L158<=15,"High","Critical")))) -> Critical | W158: =IF(I158="","",MAX(1,I158-(IF(V158="Limited",1,IF(V158="Partial",2,IF(V158="Substantial",3,IF(V158="Highly Effective",4,0))))))) -> 4 | X158: =IF(K158="","",MAX(1,K158-ROUNDDOWN((IF(V158="Limited",1,IF(V158="Partial",2,IF(V158="Substantial",3,IF(V158="Highly Effective",4,0)))))/2,0))) -> 5 | Y158: =IF(OR(W158="",X158=""),"",W158*X158) -> 20 | Z158: =IF(Y158="","",IF(Y158<=4,"Low",IF(Y158<=9,"Medium",IF(Y158<=15,"High","Critical")))) -> Critical | AA158: =IF(OR(L158="",Y158=""),"",IF(Y158<L158,"Reduced by "&(L158-Y158)&" pts",IF(Y158=L158,"No Change","Increased by "&(Y158-L158)&" pts"))) -> No Change | AB158: =IF(Y158="","",Y158+(ROW()/10000000)) -> 20.000016
A159: 154 | B159: HR | C159: 8. Integrity, compliance, and safeguarding | D159: Unresolved employee grievances which can lead to public complaints, legal suits damaging the reputation of the organization. This risk can affect staff morale if staff don’t feel safe escalating grievances. | F159: 1. Lack of timely girevance resolution 2. Perceived bias in handling of grievance cases 3. Inconsistent application of policies and procedures 4. Lack of awareness on how to raise grievances 5, Fear of retaliation or victimizaiton | G159: Reputational | H159: Possible | I159: =IFERROR(IF(H159="Unlikely",1,IF(H159="Possible",2,IF(H159="Likely",3,IF(H159="Almost Certain",4,IF(H159="Certain",5,""))))),"") -> 2 | J159: Major | K159: =IFERROR(IF(J159="Negligible",1,IF(J159="Minor",2,IF(J159="Moderate",3,IF(J159="Major",4,IF(J159="Critical",5,""))))),"") -> 4 | L159: =IF(OR(I159="",K159=""),"",I159*K159) -> 8 | M159: 1. Training of staff and managers on SRR 2.Timely resolution of grievances 3. Conduct awareness campaigns and onboarding sessions covering grievance channels. 4. Empower whistleblower protection protocols and communicate these policies widely. | Q159: Head of HR Senior Management OIO | U159: =IF(L159="","",IF(L159<=4,"Low",IF(L159<=9,"Medium",IF(L159<=15,"High","Critical")))) -> Medium | W159: =IF(I159="","",MAX(1,I159-(IF(V159="Limited",1,IF(V159="Partial",2,IF(V159="Substantial",3,IF(V159="Highly Effective",4,0))))))) -> 2 | X159: =IF(K159="","",MAX(1,K159-ROUNDDOWN((IF(V159="Limited",1,IF(V159="Partial",2,IF(V159="Substantial",3,IF(V159="Highly Effective",4,0)))))/2,0))) -> 4 | Y159: =IF(OR(W159="",X159=""),"",W159*X159) -> 8 | Z159: =IF(Y159="","",IF(Y159<=4,"Low",IF(Y159<=9,"Medium",IF(Y159<=15,"High","Critical")))) -> Medium | AA159: =IF(OR(L159="",Y159=""),"",IF(Y159<L159,"Reduced by "&(L159-Y159)&" pts",IF(Y159=L159,"No Change","Increased by "&(Y159-L159)&" pts"))) -> No Change | AB159: =IF(Y159="","",Y159+(ROW()/10000000)) -> 8.0000159
A160: 155 | B160: HR | C160: 7. Data governance and management reporting | D160: Unauthorized access, disclosure, loss of confidential HR data e.g personal information, medical records, payroll details, disciplinary records. Non compliance with data protection laws. | F160: 1. Lack of data access protocols 2. Human error 3. Weak protection of networks and devices/ insufficient data security measures 4. Physical security lapses - lack of proper storage of HR data/ unencrypted data 5,. Lack of proper back up and recovery plans/ outdated software 6. , weak passwords/ | G160: Operational | H160: Almost Certain | I160: =IFERROR(IF(H160="Unlikely",1,IF(H160="Possible",2,IF(H160="Likely",3,IF(H160="Almost Certain",4,IF(H160="Certain",5,""))))),"") -> 4 | J160: Moderate | K160: =IFERROR(IF(J160="Negligible",1,IF(J160="Minor",2,IF(J160="Moderate",3,IF(J160="Major",4,IF(J160="Critical",5,""))))),"") -> 3 | L160: =IF(OR(I160="",K160=""),"",I160*K160) -> 12 | M160: 1. Development of protocols and SOPs 2. Training for staff on HR Data management 3. Creation of back-up for HR records 4. Restriction of access to HR records 5. Provision of secure archive and registry for storage of personnel records | Q160: HR MIS | U160: =IF(L160="","",IF(L160<=4,"Low",IF(L160<=9,"Medium",IF(L160<=15,"High","Critical")))) -> High | W160: =IF(I160="","",MAX(1,I160-(IF(V160="Limited",1,IF(V160="Partial",2,IF(V160="Substantial",3,IF(V160="Highly Effective",4,0))))))) -> 4 | X160: =IF(K160="","",MAX(1,K160-ROUNDDOWN((IF(V160="Limited",1,IF(V160="Partial",2,IF(V160="Substantial",3,IF(V160="Highly Effective",4,0)))))/2,0))) -> 3 | Y160: =IF(OR(W160="",X160=""),"",W160*X160) -> 12 | Z160: =IF(Y160="","",IF(Y160<=4,"Low",IF(Y160<=9,"Medium",IF(Y160<=15,"High","Critical")))) -> High | AA160: =IF(OR(L160="",Y160=""),"",IF(Y160<L160,"Reduced by "&(L160-Y160)&" pts",IF(Y160=L160,"No Change","Increased by "&(Y160-L160)&" pts"))) -> No Change | AB160: =IF(Y160="","",Y160+(ROW()/10000000)) -> 12.000016
A161: 156 | B161: HR | C161: 8. Integrity, compliance, and safeguarding | D161: Discrimination, bullying, harassment affects staff morale and well being. This may lead to reputational damage, decreased productivity,toxic work environment and legal suits. These incidences undermine trust and credibility of the institution. They can undermine the values of the institution. | F161: 1. Lack of policy enforcement 2. Unclear reporting mechanisms 3.Tolerance and silence around inappropriate and unacceptable behavior in the organization 4. Misuse of power by those in positions of authority 5. Lack of investigation 6. Lack of accountability and transparency 7. Absence of Advisory and Disciplinary Boards | G161: Reputational | H161: Likely | I161: =IFERROR(IF(H161="Unlikely",1,IF(H161="Possible",2,IF(H161="Likely",3,IF(H161="Almost Certain",4,IF(H161="Certain",5,""))))),"") -> 3 | J161: Moderate | K161: =IFERROR(IF(J161="Negligible",1,IF(J161="Minor",2,IF(J161="Moderate",3,IF(J161="Major",4,IF(J161="Critical",5,""))))),"") -> 3 | L161: =IF(OR(I161="",K161=""),"",I161*K161) -> 9 | M161: 1. Dissemination of policy and sign-off by Staff 2. Training of staff on the policies 3. Institution of Advisory and Disciplinary Boards 4. Conduct of sensitization campaigns 5. Anonymous hotlines 6. Monitoring of Incident Reports of Discrimination and Harasssment | Q161: HR Senior Leadership | U161: =IF(L161="","",IF(L161<=4,"Low",IF(L161<=9,"Medium",IF(L161<=15,"High","Critical")))) -> Medium | W161: =IF(I161="","",MAX(1,I161-(IF(V161="Limited",1,IF(V161="Partial",2,IF(V161="Substantial",3,IF(V161="Highly Effective",4,0))))))) -> 3 | X161: =IF(K161="","",MAX(1,K161-ROUNDDOWN((IF(V161="Limited",1,IF(V161="Partial",2,IF(V161="Substantial",3,IF(V161="Highly Effective",4,0)))))/2,0))) -> 3 | Y161: =IF(OR(W161="",X161=""),"",W161*X161) -> 9 | Z161: =IF(Y161="","",IF(Y161<=4,"Low",IF(Y161<=9,"Medium",IF(Y161<=15,"High","Critical")))) -> Medium | AA161: =IF(OR(L161="",Y161=""),"",IF(Y161<L161,"Reduced by "&(L161-Y161)&" pts",IF(Y161=L161,"No Change","Increased by "&(Y161-L161)&" pts"))) -> No Change | AB161: =IF(Y161="","",Y161+(ROW()/10000000)) -> 9.0000161
A162: 157 | B162: HR | C162: 2. Workforce sustainability and institutional capability | D162: Lack of proactive succession planning for key roles. This can lead to disruption in operations, loss of institutional memory, hindered strategic initiatives implementation. | F162: 1. Reactive strategic HR workforce planning/ Lack of strategic workforce planning 2. Lack of structured coaching and mentoring initiatives 3. Short contract durations due to funding 4. Lack of capacity building and staff development | G162: Strategic | H162: Likely | I162: =IFERROR(IF(H162="Unlikely",1,IF(H162="Possible",2,IF(H162="Likely",3,IF(H162="Almost Certain",4,IF(H162="Certain",5,""))))),"") -> 3 | J162: Negligible | K162: =IFERROR(IF(J162="Negligible",1,IF(J162="Minor",2,IF(J162="Moderate",3,IF(J162="Major",4,IF(J162="Critical",5,""))))),"") -> 1 | L162: =IF(OR(I162="",K162=""),"",I162*K162) -> 3 | M162: 1. Priroritization of capacity building for staff 2. Development of robust succession planning strategy 3. Leadership, coaching and mentoring training for senior management 4. Use the current data to anticipate future talent needs, skill gaps, and retirement trends. | U162: =IF(L162="","",IF(L162<=4,"Low",IF(L162<=9,"Medium",IF(L162<=15,"High","Critical")))) -> Low | W162: =IF(I162="","",MAX(1,I162-(IF(V162="Limited",1,IF(V162="Partial",2,IF(V162="Substantial",3,IF(V162="Highly Effective",4,0))))))) -> 3 | X162: =IF(K162="","",MAX(1,K162-ROUNDDOWN((IF(V162="Limited",1,IF(V162="Partial",2,IF(V162="Substantial",3,IF(V162="Highly Effective",4,0)))))/2,0))) -> 1 | Y162: =IF(OR(W162="",X162=""),"",W162*X162) -> 3 | Z162: =IF(Y162="","",IF(Y162<=4,"Low",IF(Y162<=9,"Medium",IF(Y162<=15,"High","Critical")))) -> Low | AA162: =IF(OR(L162="",Y162=""),"",IF(Y162<L162,"Reduced by "&(L162-Y162)&" pts",IF(Y162=L162,"No Change","Increased by "&(Y162-L162)&" pts"))) -> No Change | AB162: =IF(Y162="","",Y162+(ROW()/10000000)) -> 3.0000162
A163: 158 | B163: HR | C163: 2. Workforce sustainability and institutional capability | D163: This can lead to staffing gaps which means increased workload for existing staff, reduced productivity and may lead to delays in project implementation. Poor onboarding leads to negative perception by new hires and can lead to high turnover. | E163: Prolonged hiring processes affecting project timelines and organizational effectiveness. | F163: 1. Lengthy recruitment procedures 2. Delays in approvals for reruitment and appointments 3. Lengthy decision making to select staff 4. Lack of proper workforce planning 5. Poor coordination between Technical and HR teams 6. Lack of proper coordination for onboardng sessions 8. The logistical hurdles in preparing for a new hire's arrival | G163: Operational | H163: Likely | I163: =IFERROR(IF(H163="Unlikely",1,IF(H163="Possible",2,IF(H163="Likely",3,IF(H163="Almost Certain",4,IF(H163="Certain",5,""))))),"") -> 3 | J163: Major | K163: =IFERROR(IF(J163="Negligible",1,IF(J163="Minor",2,IF(J163="Moderate",3,IF(J163="Major",4,IF(J163="Critical",5,""))))),"") -> 4 | L163: =IF(OR(I163="",K163=""),"",I163*K163) -> 12 | M163: 1. Streamline hiring procedures, 2. utilize digital end-to-end recruitment tools,covering recruitment and onboarding 3. development of SOPs with clear timelines for stalkholders in the recruitment process 4. adherence to onboarding SOPs 5. Pre-onboarding coordination with all stakeholders | Q163: HR, Procurement, Finance. Hiring Departments Communications | U163: =IF(L163="","",IF(L163<=4,"Low",IF(L163<=9,"Medium",IF(L163<=15,"High","Critical")))) -> High | W163: =IF(I163="","",MAX(1,I163-(IF(V163="Limited",1,IF(V163="Partial",2,IF(V163="Substantial",3,IF(V163="Highly Effective",4,0))))))) -> 3 | X163: =IF(K163="","",MAX(1,K163-ROUNDDOWN((IF(V163="Limited",1,IF(V163="Partial",2,IF(V163="Substantial",3,IF(V163="Highly Effective",4,0)))))/2,0))) -> 4 | Y163: =IF(OR(W163="",X163=""),"",W163*X163) -> 12 | Z163: =IF(Y163="","",IF(Y163<=4,"Low",IF(Y163<=9,"Medium",IF(Y163<=15,"High","Critical")))) -> High | AA163: =IF(OR(L163="",Y163=""),"",IF(Y163<L163,"Reduced by "&(L163-Y163)&" pts",IF(Y163=L163,"No Change","Increased by "&(Y163-L163)&" pts"))) -> No Change | AB163: =IF(Y163="","",Y163+(ROW()/10000000)) -> 12.000016
A164: 159 | B164: HR | C164: 2. Workforce sustainability and institutional capability | D164: Inability to retain high performing employees is a risk to stability, continuity and performance of the organization. It can lead to implementation disruptions, increased recruitment costs | E164: Difficulty in attracting and retaining qualified personnel due to competitive market conditions or limited local talent pools. | F164: 1. Lack of competitive compensation and benefits packages 2. Limited career growth and development opportunities 3. Job insecurity, short contracts 4. Burnout and stress 5. Lack of meaningful or impactful work 6. Working away from family 7. Lack of talent identification/recognition | G164: Strategic | H164: Possible | I164: =IFERROR(IF(H164="Unlikely",1,IF(H164="Possible",2,IF(H164="Likely",3,IF(H164="Almost Certain",4,IF(H164="Certain",5,""))))),"") -> 2 | J164: Critical | K164: =IFERROR(IF(J164="Negligible",1,IF(J164="Minor",2,IF(J164="Moderate",3,IF(J164="Major",4,IF(J164="Critical",5,""))))),"") -> 5 | L164: =IF(OR(I164="",K164=""),"",I164*K164) -> 10 | M164: 1. Improve work environment, 2. Recognize employee achievements, 3. Establish Career Pathways. | Q164: HR, SMT | U164: =IF(L164="","",IF(L164<=4,"Low",IF(L164<=9,"Medium",IF(L164<=15,"High","Critical")))) -> High | W164: =IF(I164="","",MAX(1,I164-(IF(V164="Limited",1,IF(V164="Partial",2,IF(V164="Substantial",3,IF(V164="Highly Effective",4,0))))))) -> 2 | X164: =IF(K164="","",MAX(1,K164-ROUNDDOWN((IF(V164="Limited",1,IF(V164="Partial",2,IF(V164="Substantial",3,IF(V164="Highly Effective",4,0)))))/2,0))) -> 5 | Y164: =IF(OR(W164="",X164=""),"",W164*X164) -> 10 | Z164: =IF(Y164="","",IF(Y164<=4,"Low",IF(Y164<=9,"Medium",IF(Y164<=15,"High","Critical")))) -> High | AA164: =IF(OR(L164="",Y164=""),"",IF(Y164<L164,"Reduced by "&(L164-Y164)&" pts",IF(Y164=L164,"No Change","Increased by "&(Y164-L164)&" pts"))) -> No Change | AB164: =IF(Y164="","",Y164+(ROW()/10000000)) -> 10.000016
A165: 160 | B165: HR | C165: 2. Workforce sustainability and institutional capability | D165: Failure to provide adequate, relevant, and continuous training and professional development opportunities can result in skill gaps, reduced staff performance, low morale, and limited organizational capacity to adapt to changing needs and technologies. Lack of investment in staff development may also contribute to poor retention and a disengaged workforce. | E165: Skills gaps that hinder performance and organizational growth. | F165: 1. Budget constraints/Limited resources 2. Lack of strategic planning and prioritization 3. Reactive learning approach/ Lack of Baseline to understand the training needs/TNA 4. Lack of sensitization on available training opportunities/ insufficient leadership support | G165: Strategic | H165: Almost Certain | I165: =IFERROR(IF(H165="Unlikely",1,IF(H165="Possible",2,IF(H165="Likely",3,IF(H165="Almost Certain",4,IF(H165="Certain",5,""))))),"") -> 4 | J165: Critical | K165: =IFERROR(IF(J165="Negligible",1,IF(J165="Minor",2,IF(J165="Moderate",3,IF(J165="Major",4,IF(J165="Critical",5,""))))),"") -> 5 | L165: =IF(OR(I165="",K165=""),"",I165*K165) -> 20 | M165: 1. Allocation of sufficient budget for Learning and Development 2. Develop continuous professional development, 3. create personalized training plans, 4. leverage on e-learning platforms 5. Conduct a Training Needs Assessment | Q165: HR, HoD, Leadership | U165: =IF(L165="","",IF(L165<=4,"Low",IF(L165<=9,"Medium",IF(L165<=15,"High","Critical")))) -> Critical | W165: =IF(I165="","",MAX(1,I165-(IF(V165="Limited",1,IF(V165="Partial",2,IF(V165="Substantial",3,IF(V165="Highly Effective",4,0))))))) -> 4 | X165: =IF(K165="","",MAX(1,K165-ROUNDDOWN((IF(V165="Limited",1,IF(V165="Partial",2,IF(V165="Substantial",3,IF(V165="Highly Effective",4,0)))))/2,0))) -> 5 | Y165: =IF(OR(W165="",X165=""),"",W165*X165) -> 20 | Z165: =IF(Y165="","",IF(Y165<=4,"Low",IF(Y165<=9,"Medium",IF(Y165<=15,"High","Critical")))) -> Critical | AA165: =IF(OR(L165="",Y165=""),"",IF(Y165<L165,"Reduced by "&(L165-Y165)&" pts",IF(Y165=L165,"No Change","Increased by "&(Y165-L165)&" pts"))) -> No Change | AB165: =IF(Y165="","",Y165+(ROW()/10000000)) -> 20.000017
A166: 161 | B166: HR | C166: 2. Workforce sustainability and institutional capability | D166: Failure to prioritize employee well being can lead to brunout, reduced moreale, increased absenteeism due to illness, high turnover. This can contribute to toxic work culrture and reuptational risk | E166: Overwork or job dissatisfaction leading to absenteeism or decreased productivity. | F166: 1. Excessive workload and unrealistic expectations/ unclear expectations 2. Lack of work life balance/ poor work-life balance 3. Lack of access to employee assistance program/ inadequate support 4. Micromanagement, lack of empathy by supervisors 5. Lack of leave utilization tracking and enforcement 6. High stress working environments, emergency response situations/ ultimately impacting physical and mental health 7. lack of recognition 8. Unclear direction or instructions on policy change | G166: Operational | H166: Likely | I166: =IFERROR(IF(H166="Unlikely",1,IF(H166="Possible",2,IF(H166="Likely",3,IF(H166="Almost Certain",4,IF(H166="Certain",5,""))))),"") -> 3 | J166: Moderate | K166: =IFERROR(IF(J166="Negligible",1,IF(J166="Minor",2,IF(J166="Moderate",3,IF(J166="Major",4,IF(J166="Critical",5,""))))),"") -> 3 | L166: =IF(OR(I166="",K166=""),"",I166*K166) -> 9 | M166: 1. Promote work-life balance initiatives, 2. provide mental health support, 3. monitor workload distribution to prevent burnout, 4. Conduct regular employee engagement surveys. 5. Segregation of duties 6. Implementation of realistic workplans and performance targets/goals 7. Compensatory Time Off 8. R&R during Emergencies | Q166: HR, Senior Leadership | U166: =IF(L166="","",IF(L166<=4,"Low",IF(L166<=9,"Medium",IF(L166<=15,"High","Critical")))) -> Medium | W166: =IF(I166="","",MAX(1,I166-(IF(V166="Limited",1,IF(V166="Partial",2,IF(V166="Substantial",3,IF(V166="Highly Effective",4,0))))))) -> 3 | X166: =IF(K166="","",MAX(1,K166-ROUNDDOWN((IF(V166="Limited",1,IF(V166="Partial",2,IF(V166="Substantial",3,IF(V166="Highly Effective",4,0)))))/2,0))) -> 3 | Y166: =IF(OR(W166="",X166=""),"",W166*X166) -> 9 | Z166: =IF(Y166="","",IF(Y166<=4,"Low",IF(Y166<=9,"Medium",IF(Y166<=15,"High","Critical")))) -> Medium | AA166: =IF(OR(L166="",Y166=""),"",IF(Y166<L166,"Reduced by "&(L166-Y166)&" pts",IF(Y166=L166,"No Change","Increased by "&(Y166-L166)&" pts"))) -> No Change | AB166: =IF(Y166="","",Y166+(ROW()/10000000)) -> 9.0000166
A167: 162 | B167: HR | C167: 9. Emergency readiness, duty of care, and biosafety/biosecurity | D167: Unforseen disruptions due to strikes, pandemics, natural disasters, health crisis can affect continuity and delivery. | E167: Impact of unforeseen events such as pandemics, political instability, or natural disasters on staffing | F167: 1. Public health emergencies 2. Natural disasters 3. Political instability 4. Security threats 5. ICT system failures/cyberattacks 6. funding cuts eg USAID | G167: Environmental | H167: Likely | I167: =IFERROR(IF(H167="Unlikely",1,IF(H167="Possible",2,IF(H167="Likely",3,IF(H167="Almost Certain",4,IF(H167="Certain",5,""))))),"") -> 3 | J167: Moderate | K167: =IFERROR(IF(J167="Negligible",1,IF(J167="Minor",2,IF(J167="Moderate",3,IF(J167="Major",4,IF(J167="Critical",5,""))))),"") -> 3 | L167: =IF(OR(I167="",K167=""),"",I167*K167) -> 9 | M167: 1. Develop flexible work arrangements, 2. Develop a business continuity plan, 3. Foster a resilient organizational culture | Q167: HR, Senior Leadership | U167: =IF(L167="","",IF(L167<=4,"Low",IF(L167<=9,"Medium",IF(L167<=15,"High","Critical")))) -> Medium | W167: =IF(I167="","",MAX(1,I167-(IF(V167="Limited",1,IF(V167="Partial",2,IF(V167="Substantial",3,IF(V167="Highly Effective",4,0))))))) -> 3 | X167: =IF(K167="","",MAX(1,K167-ROUNDDOWN((IF(V167="Limited",1,IF(V167="Partial",2,IF(V167="Substantial",3,IF(V167="Highly Effective",4,0)))))/2,0))) -> 3 | Y167: =IF(OR(W167="",X167=""),"",W167*X167) -> 9 | Z167: =IF(Y167="","",IF(Y167<=4,"Low",IF(Y167<=9,"Medium",IF(Y167<=15,"High","Critical")))) -> Medium | AA167: =IF(OR(L167="",Y167=""),"",IF(Y167<L167,"Reduced by "&(L167-Y167)&" pts",IF(Y167=L167,"No Change","Increased by "&(Y167-L167)&" pts"))) -> No Change | AB167: =IF(Y167="","",Y167+(ROW()/10000000)) -> 9.0000167
A168: 163 | B168: HR | C168: 8. Integrity, compliance, and safeguarding | D168: Lack of diversity and inclusion can lead to unequal opportunities, discrimination, reduced staff engagement. | E168: Risks related to unfair practices or lack of representation affecting organizational culture Challenges in effective communication within a diverse workforce. | F168: 1. Bias in recruitment and promotion 2. Lack of diversity and inclusion policy 3. inadequate training 4. lack of data for decision making | G168: Contextual | H168: Certain | I168: =IFERROR(IF(H168="Unlikely",1,IF(H168="Possible",2,IF(H168="Likely",3,IF(H168="Almost Certain",4,IF(H168="Certain",5,""))))),"") -> 5 | J168: Moderate | K168: =IFERROR(IF(J168="Negligible",1,IF(J168="Minor",2,IF(J168="Moderate",3,IF(J168="Major",4,IF(J168="Critical",5,""))))),"") -> 3 | L168: =IF(OR(I168="",K168=""),"",I168*K168) -> 15 | M168: 1. Implement inclusive hiring policies and practices, 2. Diversity training, and 3. Establish policies that promote equity and a culture of respect and fairness. | Q168: HR, Senior Leadership | U168: =IF(L168="","",IF(L168<=4,"Low",IF(L168<=9,"Medium",IF(L168<=15,"High","Critical")))) -> High | W168: =IF(I168="","",MAX(1,I168-(IF(V168="Limited",1,IF(V168="Partial",2,IF(V168="Substantial",3,IF(V168="Highly Effective",4,0))))))) -> 5 | X168: =IF(K168="","",MAX(1,K168-ROUNDDOWN((IF(V168="Limited",1,IF(V168="Partial",2,IF(V168="Substantial",3,IF(V168="Highly Effective",4,0)))))/2,0))) -> 3 | Y168: =IF(OR(W168="",X168=""),"",W168*X168) -> 15 | Z168: =IF(Y168="","",IF(Y168<=4,"Low",IF(Y168<=9,"Medium",IF(Y168<=15,"High","Critical")))) -> High | AA168: =IF(OR(L168="",Y168=""),"",IF(Y168<L168,"Reduced by "&(L168-Y168)&" pts",IF(Y168=L168,"No Change","Increased by "&(Y168-L168)&" pts"))) -> No Change | AB168: =IF(Y168="","",Y168+(ROW()/10000000)) -> 15.000017
A169: 164 | B169: HR | C169: 2. Workforce sustainability and institutional capability | D169: Significant delay in the annual appraisal of staff members | E169: Reduced staff motivation and morale Inaccurate or outdated performance data for decision-making Delayed promotions, rewards, or contract renewals Perception of unfairness and weakened accountability culture Reduced organizational performance and productivity | F169: Lack of clear appraisal timelines or enforcement of deadlines Competing priorities and workload pressures on supervisors Limited HR monitoring or follow-up mechanisms Inadequate training of supervisors on performance management Delays in cascading performance objectives from management | G169: Operational | H169: Certain | I169: =IFERROR(IF(H169="Unlikely",1,IF(H169="Possible",2,IF(H169="Likely",3,IF(H169="Almost Certain",4,IF(H169="Certain",5,""))))),"") -> 5 | J169: Moderate | K169: =IFERROR(IF(J169="Negligible",1,IF(J169="Minor",2,IF(J169="Moderate",3,IF(J169="Major",4,IF(J169="Critical",5,""))))),"") -> 3 | L169: =IF(OR(I169="",K169=""),"",I169*K169) -> 15 | M169: Enforce strict annual appraisal timelines with reminders and escalation mechanisms Automate appraisal process through HRMIS or digital tools Provide training for supervisors on timely performance evaluation Conduct mid-year reviews to avoid end-year bottlenecks HR to monitor and report compliance to senior management quarterly | Q169: HR, Senior Leadership | U169: =IF(L169="","",IF(L169<=4,"Low",IF(L169<=9,"Medium",IF(L169<=15,"High","Critical")))) -> High | W169: =IF(I169="","",MAX(1,I169-(IF(V169="Limited",1,IF(V169="Partial",2,IF(V169="Substantial",3,IF(V169="Highly Effective",4,0))))))) -> 5 | X169: =IF(K169="","",MAX(1,K169-ROUNDDOWN((IF(V169="Limited",1,IF(V169="Partial",2,IF(V169="Substantial",3,IF(V169="Highly Effective",4,0)))))/2,0))) -> 3 | Y169: =IF(OR(W169="",X169=""),"",W169*X169) -> 15 | Z169: =IF(Y169="","",IF(Y169<=4,"Low",IF(Y169<=9,"Medium",IF(Y169<=15,"High","Critical")))) -> High | AA169: =IF(OR(L169="",Y169=""),"",IF(Y169<L169,"Reduced by "&(L169-Y169)&" pts",IF(Y169=L169,"No Change","Increased by "&(Y169-L169)&" pts"))) -> No Change | AB169: =IF(Y169="","",Y169+(ROW()/10000000)) -> 15.000017
A170: 165 | B170: SDI | C170: 5. Country, partner, and geopolitical context | D170: Delayed response and activity adjustments by Member States | E170: 🔴Disrupted implementation schedules; which impacts on project timelines & coordination | F170: Lack of effective communication strategy between the Member States and Africa CDC Delayed approval of funded workplans, which leads to delayed communication with the Member States Long beuractratic administrative processes which lead to delayed comfirmations. Conflicting priorities of the MemberStates. | G170: Operational | H170: Likely | I170: =IFERROR(IF(H170="Unlikely",1,IF(H170="Possible",2,IF(H170="Likely",3,IF(H170="Almost Certain",4,IF(H170="Certain",5,""))))),"") -> 3 | J170: Major | K170: =IFERROR(IF(J170="Negligible",1,IF(J170="Minor",2,IF(J170="Moderate",3,IF(J170="Major",4,IF(J170="Critical",5,""))))),"") -> 4 | L170: =IF(OR(I170="",K170=""),"",I170*K170) -> 12 | M170: 1. Strengthen early engagement and communication via regional focal points; 2. Develop proactive coordination mechanisms, and regular follow ups | Q170: Head of Units Head of Division Technical staff | U170: =IF(L170="","",IF(L170<=4,"Low",IF(L170<=9,"Medium",IF(L170<=15,"High","Critical")))) -> High | W170: =IF(I170="","",MAX(1,I170-(IF(V170="Limited",1,IF(V170="Partial",2,IF(V170="Substantial",3,IF(V170="Highly Effective",4,0))))))) -> 3 | X170: =IF(K170="","",MAX(1,K170-ROUNDDOWN((IF(V170="Limited",1,IF(V170="Partial",2,IF(V170="Substantial",3,IF(V170="Highly Effective",4,0)))))/2,0))) -> 4 | Y170: =IF(OR(W170="",X170=""),"",W170*X170) -> 12 | Z170: =IF(Y170="","",IF(Y170<=4,"Low",IF(Y170<=9,"Medium",IF(Y170<=15,"High","Critical")))) -> High | AA170: =IF(OR(L170="",Y170=""),"",IF(Y170<L170,"Reduced by "&(L170-Y170)&" pts",IF(Y170=L170,"No Change","Increased by "&(Y170-L170)&" pts"))) -> No Change | AB170: =IF(Y170="","",Y170+(ROW()/10000000)) -> 12.000017
